Workbook

Sheet Оплата Завод
B1: =SUBTOTAL(9,ОплатаЗавод[Сумма]) -> 2101088520
A2: Дата | B2: Сумма | C2: Платеелшик | D2: Получател
A3: 46198 | B3: 45570000 | C3: Септем Алока | D3: "CAOLS KS" MCHJ
A4: 46198 | B4: 23328000 | C4: Септем Алока | D4: "CAOLS KS" MCHJ
A5: 46202 | B5: 24624000 | C5: Септем Алока | D5: "CAOLS KS" MCHJ
A6: 46202 | B6: 23965000 | C6: Септем Алока | D6: "CAOLS KS" MCHJ
A7: 46202 | B7: 47952000 | C7: Септем Алока | D7: "CAOLS KS" MCHJ
A8: 46203 | B8: 50000000 | C8: Септем Алока | D8: "CAOLS KS" MCHJ
A9: 46203 | B9: 23872000 | C9: Септем Алока | D9: "CAOLS KS" MCHJ
A10: 46203 | B10: 22703000 | C10: Септем Алока | D10: "CAOLS KS" MCHJ
A11: 46204 | B11: 25231000 | C11: Септем Алока | D11: "CAOLS KS" MCHJ
A12: 46205 | B12: 67737600 | C12: Септем Алока | D12: "CAOLS KS" MCHJ
A13: 46205 | B13: 72394560 | C13: Септем Алока | D13: "CAOLS KS" MCHJ
A14: 46205 | B14: 73872000 | C14: Септем Алока | D14: "CAOLS KS" MCHJ
... A19: 46206 | B19: 50000000 | C19: Септем Алока | D19: "CAOLS KS" MCHJ
A20: 46206 | B20: 6000000 | C20: Нахт
A21: 46210 | B21: 50000000 | C21: Нахт пластика | D21: 9.8601901e+15

Sheet Свод Завод
A1: Сумма Товар | B1: =Товар!J2 -> 1647154250 | D1: =Товар!M2 -> 211900000
A2: Сумма Товар с паддон | B2: =Товар!N2 -> 1859054250 | D2: =B3-B1 -> 453934270
A3: Сумма Оплата Завод | B3: ='Оплата Завод'!B1 -> 2101088520
A4: Завод Остаток | B4: =B3-B2 -> 242034270 | D4: 1 | E4: Жамол | K4: 2 | L4: Арслон ога | R4: 3 | S4: Зафар ога | Y4: S | Z4: Шохрух ога
A5: Завод Остаток без паддон | B5: =D2 -> 453934270 | E5: =SUM(E7:E12) -> 4.1963016e+08 | F5: =SUM(F7:F12) -> 372450160 | G5: =SUM(G7:G12) -> -47180000 | H5: =SUM(H7:H12) -> 339 | L5: =SUM(L7:L11) -> 121824000 | M5: =SUM(M7:M11) -> 207906400 | N5: =SUM(N7:N11) -> 86082400 | O5: =SUM(O7:O12) -> 94 | S5: =SUM(S7:S11) -> 516136320 | T5: =SUM(T7:T11) -> 524219920 | U5: =SUM(U7:U11) -> 8083600 | V5: =SUM(V7:V13) -> 417 | Z5: =SUM(Z7:Z11) -> 1.1983444e+08 | AA5: =SUM(AA7:AA11) -> 119834440 | AB5: =SUM(AB7:AB11) -> 0.6208 | AC5: =SUM(AC7:AC14) -> 95
D6: Клиенты | E6: Товар | F6: Оплата | G6: Остаток | H6: Остаток Паддон | I6: Клент шопрга барди: | K6: Клиенты | L6: Товар | M6: Оплата | N6: Остаток | O6: Остаток Паддон | P6: Клент шопрга барди: | R6: Клиенты | S6: Товар | T6: Оплата | U6: Остаток | V6: Остаток Паддон | W6: Клент шопрга барди: | Y6: Клиенты | Z6: Товар | AA6: Оплата | AB6: Остаток | AC6: Остаток Паддон | AD6: Клент шопрга барди:
A7: остаток паддон: | B7: =(-1)*(H5+O5+V5+AC5) -> -945 | D7: ='1-Урганч Тамирлаш'!D1 -> 1-Урганч Тамирлаш | E7: ='1-Урганч Тамирлаш'!M5 -> 1.374996e+08 | F7: ='1-Урганч Тамирлаш'!C5 -> 130570000 | G7: ='1-Урганч Тамирлаш'!F2 -> -6929600 | H7: ='1-Урганч Тамирлаш'!K5-'1-Урганч Тамирлаш'!E5 -> 112 | I7: ='1-Урганч Тамирлаш'!I1 -> 0 | K7: ='2-Гофур Хазорасп'!D1 -> 2-Гофур Хазорасп | L7: ='2-Гофур Хазорасп'!M5 -> 121824000 | M7: ='2-Гофур Хазорасп'!C5 -> 121824000 | N7: ='2-Гофур Хазорасп'!F2 -> 0 | O7: ='2-Гофур Хазорасп'!K5-'2-Гофур Хазорасп'!E5 -> 94 | P7: ='2-Гофур Хазорасп'!I1 -> 0 | R7: ='3-Сулаймон Ога Хазарасп'!D1 -> 3-Сулаймон Ога Хазарасп | S7: ='3-Сулаймон Ога Хазарасп'!M5 -> 399254400 | T7: ='3-Сулаймон Ога Хазарасп'!C5 -> 366373200 | U7: ='3-Сулаймон Ога Хазарасп'!F2 -> -32881200 | V7: ='3-Сулаймон Ога Хазарасп'!K5-'3-Сулаймон Ога Хазарасп'!E5 -> 322 | W7: ='3-Сулаймон Ога Хазарасп'!I1 -> 25900000 | Y7: ='4-Гайрат Штб'!D1 -> 4-Гайрат Штб | Z7: ='4-Гайрат Штб'!M5 -> 49904640 | AA7: ='4-Гайрат Штб'!C5 -> 49904640 | AB7: ='4-Гайрат Штб'!F2 -> 0 | AC7: ='4-Гайрат Штб'!K5-'4-Гайрат Штб'!E5 -> 38 | AD7: ='4-Гайрат Штб'!I1 -> 0
A8: Жами остстка: | B8: =G5+N5+U5+AB5+G16 -> 68221001 | D8: ='1-Инвест Холдинг'!D1 -> 1-Инвест Холдинг | E8: ='1-Инвест Холдинг'!M5 -> 67737600 | F8: ='1-Инвест Холдинг'!C5 -> 67737600 | G8: ='1-Инвест Холдинг'!F2 -> 0 | H8: ='1-Инвест Холдинг'!K5-'1-Инвест Холдинг'!E5 -> 56 | I8: ='1-Инвест Холдинг'!I1 -> 0 | K8: ='2-Шиддат маналит'!D1 -> 2-Шиддат маналит | L8: ='2-Шиддат маналит'!M5 -> 0 | M8: ='2-Шиддат маналит'!C5 -> 86082400 | N8: ='2-Шиддат маналит'!F2 -> 86082400 | O8: ='2-Шиддат маналит'!K5-'2-Шиддат маналит'!E5 -> 0 | P8: ='2-Шиддат маналит'!I1 -> 0 | R8: ='3-Мурод ога Урганч'!D1 -> 3-Мурод ога Урганч | S8: ='3-Мурод ога Урганч'!M5 -> 47934720 | T8: ='3-Мурод ога Урганч'!C5 -> 47934720 | U8: ='3-Мурод ога Урганч'!F2 -> 0 | V8: ='3-Мурод ога Урганч'!K5-'3-Мурод ога Урганч'!E5 -> 38 | W8: ='3-Мурод ога Урганч'!I1 -> 0 | Y8: ='4-Рустам Шпик'!D1 -> 4-Рустам Шпик | Z8: ='4-Рустам Шпик'!M5 -> 69929799 | AA8: ='4-Рустам Шпик'!C5 -> 69929800 | AB8: ='4-Рустам Шпик'!F2 -> 0.6208 | AC8: ='4-Рустам Шпик'!K5-'4-Рустам Шпик'!E5 -> 57 | AD8: ='4-Рустам Шпик'!I1 -> 4000000
A9: =E4 -> Жамол | B9: =G5 -> -47180000 | D9: ='1-Нормат Умидбек'!D1 -> 1-Нормат Умидбек | E9: ='1-Нормат Умидбек'!M5 -> 72394560 | F9: ='1-Нормат Умидбек'!C5 -> 72394560 | G9: ='1-Нормат Умидбек'!F2 -> 0 | H9: ='1-Нормат Умидбек'!K5-'1-Нормат Умидбек'!E5 -> 57 | I9: ='1-Нормат Умидбек'!I1 -> 0 | R9: ='3-Сарвар ога Шовот'!D1 -> 3-Сарвар ога Шовот | S9: ='3-Сарвар ога Шовот'!M5 -> 68947200 | T9: ='3-Сарвар ога Шовот'!C5 -> 68947200 | U9: ='3-Сарвар ога Шовот'!F2 -> 0 | V9: ='3-Сарвар ога Шовот'!K5-'3-Сарвар ога Шовот'!E5 -> 57 | W9: ='3-Сарвар ога Шовот'!I1 -> 2000000 | Y9: ='4-Элликкала Бостон'!D1 -> 4-Элликкала Бостон
A10: =L4 -> Арслон ога | B10: =N5 -> 86082400 | D10: ='1-Фидато Груп'!D1 -> 1-Фидато Груп | E10: ='1-Фидато Груп'!M5 -> 93899520 | F10: ='1-Фидато Груп'!C5 -> 68916000 | G10: ='1-Фидато Груп'!F2 -> -24983520 | H10: ='1-Фидато Груп'!K5-'1-Фидато Груп'!E5 -> 76 | I10: ='1-Фидато Груп'!I1 -> 0 | R10: 3-Уктир ога Шовот | S10: ='3-Уктир ога Шовот'!M5 -> 0 | T10: ='3-Уктир ога Шовот'!C5 -> 40964800 | U10: ='3-Уктир ога Шовот'!F2 -> 40964800 | V10: ='3-Уктир ога Шовот'!K5-'3-Уктир ога Шовот'!E5 -> 0 | W10: ='3-Уктир ога Шовот'!I1 -> 0
A11: =S4 -> Зафар ога | B11: =U5 -> 8083600 | D11: ='1-Ирригатсия темир бетон'!D1 -> 1-Ирригатсия темир бетон | E11: ='1-Ирригатсия темир бетон'!M5 -> 24131520 | F11: ='1-Ирригатсия темир бетон'!C5 -> 32832000 | G11: ='1-Ирригатсия темир бетон'!F2 -> 8700480 | H11: ='1-Ирригатсия темир бетон'!K5-'1-Ирригатсия темир бетон'!E5 -> 19 | I11: ='1-Ирригатсия темир бетон'!I1 -> 0
A12: =Z4 -> Шохрух ога | B12: =AB5 -> 0.6208 | D12: ='1-Хонкага'!D1 -> 1-Хонкага | E12: ='1-Хонкага'!M5 -> 23967360 | F12: ='1-Хонкага'!C5 -> 0 | G12: ='1-Хонкага'!F2 -> -23967360 | H12: ='1-Хонкага'!K5-'1-Хонкага'!E5 -> 19 | I12: ='1-Хонкага'!I1 -> 0
D15: 5 | E15: Темур | K15: 5 | L15: Сардор ога
E16: =SUM(E18:E23) -> 367718400 | F16: =SUM(F18:F23) -> 388953400 | G16: =SUM(G18:G23) -> 21235000 | H16: =SUM(H18:H23) -> 304 | L16: =SUM(L18:L23) -> 156038400 | M16: =SUM(M18:M23) -> 202314800 | N16: =SUM(N18:N23) -> 46276400 | O16: =SUM(O18:O23) -> 129
A17: Клентларга тушилган ПУЛ | B17: =SUM(F5+M5+T5+AA5+F16+M16) -> 1815679120 | D17: Клиенты | E17: Товар | F17: Оплата | G17: Остаток | H17: Остаток Паддон | I17: Клент шопрга барди: | K17: Клиенты | L17: Товар | M17: Оплата | N17: Остаток | O17: Остаток Паддон | P17: Клент шопрга барди:
A18: Клентлар шопрга | B18: =SUM(I7:I14,I18:I24,P7:P12,W7:W12,AD7:AD12) -> 65600000 | D18: ='5-Жаср Версал'!D1 -> 5-Жасур Версал | E18: ='5-Жаср Версал'!M5 -> 206841600 | F18: ='5-Жаср Версал'!C5 -> 206841600 | G18: ='5-Жаср Версал'!F2 -> 0 | H18: ='5-Жаср Версал'!K5-'5-Жаср Версал'!E5 -> 171 | I18: ='5-Жаср Версал'!I1 -> 18600000 | K18: ='6-Уткир мини'!D1 -> 6-Уткир мини | L18: ='6-Уткир мини'!M5 -> 45964800 | M18: ='6-Уткир мини'!C5 -> 45964800 | N18: ='6-Уткир мини'!F2 -> 0 | O18: ='6-Уткир мини'!K5-'6-Уткир мини'!E5 -> 38 | P18: ='6-Уткир мини'!I1 -> 4000000
A19: Оплата лист | B19: =Оплата!R3 -> 1509053920 | D19: ='5-Мустафо машал'!D1 -> 5-Мустафо машал | E19: ='5-Мустафо машал'!M5 -> 45964800 | F19: ='5-Мустафо машал'!C5 -> 67200000 | G19: ='5-Мустафо машал'!F2 -> 21235200 | H19: ='5-Мустафо машал'!K5-'5-Мустафо машал'!E5 -> 38 | I19: ='5-Мустафо машал'!I1 -> 4200000 | K19: 6-Отабек дамирчи | L19: ='6-Отабек дамирчи'!M5 -> 45964800 | M19: ='6-Отабек дамирчи'!C5 -> 49700000 | N19: ='6-Отабек дамирчи'!F2 -> 3735200 | O19: ='6-Отабек дамирчи'!K5-'6-Отабек дамирчи'!E5 -> 38 | P19: ='6-Отабек дамирчи'!I1 -> 4700000
A20: фарк | B20: =B19-B17+B18 -> -241025200 | D20: ='5-Одилбек Ера хоус'!D1 -> 5-Одилбек Ера хоус | E20: ='5-Одилбек Ера хоус'!M5 -> 91929600 | F20: ='5-Одилбек Ера хоус'!C5 -> 91929800 | G20: ='5-Одилбек Ера хоус'!F2 -> 200 | H20: ='5-Одилбек Ера хоус'!K5-'5-Одилбек Ера хоус'!E5 -> 76 | I20: ='5-Одилбек Ера хоус'!I1 -> 8600000 | K20: 6-Мамун Университети | L20: ='6-Мамун Университети'!M5 -> 45964800 | M20: ='6-Мамун Университети'!C5 -> 104400000 | N20: ='6-Мамун Университети'!F2 -> 58435200 | O20: ='6-Мамун Университети'!K5-'6-Мамун Университети'!E5 -> 38 | P20: ='6-Мамун Университети'!I1 -> 4400000
D21: 5-Журат ога хонка | E21: ='5-Журат ога хонка'!M5 -> 22982400 | F21: ='5-Журат ога хонка'!C5 -> 22982000 | G21: ='5-Журат ога хонка'!F2 -> -400 | H21: ='5-Журат ога хонка'!K5-'5-Журат ога хонка'!E5 -> 19 | I21: ='5-Журат ога хонка'!I1 -> 2300000 | K21: 6-накд клент | L21: ='6-накд клент'!M5 -> 18144000 | M21: ='6-накд клент'!C5 -> 2250000 | N21: ='6-накд клент'!F2 -> -15894000 | O21: ='6-накд клент'!K5-'6-накд клент'!E5 -> 15 | P21: ='6-накд клент'!I1 -> 2250000
A23: Клентларга тушилган ТОВАР | B23: =E5+L5+S5+Z5+E16 -> 1.5451433e+09
A24: Товар лист | B24: =Товар!R2 -> 2.0066575e+09
A25: фарк | B25: =B24-B23 -> 461514200

Sheet Оплата
R3: =SUBTOTAL(9,Таблица15[Жами сумма]) -> 1509053920
A4: Дата | B4: Агент | C4: Клиент | D4: ПР-Сумма | E4: Плателщик | F4: Накд | G4: -5 | H4: -10 | I4: -15 | J4: -20 | K4: -50 | L4: Клик | M4: Терминал | N4: $ | O4: Курс | P4: Сумма | Q4: Прочие | R4: Жами сумма | S4: Получател | T4: Изох
A5: 46198 | B5: Жамол 22-22 | C5: Урганч Тамирлаш | D5: 45570000 | E5: URGANCH TAMIRLASH | P5: 0 | R5: =SUM(Таблица15[[#This Row],[ПР-Сумма]],Таблица15[[#This Row],[Сумма]],Таблица15[[#This Row],[Прочие]]) -> 45570000
A6: 46198 | B6: Зафар ога | C6: Сулаймон Ога Хазарасп | D6: 23328000 | E6: HAZORASP MUHAMMAD | P6: 0 | R6: =SUM(Таблица15[[#This Row],[ПР-Сумма]],Таблица15[[#This Row],[Сумма]],Таблица15[[#This Row],[Прочие]]) -> 23328000
A7: 46202 | B7: Зафар ога | C7: Сулаймон Ога Хазарасп | D7: 24624000 | E7: "A-SIA HOUSE" MCHJ | P7: 0 | R7: =SUM(Таблица15[[#This Row],[ПР-Сумма]],Таблица15[[#This Row],[Сумма]],Таблица15[[#This Row],[Прочие]]) -> 24624000
A8: 46202 | B8: Шохрух ога | C8: Рустам Шпик | D8: 23965000 | E8: "Ифтихор" хусусий корхонаси | P8: 0 | R8: =SUM(Таблица15[[#This Row],[ПР-Сумма]],Таблица15[[#This Row],[Сумма]],Таблица15[[#This Row],[Прочие]]) -> 23965000
A9: 46202 | B9: Арслон ога | C9: Гофур хазорасп | D9: 47952000 | E9: "EZVIZ CITY"Mchj | P9: 0 | R9: =SUM(Таблица15[[#This Row],[ПР-Сумма]],Таблица15[[#This Row],[Сумма]],Таблица15[[#This Row],[Прочие]]) -> 47952000
A10: 46203 | B10: Арслон ога | C10: Сулаймон Ога Хазарасп | D10: 73872000 | E10: Xazorasp Ipoteka Qurilish мчж | P10: 0 | R10: =SUM(Таблица15[[#This Row],[ПР-Сумма]],Таблица15[[#This Row],[Сумма]],Таблица15[[#This Row],[Прочие]]) -> 73872000
A11: 46203 | B11: Жамол 22-22 | C11: Фидато Груп | D11: 22703000 | E11: ООО "FIDATO GROUP" | P11: 0 | R11: =SUM(Таблица15[[#This Row],[ПР-Сумма]],Таблица15[[#This Row],[Сумма]],Таблица15[[#This Row],[Прочие]]) -> 22703000
A12: 46203 | B12: Жамол 22-22 | C12: Фидато Груп | D12: 25231000 | E12: ООО "FIDATO GROUP" | P12: 0 | R12: =SUM(Таблица15[[#This Row],[ПР-Сумма]],Таблица15[[#This Row],[Сумма]],Таблица15[[#This Row],[Прочие]]) -> 25231000
A13: 46205 | B13: Жамол 22-22 | C13: Инвест Холдинг | D13: 67737600 | E13: Хоразм Инвест Холдинг | P13: 0 | R13: =SUM(Таблица15[[#This Row],[ПР-Сумма]],Таблица15[[#This Row],[Сумма]],Таблица15[[#This Row],[Прочие]]) -> 67737600
A14: 46205 | B14: Жамол 22-22 | C14: NORMAT UMIDBEK | D14: 72394560 | E14: NORMAT UMIDBEK MCHJ | P14: 0 | R14: =SUM(Таблица15[[#This Row],[ПР-Сумма]],Таблица15[[#This Row],[Сумма]],Таблица15[[#This Row],[Прочие]]) -> 72394560
A15: 46205 | B15: Жамол 22-22 | C15: Гофур Хазорасп | D15: 73872000 | E15: "DOMEX GROUP" Mchj | P15: 0 | R15: =SUM(Таблица15[[#This Row],[ПР-Сумма]],Таблица15[[#This Row],[Сумма]],Таблица15[[#This Row],[Прочие]]) -> 73872000
A16: 46206 | B16: Зафар ога | C16: Мурод ога Урганч | D16: 47934720 | E16: "Ulgircha savdo diyor" MCHJ | P16: 0 | R16: =SUM(Таблица15[[#This Row],[ПР-Сумма]],Таблица15[[#This Row],[Сумма]],Таблица15[[#This Row],[Прочие]]) -> 47934720
... A25: 46209 | B25: Зафар ога | C25: Сулаймон Ога Хазарасп | D25: 61447200 | E25: HAZORASP BINOKOR USTA MChJ | P25: 0 | R25: =SUM(Таблица15[[#This Row],[ПР-Сумма]],Таблица15[[#This Row],[Сумма]],Таблица15[[#This Row],[Прочие]]) -> 61447200
A26: 46209 | B26: Арслон ога | C26: Шиддат маналит | D26: 2100000 | E26: SHIDDAT MONOLIT MCHJ | P26: 0 | R26: =SUM(Таблица15[[#This Row],[ПР-Сумма]],Таблица15[[#This Row],[Сумма]],Таблица15[[#This Row],[Прочие]]) -> 2100000 | T26: бир машин газаблок даставка учун ташоди
A27: 46209 | B27: Темур | C27: Мустафо машал | D27: 21000000 | E27: "SHUKR BARAKA" MCHJ | P27: 0 | R27: =SUM(Таблица15[[#This Row],[ПР-Сумма]],Таблица15[[#This Row],[Сумма]],Таблица15[[#This Row],[Прочие]]) -> 21000000
A28: 46210 | B28: Сардор ога | C28: Уткир мини | D28: 40000000 | E28: Коровул курилиш монтаж | P28: 0 | R28: =SUM(Таблица15[[#This Row],[ПР-Сумма]],Таблица15[[#This Row],[Сумма]],Таблица15[[#This Row],[Прочие]]) -> 40000000 | S28: Септем семент
A29: 46210 | B29: Шохрух ога | C29: БУНЕДКОР | D29: 41964800 | E29: "БУНЕДКОР" МЧЖ | P29: 0 | R29: =SUM(Таблица15[[#This Row],[ПР-Сумма]],Таблица15[[#This Row],[Сумма]],Таблица15[[#This Row],[Прочие]]) -> 41964800 | S29: Септем семент
A30: 46210 | B30: Зафар ога | C30: Сулаймон ога Хазарасп | D30: 41965000 | E30: HAZORASP MUHAMMAD XO'JA MChJ | P30: 0 | R30: =SUM(Таблица15[[#This Row],[ПР-Сумма]],Таблица15[[#This Row],[Сумма]],Таблица15[[#This Row],[Прочие]]) -> 41965000 | S30: Септем семент
A31: 46211 | B31: Шохрух ога | C31: Жамол 22-22 | D31: 20982000 | E31: ООО "FIDATO GROUP" | P31: 0 | R31: =SUM(Таблица15[[#This Row],[ПР-Сумма]],Таблица15[[#This Row],[Сумма]],Таблица15[[#This Row],[Прочие]]) -> 20982000 | S31: Септем семент
A32: 46211 | B32: Сардор ога | C32: Уткир мини | D32: 1964800 | E32: КОРОВУЛ КУРИЛИШ МОНТАЖ ХК | P32: 0 | R32: =SUM(Таблица15[[#This Row],[ПР-Сумма]],Таблица15[[#This Row],[Сумма]],Таблица15[[#This Row],[Прочие]]) -> 1964800 | S32: Септем семент
A33: 46211 | B33: Шохрух ога | C33: Жамол 22-22 | D33: 32832000 | E33: IRRIGATSIYA TEMIR BETON QURILISH | P33: 0 | R33: =SUM(Таблица15[[#This Row],[ПР-Сумма]],Таблица15[[#This Row],[Сумма]],Таблица15[[#This Row],[Прочие]]) -> 32832000 | S33: Септем семент
A34: 46211 | B34: Арслон ога | C34: шиддат маналит | D34: 63000000 | E34: SHIDDAT MONOLIT MCHJ | P34: 0 | R34: =SUM(Таблица15[[#This Row],[ПР-Сумма]],Таблица15[[#This Row],[Сумма]],Таблица15[[#This Row],[Прочие]]) -> 63000000 | S34: Септем семент
A35: 46212 | B35: Темур ога | C35: Одилбек ера | D35: 41964800 | E35: "ERA MOTOR'S" MCHJ | P35: 0 | R35: =SUM(Таблица15[[#This Row],[ПР-Сумма]],Таблица15[[#This Row],[Сумма]],Таблица15[[#This Row],[Прочие]]) -> 41964800 | S35: Септем семент
A36: 46212 | B36: Темур ога | C36: Мустофо курилиш Машал | D36: 21000000 | E36: ``SHUKR BARAKA``MCHJ | P36: 0 | R36: =SUM(Таблица15[[#This Row],[ПР-Сумма]],Таблица15[[#This Row],[Сумма]],Таблица15[[#This Row],[Прочие]]) -> 21000000 | S36: Септем семент
A37: 46212 | B37: Сардор ога | C37: Отабек дамирчи | D37: 45000000 | E37: "Qodiriy Construction" Масъулияти Чекланган Жамият | P37: 0 | R37: =SUM(Таблица15[[#This Row],[ПР-Сумма]],Таблица15[[#This Row],[Сумма]],Таблица15[[#This Row],[Прочие]]) -> 45000000 | S37: Септем семент
A38: 46212 | B38: Темур ога | C38: Журат ога хонка | D38: 20682000 | E38: "VATANPARVARLIK YOSHLAR KELAJAGI" MCHJ | P38: 0 | R38: =SUM(Таблица15[[#This Row],[ПР-Сумма]],Таблица15[[#This Row],[Сумма]],Таблица15[[#This Row],[Прочие]]) -> 20682000 | S38: Септем семент
A39: 46213 | B39: Зафар ога | C39: Сулаймон ога Хазарасп | D39: 20810000 | E39: OOO QILICH-AMIN-NIYAZ | P39: 0 | R39: =SUM(Таблица15[[#This Row],[ПР-Сумма]],Таблица15[[#This Row],[Сумма]],Таблица15[[#This Row],[Прочие]]) -> 20810000 | S39: Септем семент
... A42: 46213 | B42: Зафар ога | C42: Сулаймон ога Хазарасп | D42: 46620000 | E42: HAZORASP BINOKOR USTA MChJ | P42: 0 | R42: =SUM(Таблица15[[#This Row],[ПР-Сумма]],Таблица15[[#This Row],[Сумма]],Таблица15[[#This Row],[Прочие]]) -> 46620000 | S42: Септем семент
P43: 0 | R43: =SUM(Таблица15[[#This Row],[ПР-Сумма]],Таблица15[[#This Row],[Сумма]],Таблица15[[#This Row],[Прочие]]) -> 0
P44: 0 | R44: =SUM(Таблица15[[#This Row],[ПР-Сумма]],Таблица15[[#This Row],[Сумма]],Таблица15[[#This Row],[Прочие]]) -> 0
P45: 0 | R45: =SUM(Таблица15[[#This Row],[ПР-Сумма]],Таблица15[[#This Row],[Сумма]],Таблица15[[#This Row],[Прочие]]) -> 0
P46: 0 | R46: =SUM(Таблица15[[#This Row],[ПР-Сумма]],Таблица15[[#This Row],[Сумма]],Таблица15[[#This Row],[Прочие]]) -> 0
P47: 0 | R47: =SUM(Таблица15[[#This Row],[ПР-Сумма]],Таблица15[[#This Row],[Сумма]],Таблица15[[#This Row],[Прочие]]) -> 0
P48: 0 | R48: =SUM(Таблица15[[#This Row],[ПР-Сумма]],Таблица15[[#This Row],[Сумма]],Таблица15[[#This Row],[Прочие]]) -> 0
P49: 0 | R49: =SUM(Таблица15[[#This Row],[ПР-Сумма]],Таблица15[[#This Row],[Сумма]],Таблица15[[#This Row],[Прочие]]) -> 0
P50: 0 | R50: =SUM(Таблица15[[#This Row],[ПР-Сумма]],Таблица15[[#This Row],[Сумма]],Таблица15[[#This Row],[Прочие]]) -> 0
P51: 0 | R51: =SUM(Таблица15[[#This Row],[ПР-Сумма]],Таблица15[[#This Row],[Сумма]],Таблица15[[#This Row],[Прочие]]) -> 0
P52: 0 | R52: =SUM(Таблица15[[#This Row],[ПР-Сумма]],Таблица15[[#This Row],[Сумма]],Таблица15[[#This Row],[Прочие]]) -> 0
P53: 0 | R53: =SUM(Таблица15[[#This Row],[ПР-Сумма]],Таблица15[[#This Row],[Сумма]],Таблица15[[#This Row],[Прочие]]) -> 0
P54: 0 | R54: =SUM(Таблица15[[#This Row],[ПР-Сумма]],Таблица15[[#This Row],[Сумма]],Таблица15[[#This Row],[Прочие]]) -> 0
... P498: 0 | R498: =SUM(Таблица15[[#This Row],[ПР-Сумма]],Таблица15[[#This Row],[Сумма]],Таблица15[[#This Row],[Прочие]]) -> 0
R499: =SUM(Таблица15[[#This Row],[ПР-Сумма]],Таблица15[[#This Row],[Сумма]],Таблица15[[#This Row],[Прочие]]) -> 0
R500: =SUM(Таблица15[[#This Row],[ПР-Сумма]],Таблица15[[#This Row],[Сумма]],Таблица15[[#This Row],[Прочие]]) -> 0
R501: =SUM(Таблица15[[#This Row],[ПР-Сумма]],Таблица15[[#This Row],[Сумма]],Таблица15[[#This Row],[Прочие]]) -> 0
R502: =SUM(Таблица15[[#This Row],[ПР-Сумма]],Таблица15[[#This Row],[Сумма]],Таблица15[[#This Row],[Прочие]]) -> 0
R503: =SUM(Таблица15[[#This Row],[ПР-Сумма]],Таблица15[[#This Row],[Сумма]],Таблица15[[#This Row],[Прочие]]) -> 0
R504: =SUM(Таблица15[[#This Row],[ПР-Сумма]],Таблица15[[#This Row],[Сумма]],Таблица15[[#This Row],[Прочие]]) -> 0
R505: =SUM(Таблица15[[#This Row],[ПР-Сумма]],Таблица15[[#This Row],[Сумма]],Таблица15[[#This Row],[Прочие]]) -> 0
R506: =SUM(Таблица15[[#This Row],[ПР-Сумма]],Таблица15[[#This Row],[Сумма]],Таблица15[[#This Row],[Прочие]]) -> 0
R507: =SUM(Таблица15[[#This Row],[ПР-Сумма]],Таблица15[[#This Row],[Сумма]],Таблица15[[#This Row],[Прочие]]) -> 0
R508: =SUM(Таблица15[[#This Row],[ПР-Сумма]],Таблица15[[#This Row],[Сумма]],Таблица15[[#This Row],[Прочие]]) -> 0
R509: =SUM(Таблица15[[#This Row],[ПР-Сумма]],Таблица15[[#This Row],[Сумма]],Таблица15[[#This Row],[Прочие]]) -> 0
R510: =SUM(Таблица15[[#This Row],[ПР-Сумма]],Таблица15[[#This Row],[Сумма]],Таблица15[[#This Row],[Прочие]]) -> 0
... R1049: =SUM(Таблица15[[#This Row],[ПР-Сумма]],Таблица15[[#This Row],[Сумма]],Таблица15[[#This Row],[Прочие]]) -> 0

Sheet Товар
H2: =SUBTOTAL(9,Таблица1[Блок Куб]) -> 2817.578 | J2: =SUBTOTAL(9,Таблица1[Сумма Приход]) -> 1647154250 | K2: =SUBTOTAL(9,Таблица1[Поддон Шт]) -> 1630 | M2: =SUBTOTAL(9,Таблица1[Сумма Поддон]) -> 211900000 | N2: =SUBTOTAL(9,Таблица1[Блок+ Поддон]) -> 1859054250 | R2: =SUBTOTAL(9,Таблица1[Сумма Продажа]) -> 2.0066575e+09 | S2: =SUBTOTAL(9,Таблица1[Расход Авто]) -> 68100000 | T2: =SUBTOTAL(9,Таблица1[Общая прибль]) -> 3.5950327e+08 | W2: =R2-J2 -> 3.5950327e+08
A3: В-о | B3: Поставшик | C3: Агент | D3: Клиент | E3: Дата | F3: № авто | G3: Размер | H3: Блок Куб | I3: Цена Приход | J3: Сумма Приход | K3: Поддон Шт | L3: Цена Поддон | M3: Сумма Поддон | N3: Блок+ Поддон | O3: Цена Продажа | P3: Разница | Q3: ИЗОХ | R3: Сумма Продажа | S3: Расход Авто | T3: Общая прибль | U3: Авто услу барлдми?
A4: 1 | B4: Газоблок | C4: Жамол 22-22 | D4: Урганч Тамирлаш | E4: 46197 | F4: 95 G 851 NA | G4: 600x300x200 | H4: 31.104 | I4: 500000 | J4: =Таблица1[[#This Row],[Блок Куб]]*Таблица1[[#This Row],[Цена Приход]] -> 15552000 | K4: 18 | L4: 130000 | M4: =Таблица1[[#This Row],[Поддон Шт]]*Таблица1[[#This Row],[Цена Поддон]] -> 2340000 | N4: =Таблица1[[#This Row],[Сумма Приход]]+Таблица1[[#This Row],[Сумма Поддон]] -> 17892000 | O4: 732542.44 | P4: =(Таблица1[[#This Row],[Цена Продажа]]+Таблица1[[#This Row],[Цена Поддон]])-Таблица1[[#This Row],[Цена Приход]] -> 362542.44 | Q4: Фойда | R4: =Таблица1[[#This Row],[Блок Куб]]*Таблица1[[#This Row],[Цена Продажа]] -> 22785000 | S4: 2000000 | T4: =Таблица1[[#This Row],[Сумма Продажа]]-Таблица1[[#This Row],[Сумма Приход]] -> 7233000 | U4: Туланди
A5: =A4+1 -> 2 | B5: Газоблок | C5: Жамол 22-22 | D5: Урганч Тамирлаш | E5: 46197 | F5: 40 Y 173 KB | G5: 600x300x200 | H5: 31.104 | I5: 500000 | J5: =Таблица1[[#This Row],[Блок Куб]]*Таблица1[[#This Row],[Цена Приход]] -> 15552000 | K5: 18 | L5: 130000 | M5: =Таблица1[[#This Row],[Поддон Шт]]*Таблица1[[#This Row],[Цена Поддон]] -> 2340000 | N5: =Таблица1[[#This Row],[Сумма Приход]]+Таблица1[[#This Row],[Сумма Поддон]] -> 17892000 | O5: 732542.44 | P5: =(Таблица1[[#This Row],[Цена Продажа]]+Таблица1[[#This Row],[Цена Поддон]])-Таблица1[[#This Row],[Цена Приход]] -> 362542.44 | Q5: Фойда | R5: =Таблица1[[#This Row],[Блок Куб]]*Таблица1[[#This Row],[Цена Продажа]] -> 22785000 | S5: 2000000 | T5: =Таблица1[[#This Row],[Сумма Продажа]]-Таблица1[[#This Row],[Сумма Приход]] -> 7233000 | U5: Туланди
A6: =A5+1 -> 3 | B6: Газоблок | C6: Жамол 22-22 | D6: Инвест Холдинг | E6: 46197 | F6: 90 X 700 CA | G6: 600x300x200 | H6: 31.104 | I6: 500000 | J6: =Таблица1[[#This Row],[Блок Куб]]*Таблица1[[#This Row],[Цена Приход]] -> 15552000 | K6: 18 | L6: 130000 | M6: =Таблица1[[#This Row],[Поддон Шт]]*Таблица1[[#This Row],[Цена Поддон]] -> 2340000 | N6: =Таблица1[[#This Row],[Сумма Приход]]+Таблица1[[#This Row],[Сумма Поддон]] -> 17892000 | O6: 700000 | P6: =(Таблица1[[#This Row],[Цена Продажа]]+Таблица1[[#This Row],[Цена Поддон]])-Таблица1[[#This Row],[Цена Приход]] -> 330000 | Q6: Фойда | R6: =Таблица1[[#This Row],[Блок Куб]]*Таблица1[[#This Row],[Цена Продажа]] -> 21772800 | S6: 2000000 | T6: =Таблица1[[#This Row],[Сумма Продажа]]-Таблица1[[#This Row],[Сумма Приход]] -> 6220800 | U6: Туланди
A7: =A6+1 -> 4 | B7: Газоблок | C7: Зафар ога | D7: Сулаймон Ога Хазарасп | E7: 46197 | F7: 90 G 991 FA | G7: 600x300x200 | H7: 31.104 | I7: 500000 | J7: =Таблица1[[#This Row],[Блок Куб]]*Таблица1[[#This Row],[Цена Приход]] -> 15552000 | K7: 18 | L7: 130000 | M7: =Таблица1[[#This Row],[Поддон Шт]]*Таблица1[[#This Row],[Цена Поддон]] -> 2340000 | N7: =Таблица1[[#This Row],[Сумма Приход]]+Таблица1[[#This Row],[Сумма Поддон]] -> 17892000 | O7: 750000 | P7: =(Таблица1[[#This Row],[Цена Продажа]]+Таблица1[[#This Row],[Цена Поддон]])-Таблица1[[#This Row],[Цена Приход]] -> 380000 | Q7: Фойда | R7: =Таблица1[[#This Row],[Блок Куб]]*Таблица1[[#This Row],[Цена Продажа]] -> 23328000 | S7: 2000000 | T7: =Таблица1[[#This Row],[Сумма Продажа]]-Таблица1[[#This Row],[Сумма Приход]] -> 7776000 | U7: Туланди
A8: =A7+1 -> 5 | B8: Газоблок | C8: Жамол 22-22 | D8: Инвест Холдинг | E8: 46197 | F8: 90 G 429 CA | G8: 600x300x200 | H8: 32.832 | I8: 500000 | J8: =Таблица1[[#This Row],[Блок Куб]]*Таблица1[[#This Row],[Цена Приход]] -> 16416000 | K8: 19 | L8: 130000 | M8: =Таблица1[[#This Row],[Поддон Шт]]*Таблица1[[#This Row],[Цена Поддон]] -> 2470000 | N8: =Таблица1[[#This Row],[Сумма Приход]]+Таблица1[[#This Row],[Сумма Поддон]] -> 18886000 | O8: 700000 | P8: =(Таблица1[[#This Row],[Цена Продажа]]+Таблица1[[#This Row],[Цена Поддон]])-Таблица1[[#This Row],[Цена Приход]] -> 330000 | Q8: Фойда | R8: =Таблица1[[#This Row],[Блок Куб]]*Таблица1[[#This Row],[Цена Продажа]] -> 22982400 | S8: 2000000 | T8: =Таблица1[[#This Row],[Сумма Продажа]]-Таблица1[[#This Row],[Сумма Приход]] -> 6566400 | U8: Туланди
A9: =A8+1 -> 6 | B9: Газоблок | C9: Жамол 22-22 | D9: Инвест Холдинг | E9: 46198 | F9: 30 N 113 MB | G9: 600x300x200 | H9: 32.832 | I9: 500000 | J9: =Таблица1[[#This Row],[Блок Куб]]*Таблица1[[#This Row],[Цена Приход]] -> 16416000 | K9: 19 | L9: 130000 | M9: =Таблица1[[#This Row],[Поддон Шт]]*Таблица1[[#This Row],[Цена Поддон]] -> 2470000 | N9: =Таблица1[[#This Row],[Сумма Приход]]+Таблица1[[#This Row],[Сумма Поддон]] -> 18886000 | O9: 700000 | P9: =Таблица1[[#This Row],[Цена Продажа]]-Таблица1[[#This Row],[Цена Приход]] -> 200000 | Q9: Фойда | R9: =Таблица1[[#This Row],[Блок Куб]]*Таблица1[[#This Row],[Цена Продажа]] -> 22982400 | S9: 2000000 | T9: =Таблица1[[#This Row],[Сумма Продажа]]-Таблица1[[#This Row],[Сумма Приход]] -> 6566400 | U9: Туланди
A10: =A9+1 -> 7 | B10: Газоблок | C10: Жамол 22-22 | D10: Нормат Умидбек | E10: 46198 | F10: 50 R 575 CB | G10: 600x300x200 | H10: 32.832 | I10: 500000 | J10: =Таблица1[[#This Row],[Блок Куб]]*Таблица1[[#This Row],[Цена Приход]] -> 16416000 | K10: 19 | L10: 130000 | M10: =Таблица1[[#This Row],[Поддон Шт]]*Таблица1[[#This Row],[Цена Поддон]] -> 2470000 | N10: =Таблица1[[#This Row],[Сумма Приход]]+Таблица1[[#This Row],[Сумма Поддон]] -> 18886000 | O10: 735000 | P10: =Таблица1[[#This Row],[Цена Продажа]]-Таблица1[[#This Row],[Цена Приход]] -> 235000 | Q10: Фойда | R10: =Таблица1[[#This Row],[Блок Куб]]*Таблица1[[#This Row],[Цена Продажа]] -> 24131520 | S10: 2000000 | T10: =Таблица1[[#This Row],[Сумма Продажа]]-Таблица1[[#This Row],[Сумма Приход]] -> 7715520 | U10: Туланди
A11: =A10+1 -> 8 | B11: Газоблок | C11: Жамол 22-22 | D11: Нормат Умидбек | E11: 46198 | F11: 30 784 WBA | G11: 600x300x200 | H11: 32.832 | I11: 500000 | J11: =Таблица1[[#This Row],[Блок Куб]]*Таблица1[[#This Row],[Цена Приход]] -> 16416000 | K11: 19 | L11: 130000 | M11: =Таблица1[[#This Row],[Поддон Шт]]*Таблица1[[#This Row],[Цена Поддон]] -> 2470000 | N11: =Таблица1[[#This Row],[Сумма Приход]]+Таблица1[[#This Row],[Сумма Поддон]] -> 18886000 | O11: 735000 | P11: =Таблица1[[#This Row],[Цена Продажа]]-Таблица1[[#This Row],[Цена Приход]] -> 235000 | Q11: Фойда | R11: =Таблица1[[#This Row],[Блок Куб]]*Таблица1[[#This Row],[Цена Продажа]] -> 24131520 | S11: 2000000 | T11: =Таблица1[[#This Row],[Сумма Продажа]]-Таблица1[[#This Row],[Сумма Приход]] -> 7715520 | U11: Туланди
A12: =A11+1 -> 9 | B12: Газоблок | C12: Жамол 22-22 | D12: Нормат Умидбек | E12: 46198 | F12: VI-004-KT | G12: 600x300x200 | H12: 32.832 | I12: 500000 | J12: =Таблица1[[#This Row],[Блок Куб]]*Таблица1[[#This Row],[Цена Приход]] -> 16416000 | K12: 19 | L12: 130000 | M12: =Таблица1[[#This Row],[Поддон Шт]]*Таблица1[[#This Row],[Цена Поддон]] -> 2470000 | N12: =Таблица1[[#This Row],[Сумма Приход]]+Таблица1[[#This Row],[Сумма Поддон]] -> 18886000 | O12: 735000 | P12: =Таблица1[[#This Row],[Цена Продажа]]-Таблица1[[#This Row],[Цена Приход]] -> 235000 | Q12: Фойда | R12: =Таблица1[[#This Row],[Блок Куб]]*Таблица1[[#This Row],[Цена Продажа]] -> 24131520 | S12: 2000000 | T12: =Таблица1[[#This Row],[Сумма Продажа]]-Таблица1[[#This Row],[Сумма Приход]] -> 7715520 | U12: Туланди
A13: =A12+1 -> 10 | B13: Газоблок | C13: Арслон ога | D13: Гофур Хазорасп | E13: 46198 | F13: 01 U 917 XC | G13: 600x300x200 | H13: 32.832 | I13: 500000 | J13: =Таблица1[[#This Row],[Блок Куб]]*Таблица1[[#This Row],[Цена Приход]] -> 16416000 | K13: 19 | L13: 130000 | M13: =Таблица1[[#This Row],[Поддон Шт]]*Таблица1[[#This Row],[Цена Поддон]] -> 2470000 | N13: =Таблица1[[#This Row],[Сумма Приход]]+Таблица1[[#This Row],[Сумма Поддон]] -> 18886000 | O13: 750000 | P13: =Таблица1[[#This Row],[Цена Продажа]]-Таблица1[[#This Row],[Цена Приход]] -> 250000 | Q13: Фойда | R13: =Таблица1[[#This Row],[Блок Куб]]*Таблица1[[#This Row],[Цена Продажа]] -> 24624000 | S13: 2500000 | T13: =Таблица1[[#This Row],[Сумма Продажа]]-Таблица1[[#This Row],[Сумма Приход]] -> 8208000 | U13: Туланди
A14: =A13+1 -> 11 | B14: Газоблок | C14: Арслон ога | D14: Гофур Хазорасп | E14: 46198 | F14: 95 194 LBA | G14: 600x300x200 | H14: 31.104 | I14: 500000 | J14: =Таблица1[[#This Row],[Блок Куб]]*Таблица1[[#This Row],[Цена Приход]] -> 15552000 | K14: 18 | L14: 130000 | M14: =Таблица1[[#This Row],[Поддон Шт]]*Таблица1[[#This Row],[Цена Поддон]] -> 2340000 | N14: =Таблица1[[#This Row],[Сумма Приход]]+Таблица1[[#This Row],[Сумма Поддон]] -> 17892000 | O14: 750000 | P14: =Таблица1[[#This Row],[Цена Продажа]]-Таблица1[[#This Row],[Цена Приход]] -> 250000 | Q14: Фойда | R14: =Таблица1[[#This Row],[Блок Куб]]*Таблица1[[#This Row],[Цена Продажа]] -> 23328000 | S14: 2500000 | T14: =Таблица1[[#This Row],[Сумма Продажа]]-Таблица1[[#This Row],[Сумма Приход]] -> 7776000 | U14: Туланди
A15: =A14+1 -> 12 | B15: Газоблок | C15: Зафар ога | D15: Сулаймон Ога Хазарасп | E15: 46200 | F15: 40 W 910 SB | G15: 600x300x100 | H15: 32.832 | I15: 500000 | J15: =Таблица1[[#This Row],[Блок Куб]]*Таблица1[[#This Row],[Цена Приход]] -> 16416000 | K15: 19 | L15: 130000 | M15: =Таблица1[[#This Row],[Поддон Шт]]*Таблица1[[#This Row],[Цена Поддон]] -> 2470000 | N15: =Таблица1[[#This Row],[Сумма Приход]]+Таблица1[[#This Row],[Сумма Поддон]] -> 18886000 | O15: 750000 | P15: =Таблица1[[#This Row],[Цена Продажа]]-Таблица1[[#This Row],[Цена Приход]] -> 250000 | Q15: Фойда | R15: =Таблица1[[#This Row],[Блок Куб]]*Таблица1[[#This Row],[Цена Продажа]] -> 24624000 | S15: 2500000 | T15: =Таблица1[[#This Row],[Сумма Продажа]]-Таблица1[[#This Row],[Сумма Приход]] -> 8208000 | U15: Туланди
A16: =A15+1 -> 13 | B16: Газоблок | C16: Зафар ога | D16: Сулаймон Ога Хазарасп | E16: 46200 | F16: 90 Z 688 AB | G16: 600x300x100 | H16: 32.832 | I16: 500000 | J16: =Таблица1[[#This Row],[Блок Куб]]*Таблица1[[#This Row],[Цена Приход]] -> 16416000 | K16: 19 | L16: 130000 | M16: =Таблица1[[#This Row],[Поддон Шт]]*Таблица1[[#This Row],[Цена Поддон]] -> 2470000 | N16: =Таблица1[[#This Row],[Сумма Приход]]+Таблица1[[#This Row],[Сумма Поддон]] -> 18886000 | O16: 750000 | P16: =Таблица1[[#This Row],[Цена Продажа]]-Таблица1[[#This Row],[Цена Приход]] -> 250000 | Q16: Фойда | R16: =Таблица1[[#This Row],[Блок Куб]]*Таблица1[[#This Row],[Цена Продажа]] -> 24624000 | S16: 2000000 | T16: =Таблица1[[#This Row],[Сумма Продажа]]-Таблица1[[#This Row],[Сумма Приход]] -> 8208000 | U16: Туланди
A17: =A16+1 -> 14 | B17: Газоблок | C17: Зафар ога | D17: Сулаймон Ога Хазарасп | E17: 46200 | F17: 95 617 MBA | G17: 600x300x200 | H17: 32.832 | I17: 500000 | J17: =Таблица1[[#This Row],[Блок Куб]]*Таблица1[[#This Row],[Цена Приход]] -> 16416000 | K17: 19 | L17: 130000 | M17: =Таблица1[[#This Row],[Поддон Шт]]*Таблица1[[#This Row],[Цена Поддон]] -> 2470000 | N17: =Таблица1[[#This Row],[Сумма Приход]]+Таблица1[[#This Row],[Сумма Поддон]] -> 18886000 | O17: 750000 | P17: =Таблица1[[#This Row],[Цена Продажа]]-Таблица1[[#This Row],[Цена Приход]] -> 250000 | Q17: Фойда | R17: =Таблица1[[#This Row],[Блок Куб]]*Таблица1[[#This Row],[Цена Продажа]] -> 24624000 | S17: 2000000 | T17: =Таблица1[[#This Row],[Сумма Продажа]]-Таблица1[[#This Row],[Сумма Приход]] -> 8208000 | U17: Туланди
A18: =A17+1 -> 15 | B18: Газоблок | C18: Зафар ога | D18: Сулаймон Ога Хазарасп | E18: 46200 | F18: 40 148 ECA | G18: 600x300x200 | H18: 32.832 | I18: 500000 | J18: =Таблица1[[#This Row],[Блок Куб]]*Таблица1[[#This Row],[Цена Приход]] -> 16416000 | K18: 19 | L18: 130000 | M18: =Таблица1[[#This Row],[Поддон Шт]]*Таблица1[[#This Row],[Цена Поддон]] -> 2470000 | N18: =Таблица1[[#This Row],[Сумма Приход]]+Таблица1[[#This Row],[Сумма Поддон]] -> 18886000 | O18: 750000 | P18: =Таблица1[[#This Row],[Цена Продажа]]-Таблица1[[#This Row],[Цена Приход]] -> 250000 | Q18: Фойда | R18: =Таблица1[[#This Row],[Блок Куб]]*Таблица1[[#This Row],[Цена Продажа]] -> 24624000 | S18: 2000000 | T18: =Таблица1[[#This Row],[Сумма Продажа]]-Таблица1[[#This Row],[Сумма Приход]] -> 8208000 | U18: Туланди
A19: =A18+1 -> 16 | B19: Газоблок | C19: Шохрух ога | D19: Гайрат Штб | E19: 46200 | F19: 90 919 LBA | G19: 600x300x200 | H19: 32.832 | I19: 500000 | J19: =Таблица1[[#This Row],[Блок Куб]]*Таблица1[[#This Row],[Цена Приход]] -> 16416000 | K19: 19 | L19: 130000 | M19: =Таблица1[[#This Row],[Поддон Шт]]*Таблица1[[#This Row],[Цена Поддон]] -> 2470000 | N19: =Таблица1[[#This Row],[Сумма Приход]]+Таблица1[[#This Row],[Сумма Поддон]] -> 18886000 | O19: 760000 | P19: =Таблица1[[#This Row],[Цена Продажа]]-Таблица1[[#This Row],[Цена Приход]] -> 260000 | Q19: Фойда | R19: =Таблица1[[#This Row],[Блок Куб]]*Таблица1[[#This Row],[Цена Продажа]] -> 24952320 | S19: 2000000 | T19: =Таблица1[[#This Row],[Сумма Продажа]]-Таблица1[[#This Row],[Сумма Приход]] -> 8536320 | U19: Туланди
A20: =A19+1 -> 17 | B20: Газоблок | C20: Шохрух ога | D20: Рустам Шпик | E20: 46200 | F20: 90 X 700 CA | G20: 600x300x200 | H20: 32.832 | I20: 500000 | J20: =Таблица1[[#This Row],[Блок Куб]]*Таблица1[[#This Row],[Цена Приход]] -> 16416000 | K20: 19 | L20: 130000 | M20: =Таблица1[[#This Row],[Поддон Шт]]*Таблица1[[#This Row],[Цена Поддон]] -> 2470000 | N20: =Таблица1[[#This Row],[Сумма Приход]]+Таблица1[[#This Row],[Сумма Поддон]] -> 18886000 | O20: 729928.1 | P20: =Таблица1[[#This Row],[Цена Продажа]]-Таблица1[[#This Row],[Цена Приход]] -> 229928.1 | Q20: Фойда | R20: =Таблица1[[#This Row],[Блок Куб]]*Таблица1[[#This Row],[Цена Продажа]] -> 23964999 | S20: 2000000 | T20: =Таблица1[[#This Row],[Сумма Продажа]]-Таблица1[[#This Row],[Сумма Приход]] -> 7548999.4 | U20: Туланди
... A30: =A29+1 -> 27 | B30: Газоблок | C30: Арслон ога | D30: Гофур Хазорасп | E30: 46204 | F30: 70 Y 119 GB | G30: 600x300x100 | H30: 32.832 | I30: 500000 | J30: =Таблица1[[#This Row],[Блок Куб]]*Таблица1[[#This Row],[Цена Приход]] -> 16416000 | K30: 19 | L30: 130000 | M30: =Таблица1[[#This Row],[Поддон Шт]]*Таблица1[[#This Row],[Цена Поддон]] -> 2470000 | N30: =Таблица1[[#This Row],[Сумма Приход]]+Таблица1[[#This Row],[Сумма Поддон]] -> 18886000 | O30: 750000 | P30: =Таблица1[[#This Row],[Цена Продажа]]-Таблица1[[#This Row],[Цена Приход]] -> 250000 | Q30: Фойда | R30: =Таблица1[[#This Row],[Блок Куб]]*Таблица1[[#This Row],[Цена Продажа]] -> 24624000 | S30: 2550000 | T30: =Таблица1[[#This Row],[Сумма Продажа]]-Таблица1[[#This Row],[Сумма Приход]] -> 8208000 | U30: Туланди
A31: =A30+1 -> 28 | B31: Газоблок | C31: Жамол 22-22 | D31: Фидато Груп | E31: 46205 | F31: 90 S 954 OA | G31: 600x300x100 | H31: 32.832 | I31: 625000 | J31: =Таблица1[[#This Row],[Блок Куб]]*Таблица1[[#This Row],[Цена Приход]] -> 20520000 | K31: 19 | L31: 130000 | M31: =Таблица1[[#This Row],[Поддон Шт]]*Таблица1[[#This Row],[Цена Поддон]] -> 2470000 | N31: =Таблица1[[#This Row],[Сумма Приход]]+Таблица1[[#This Row],[Сумма Поддон]] -> 22990000 | O31: 730000 | P31: =Таблица1[[#This Row],[Цена Продажа]]-Таблица1[[#This Row],[Цена Приход]] -> 105000 | Q31: Фойда | R31: =Таблица1[[#This Row],[Блок Куб]]*Таблица1[[#This Row],[Цена Продажа]] -> 23967360 | S31: 2000000 | T31: =Таблица1[[#This Row],[Сумма Продажа]]-Таблица1[[#This Row],[Сумма Приход]] -> 3447360 | U31: 46206
A32: =A31+1 -> 29 | B32: Газоблок | C32: Жамол 22-22 | D32: Урганч Тамирлаш | E32: 46206 | F32: 40 F 105 RB | G32: 600x300x200 | H32: 32.832 | I32: 625000 | J32: =Таблица1[[#This Row],[Блок Куб]]*Таблица1[[#This Row],[Цена Приход]] -> 20520000 | K32: 19 | L32: 130000 | M32: =Таблица1[[#This Row],[Поддон Шт]]*Таблица1[[#This Row],[Цена Поддон]] -> 2470000 | N32: =Таблица1[[#This Row],[Сумма Приход]]+Таблица1[[#This Row],[Сумма Поддон]] -> 22990000 | O32: 700000 | P32: =Таблица1[[#This Row],[Цена Продажа]]-Таблица1[[#This Row],[Цена Приход]] -> 75000 | Q32: Фойда | R32: =Таблица1[[#This Row],[Блок Куб]]*Таблица1[[#This Row],[Цена Продажа]] -> 22982400 | S32: 2000000 | T32: =Таблица1[[#This Row],[Сумма Продажа]]-Таблица1[[#This Row],[Сумма Приход]] -> 2462400 | U32: 46207
A33: =A32+1 -> 30 | B33: Газоблок | C33: Жамол 22-22 | D33: Урганч Тамирлаш | E33: 46206 | F33: 90 K 295 QA | G33: 600x300x200 | H33: 32.832 | I33: 625000 | J33: =Таблица1[[#This Row],[Блок Куб]]*Таблица1[[#This Row],[Цена Приход]] -> 20520000 | K33: 19 | L33: 130000 | M33: =Таблица1[[#This Row],[Поддон Шт]]*Таблица1[[#This Row],[Цена Поддон]] -> 2470000 | N33: =Таблица1[[#This Row],[Сумма Приход]]+Таблица1[[#This Row],[Сумма Поддон]] -> 22990000 | O33: 700000 | P33: =Таблица1[[#This Row],[Цена Продажа]]-Таблица1[[#This Row],[Цена Приход]] -> 75000 | Q33: Фойда | R33: =Таблица1[[#This Row],[Блок Куб]]*Таблица1[[#This Row],[Цена Продажа]] -> 22982400 | T33: =Таблица1[[#This Row],[Сумма Продажа]]-Таблица1[[#This Row],[Сумма Приход]] -> 2462400
A34: =A33+1 -> 31 | B34: Газоблок | C34: Шохрух ога | D34: Рустам Шпик | E34: 46206 | F34: 90 015 WAA | G34: 600x300x200 | H34: 32.832 | I34: 625000 | J34: =Таблица1[[#This Row],[Блок Куб]]*Таблица1[[#This Row],[Цена Приход]] -> 20520000 | K34: 19 | L34: 130000 | M34: =Таблица1[[#This Row],[Поддон Шт]]*Таблица1[[#This Row],[Цена Поддон]] -> 2470000 | N34: =Таблица1[[#This Row],[Сумма Приход]]+Таблица1[[#This Row],[Сумма Поддон]] -> 22990000 | O34: 700000 | P34: =Таблица1[[#This Row],[Цена Продажа]]-Таблица1[[#This Row],[Цена Приход]] -> 75000 | Q34: Фойда | R34: =Таблица1[[#This Row],[Блок Куб]]*Таблица1[[#This Row],[Цена Продажа]] -> 22982400 | S34: 2000000 | T34: =Таблица1[[#This Row],[Сумма Продажа]]-Таблица1[[#This Row],[Сумма Приход]] -> 2462400 | U34: 46206
A35: =A34+1 -> 32 | B35: Газоблок | C35: Зафар ога | D35: Сулаймон Ога Хазарасп | E35: 46206 | F35: 90 452 PBA | G35: 600x300x200 | H35: 32.832 | I35: 625000 | J35: =Таблица1[[#This Row],[Блок Куб]]*Таблица1[[#This Row],[Цена Приход]] -> 20520000 | K35: 19 | L35: 130000 | M35: =Таблица1[[#This Row],[Поддон Шт]]*Таблица1[[#This Row],[Цена Поддон]] -> 2470000 | N35: =Таблица1[[#This Row],[Сумма Приход]]+Таблица1[[#This Row],[Сумма Поддон]] -> 22990000 | O35: 700000 | P35: =Таблица1[[#This Row],[Цена Продажа]]-Таблица1[[#This Row],[Цена Приход]] -> 75000 | Q35: Фойда | R35: =Таблица1[[#This Row],[Блок Куб]]*Таблица1[[#This Row],[Цена Продажа]] -> 22982400 | S35: клентдан | T35: =Таблица1[[#This Row],[Сумма Продажа]]-Таблица1[[#This Row],[Сумма Приход]] -> 2462400
A36: =A35+1 -> 33 | B36: Газоблок | C36: Шохрух ога | D36: Рустам Шпик | E36: 46206 | F36: 90 306 FBA | G36: 600x300x200 | H36: 32.832 | I36: 625000 | J36: =Таблица1[[#This Row],[Блок Куб]]*Таблица1[[#This Row],[Цена Приход]] -> 20520000 | K36: 19 | L36: 130000 | M36: =Таблица1[[#This Row],[Поддон Шт]]*Таблица1[[#This Row],[Цена Поддон]] -> 2470000 | N36: =Таблица1[[#This Row],[Сумма Приход]]+Таблица1[[#This Row],[Сумма Поддон]] -> 22990000 | O36: 700000 | P36: =Таблица1[[#This Row],[Цена Продажа]]-Таблица1[[#This Row],[Цена Приход]] -> 75000 | Q36: Фойда | R36: =Таблица1[[#This Row],[Блок Куб]]*Таблица1[[#This Row],[Цена Продажа]] -> 22982400 | S36: 2000000 | T36: =Таблица1[[#This Row],[Сумма Продажа]]-Таблица1[[#This Row],[Сумма Приход]] -> 2462400 | U36: 46207
A37: =A36+1 -> 34 | B37: Газоблок | C37: Жамол 22-22 | D37: Урганч Тамирлаш | E37: 46206 | F37: 90 N 831 HA | G37: 600x300x200 | H37: 32.832 | I37: 625000 | J37: =Таблица1[[#This Row],[Блок Куб]]*Таблица1[[#This Row],[Цена Приход]] -> 20520000 | K37: 19 | L37: 130000 | M37: =Таблица1[[#This Row],[Поддон Шт]]*Таблица1[[#This Row],[Цена Поддон]] -> 2470000 | N37: =Таблица1[[#This Row],[Сумма Приход]]+Таблица1[[#This Row],[Сумма Поддон]] -> 22990000 | O37: 700000 | P37: =Таблица1[[#This Row],[Цена Продажа]]-Таблица1[[#This Row],[Цена Приход]] -> 75000 | Q37: Фойда | R37: =Таблица1[[#This Row],[Блок Куб]]*Таблица1[[#This Row],[Цена Продажа]] -> 22982400 | T37: =Таблица1[[#This Row],[Сумма Продажа]]-Таблица1[[#This Row],[Сумма Приход]] -> 2462400
A38: =A37+1 -> 35 | B38: Газоблок | C38: Жамол 22-22 | D38: Урганч Тамирлаш | E38: 46206 | F38: 90 255 FBA | G38: 600x300x200 | H38: 32.832 | I38: 625000 | J38: =Таблица1[[#This Row],[Блок Куб]]*Таблица1[[#This Row],[Цена Приход]] -> 20520000 | K38: 19 | L38: 130000 | M38: =Таблица1[[#This Row],[Поддон Шт]]*Таблица1[[#This Row],[Цена Поддон]] -> 2470000 | N38: =Таблица1[[#This Row],[Сумма Приход]]+Таблица1[[#This Row],[Сумма Поддон]] -> 22990000 | O38: 700000 | P38: =Таблица1[[#This Row],[Цена Продажа]]-Таблица1[[#This Row],[Цена Приход]] -> 75000 | Q38: Фойда | R38: =Таблица1[[#This Row],[Блок Куб]]*Таблица1[[#This Row],[Цена Продажа]] -> 22982400 | S38: 2000000 | T38: =Таблица1[[#This Row],[Сумма Продажа]]-Таблица1[[#This Row],[Сумма Приход]] -> 2462400
A39: =A38+1 -> 36 | B39: Газоблок | C39: Зафар ога | D39: Сулаймон Ога Хазарасп | E39: 46206 | F39: 40 E 471 SB | G39: 600x300x100 | H39: 32.832 | I39: 625000 | J39: =Таблица1[[#This Row],[Блок Куб]]*Таблица1[[#This Row],[Цена Приход]] -> 20520000 | K39: 19 | L39: 130000 | M39: =Таблица1[[#This Row],[Поддон Шт]]*Таблица1[[#This Row],[Цена Поддон]] -> 2470000 | N39: =Таблица1[[#This Row],[Сумма Приход]]+Таблица1[[#This Row],[Сумма Поддон]] -> 22990000 | O39: 700000 | P39: =Таблица1[[#This Row],[Цена Продажа]]-Таблица1[[#This Row],[Цена Приход]] -> 75000 | Q39: Фойда | R39: =Таблица1[[#This Row],[Блок Куб]]*Таблица1[[#This Row],[Цена Продажа]] -> 22982400 | S39: клентдан | T39: =Таблица1[[#This Row],[Сумма Продажа]]-Таблица1[[#This Row],[Сумма Приход]] -> 2462400
A40: =A39+1 -> 37 | B40: Газоблок | C40: Зафар ога | D40: Сулаймон Ога Хазарасп | E40: 46206 | F40: 80 N 441 DB | G40: 600x300x200 | H40: 32.832 | I40: 625000 | J40: =Таблица1[[#This Row],[Блок Куб]]*Таблица1[[#This Row],[Цена Приход]] -> 20520000 | K40: 19 | L40: 130000 | M40: =Таблица1[[#This Row],[Поддон Шт]]*Таблица1[[#This Row],[Цена Поддон]] -> 2470000 | N40: =Таблица1[[#This Row],[Сумма Приход]]+Таблица1[[#This Row],[Сумма Поддон]] -> 22990000 | O40: 700000 | P40: =Таблица1[[#This Row],[Цена Продажа]]-Таблица1[[#This Row],[Цена Приход]] -> 75000 | Q40: Фойда | R40: =Таблица1[[#This Row],[Блок Куб]]*Таблица1[[#This Row],[Цена Продажа]] -> 22982400 | S40: клентдан | T40: =Таблица1[[#This Row],[Сумма Продажа]]-Таблица1[[#This Row],[Сумма Приход]] -> 2462400
A41: =A40+1 -> 38 | B41: Газоблок | C41: Темур | D41: Жасур Версал | E41: 46206 | F41: 80 C 385 CB | G41: 600x300x200 | H41: 32.832 | I41: 625000 | J41: =Таблица1[[#This Row],[Блок Куб]]*Таблица1[[#This Row],[Цена Приход]] -> 20520000 | K41: 19 | L41: 130000 | M41: =Таблица1[[#This Row],[Поддон Шт]]*Таблица1[[#This Row],[Цена Поддон]] -> 2470000 | N41: =Таблица1[[#This Row],[Сумма Приход]]+Таблица1[[#This Row],[Сумма Поддон]] -> 22990000 | O41: 700000 | P41: =Таблица1[[#This Row],[Цена Продажа]]-Таблица1[[#This Row],[Цена Приход]] -> 75000 | Q41: Фойда | R41: =Таблица1[[#This Row],[Блок Куб]]*Таблица1[[#This Row],[Цена Продажа]] -> 22982400 | S41: клентдан | T41: =Таблица1[[#This Row],[Сумма Продажа]]-Таблица1[[#This Row],[Сумма Приход]] -> 2462400
A42: =A41+1 -> 39 | B42: Газоблок | C42: Темур | D42: Жасур Версал | E42: 46206 | F42: 90 S 954 OA | G42: 600x300x200 | H42: 32.832 | I42: 625000 | J42: =Таблица1[[#This Row],[Блок Куб]]*Таблица1[[#This Row],[Цена Приход]] -> 20520000 | K42: 19 | L42: 130000 | M42: =Таблица1[[#This Row],[Поддон Шт]]*Таблица1[[#This Row],[Цена Поддон]] -> 2470000 | N42: =Таблица1[[#This Row],[Сумма Приход]]+Таблица1[[#This Row],[Сумма Поддон]] -> 22990000 | O42: 700000 | P42: =Таблица1[[#This Row],[Цена Продажа]]-Таблица1[[#This Row],[Цена Приход]] -> 75000 | Q42: Фойда | R42: =Таблица1[[#This Row],[Блок Куб]]*Таблица1[[#This Row],[Цена Продажа]] -> 22982400 | S42: клентдан | T42: =Таблица1[[#This Row],[Сумма Продажа]]-Таблица1[[#This Row],[Сумма Приход]] -> 2462400
A43: =A42+1 -> 40 | B43: Газоблок | C43: Темур | D43: Жасур Версал | E43: 46206 | F43: 90 734 МВА | G43: 600x300x100 | H43: 32.832 | I43: 625000 | J43: =Таблица1[[#This Row],[Блок Куб]]*Таблица1[[#This Row],[Цена Приход]] -> 20520000 | K43: 19 | L43: 130000 | M43: =Таблица1[[#This Row],[Поддон Шт]]*Таблица1[[#This Row],[Цена Поддон]] -> 2470000 | N43: =Таблица1[[#This Row],[Сумма Приход]]+Таблица1[[#This Row],[Сумма Поддон]] -> 22990000 | O43: 700000 | P43: =Таблица1[[#This Row],[Цена Продажа]]-Таблица1[[#This Row],[Цена Приход]] -> 75000 | Q43: Фойда | R43: =Таблица1[[#This Row],[Блок Куб]]*Таблица1[[#This Row],[Цена Продажа]] -> 22982400 | S43: клентдан | T43: =Таблица1[[#This Row],[Сумма Продажа]]-Таблица1[[#This Row],[Сумма Приход]] -> 2462400
A44: =A43+1 -> 41 | B44: Газоблок | C44: Зафар ога | D44: Сарвар ога Шовот | E44: 46209 | F44: 90 015 WAA | G44: 600x300x200 | H44: 32.832 | I44: 625000 | J44: =Таблица1[[#This Row],[Блок Куб]]*Таблица1[[#This Row],[Цена Приход]] -> 20520000 | K44: 19 | L44: 130000 | M44: =Таблица1[[#This Row],[Поддон Шт]]*Таблица1[[#This Row],[Цена Поддон]] -> 2470000 | N44: =Таблица1[[#This Row],[Сумма Приход]]+Таблица1[[#This Row],[Сумма Поддон]] -> 22990000 | O44: 700000 | P44: =Таблица1[[#This Row],[Цена Продажа]]-Таблица1[[#This Row],[Цена Приход]] -> 75000 | Q44: Фойда | R44: =Таблица1[[#This Row],[Блок Куб]]*Таблица1[[#This Row],[Цена Продажа]] -> 22982400 | S44: клентдан | T44: =Таблица1[[#This Row],[Сумма Продажа]]-Таблица1[[#This Row],[Сумма Приход]] -> 2462400
A45: =A44+1 -> 42 | B45: Газоблок | C45: Темур | D45: Мустафо машал | E45: 46209 | F45: 40 O 636 TB | G45: 600x300x200 | H45: 32.832 | I45: 625000 | J45: =Таблица1[[#This Row],[Блок Куб]]*Таблица1[[#This Row],[Цена Приход]] -> 20520000 | K45: 19 | L45: 130000 | M45: =Таблица1[[#This Row],[Поддон Шт]]*Таблица1[[#This Row],[Цена Поддон]] -> 2470000 | N45: =Таблица1[[#This Row],[Сумма Приход]]+Таблица1[[#This Row],[Сумма Поддон]] -> 22990000 | O45: 700000 | P45: =Таблица1[[#This Row],[Цена Продажа]]-Таблица1[[#This Row],[Цена Приход]] -> 75000 | Q45: Фойда | R45: =Таблица1[[#This Row],[Блок Куб]]*Таблица1[[#This Row],[Цена Продажа]] -> 22982400 | S45: клентдан | T45: =Таблица1[[#This Row],[Сумма Продажа]]-Таблица1[[#This Row],[Сумма Приход]] -> 2462400
A46: =A45+1 -> 43 | B46: Газоблок | C46: Арслон ога | D46: Шиддат моналит | E46: 46209 | F46: 85 L 457 HA | G46: 600x300x250 | H46: 23.4 | I46: 625000 | J46: =Таблица1[[#This Row],[Блок Куб]]*Таблица1[[#This Row],[Цена Приход]] -> 14625000 | K46: 13 | L46: 130000 | M46: =Таблица1[[#This Row],[Поддон Шт]]*Таблица1[[#This Row],[Цена Поддон]] -> 1690000 | N46: =Таблица1[[#This Row],[Сумма Приход]]+Таблица1[[#This Row],[Сумма Поддон]] -> 16315000 | O46: 700000 | P46: =Таблица1[[#This Row],[Цена Продажа]]-Таблица1[[#This Row],[Цена Приход]] -> 75000 | Q46: Фойда | R46: =Таблица1[[#This Row],[Блок Куб]]*Таблица1[[#This Row],[Цена Продажа]] -> 16380000 | T46: =Таблица1[[#This Row],[Сумма Продажа]]-Таблица1[[#This Row],[Сумма Приход]] -> 1755000
A47: =A46+1 -> 44 | B47: Газоблок | C47: Арслон ога | D47: Шиддат моналит | E47: 46209 | F47: 85 L 457 HA | G47: 600x300x200 | H47: 10.37 | I47: 625000 | J47: =Таблица1[[#This Row],[Блок Куб]]*Таблица1[[#This Row],[Цена Приход]] -> 6481250 | K47: 6 | L47: 130000 | M47: =Таблица1[[#This Row],[Поддон Шт]]*Таблица1[[#This Row],[Цена Поддон]] -> 780000 | N47: =Таблица1[[#This Row],[Сумма Приход]]+Таблица1[[#This Row],[Сумма Поддон]] -> 7261250 | O47: 700000 | P47: =Таблица1[[#This Row],[Цена Продажа]]-Таблица1[[#This Row],[Цена Приход]] -> 75000 | Q47: Фойда | R47: =Таблица1[[#This Row],[Блок Куб]]*Таблица1[[#This Row],[Цена Продажа]] -> 7259000 | T47: =Таблица1[[#This Row],[Сумма Продажа]]-Таблица1[[#This Row],[Сумма Приход]] -> 777750
A48: =A47+1 -> 45 | B48: Газоблок | C48: Зафар ога | D48: Сулаймон Ога Хазарасп | E48: 46209 | F48: 95 N 260 OA | G48: 600x300x200 | H48: 32.832 | I48: 625000 | J48: =Таблица1[[#This Row],[Блок Куб]]*Таблица1[[#This Row],[Цена Приход]] -> 20520000 | K48: 19 | L48: 130000 | M48: =Таблица1[[#This Row],[Поддон Шт]]*Таблица1[[#This Row],[Цена Поддон]] -> 2470000 | N48: =Таблица1[[#This Row],[Сумма Приход]]+Таблица1[[#This Row],[Сумма Поддон]] -> 22990000 | O48: 700000 | P48: =Таблица1[[#This Row],[Цена Продажа]]-Таблица1[[#This Row],[Цена Приход]] -> 75000 | Q48: Фойда | R48: =Таблица1[[#This Row],[Блок Куб]]*Таблица1[[#This Row],[Цена Продажа]] -> 22982400 | S48: клентдан | T48: =Таблица1[[#This Row],[Сумма Продажа]]-Таблица1[[#This Row],[Сумма Приход]] -> 2462400
A49: =A48+1 -> 46 | B49: Газоблок | C49: Темур | D49: Жасур Версал | E49: 46209 | F49: 95 C 626 SA | G49: 600x300x100 | H49: 32.832 | I49: 625000 | J49: =Таблица1[[#This Row],[Блок Куб]]*Таблица1[[#This Row],[Цена Приход]] -> 20520000 | K49: 19 | L49: 130000 | M49: =Таблица1[[#This Row],[Поддон Шт]]*Таблица1[[#This Row],[Цена Поддон]] -> 2470000 | N49: =Таблица1[[#This Row],[Сумма Приход]]+Таблица1[[#This Row],[Сумма Поддон]] -> 22990000 | O49: 700000 | P49: =Таблица1[[#This Row],[Цена Продажа]]-Таблица1[[#This Row],[Цена Приход]] -> 75000 | Q49: Фойда | R49: =Таблица1[[#This Row],[Блок Куб]]*Таблица1[[#This Row],[Цена Продажа]] -> 22982400 | T49: =Таблица1[[#This Row],[Сумма Продажа]]-Таблица1[[#This Row],[Сумма Приход]] -> 2462400
A50: =A49+1 -> 47 | B50: Газоблок | C50: Темур | D50: Жасур Версал | E50: 46210 | F50: 90 Z 410 ZZ | G50: 600x300x100 | H50: 32.832 | I50: 625000 | J50: =Таблица1[[#This Row],[Блок Куб]]*Таблица1[[#This Row],[Цена Приход]] -> 20520000 | K50: 19 | L50: 130000 | M50: =Таблица1[[#This Row],[Поддон Шт]]*Таблица1[[#This Row],[Цена Поддон]] -> 2470000 | N50: =Таблица1[[#This Row],[Сумма Приход]]+Таблица1[[#This Row],[Сумма Поддон]] -> 22990000 | O50: 700000 | P50: =Таблица1[[#This Row],[Цена Продажа]]-Таблица1[[#This Row],[Цена Приход]] -> 75000 | Q50: Фойда | R50: =Таблица1[[#This Row],[Блок Куб]]*Таблица1[[#This Row],[Цена Продажа]] -> 22982400 | T50: =Таблица1[[#This Row],[Сумма Продажа]]-Таблица1[[#This Row],[Сумма Приход]] -> 2462400
A51: =A50+1 -> 48 | B51: Газоблок | C51: Зафар ога | D51: Сулаймон Ога Хазарасп | E51: 46210 | F51: 95 512 DBA | G51: 600x300x200 | H51: 32.832 | I51: 625000 | J51: =Таблица1[[#This Row],[Блок Куб]]*Таблица1[[#This Row],[Цена Приход]] -> 20520000 | K51: 19 | L51: 130000 | M51: =Таблица1[[#This Row],[Поддон Шт]]*Таблица1[[#This Row],[Цена Поддон]] -> 2470000 | N51: =Таблица1[[#This Row],[Сумма Приход]]+Таблица1[[#This Row],[Сумма Поддон]] -> 22990000 | O51: 700000 | P51: =Таблица1[[#This Row],[Цена Продажа]]-Таблица1[[#This Row],[Цена Приход]] -> 75000 | Q51: Фойда | R51: =Таблица1[[#This Row],[Блок Куб]]*Таблица1[[#This Row],[Цена Продажа]] -> 22982400 | S51: клентдан | T51: =Таблица1[[#This Row],[Сумма Продажа]]-Таблица1[[#This Row],[Сумма Приход]] -> 2462400
A52: =A51+1 -> 49 | B52: Газоблок | C52: Зафар ога | D52: Сулаймон Ога Хазарасп | E52: 46210 | F52: 90 015 WAA | G52: 600x300x200 | H52: 32.832 | I52: 625000 | J52: =Таблица1[[#This Row],[Блок Куб]]*Таблица1[[#This Row],[Цена Приход]] -> 20520000 | K52: 19 | L52: 130000 | M52: =Таблица1[[#This Row],[Поддон Шт]]*Таблица1[[#This Row],[Цена Поддон]] -> 2470000 | N52: =Таблица1[[#This Row],[Сумма Приход]]+Таблица1[[#This Row],[Сумма Поддон]] -> 22990000 | O52: 700000 | P52: =Таблица1[[#This Row],[Цена Продажа]]-Таблица1[[#This Row],[Цена Приход]] -> 75000 | Q52: Фойда | R52: =Таблица1[[#This Row],[Блок Куб]]*Таблица1[[#This Row],[Цена Продажа]] -> 22982400 | S52: клентдан | T52: =Таблица1[[#This Row],[Сумма Продажа]]-Таблица1[[#This Row],[Сумма Приход]] -> 2462400
A53: =A52+1 -> 50 | B53: Газоблок | C53: Зафар ога | D53: Сулаймон Ога Хазарасп | E53: 46210 | F53: 80 801 UBA | G53: 600x300x200 | H53: 32.832 | I53: 625000 | J53: =Таблица1[[#This Row],[Блок Куб]]*Таблица1[[#This Row],[Цена Приход]] -> 20520000 | K53: 19 | L53: 130000 | M53: =Таблица1[[#This Row],[Поддон Шт]]*Таблица1[[#This Row],[Цена Поддон]] -> 2470000 | N53: =Таблица1[[#This Row],[Сумма Приход]]+Таблица1[[#This Row],[Сумма Поддон]] -> 22990000 | O53: 700000 | P53: =Таблица1[[#This Row],[Цена Продажа]]-Таблица1[[#This Row],[Цена Приход]] -> 75000 | Q53: Фойда | R53: =Таблица1[[#This Row],[Блок Куб]]*Таблица1[[#This Row],[Цена Продажа]] -> 22982400 | S53: клентдан | T53: =Таблица1[[#This Row],[Сумма Продажа]]-Таблица1[[#This Row],[Сумма Приход]] -> 2462400
A54: =A53+1 -> 51 | B54: Газоблок | C54: Сардор ога | D54: Уткир мини | E54: 46210 | F54: 95 693 GBA | G54: 600x300x100 | H54: 32.832 | I54: 625000 | J54: =Таблица1[[#This Row],[Блок Куб]]*Таблица1[[#This Row],[Цена Приход]] -> 20520000 | K54: 19 | L54: 130000 | M54: =Таблица1[[#This Row],[Поддон Шт]]*Таблица1[[#This Row],[Цена Поддон]] -> 2470000 | N54: =Таблица1[[#This Row],[Сумма Приход]]+Таблица1[[#This Row],[Сумма Поддон]] -> 22990000 | O54: 700000 | P54: =Таблица1[[#This Row],[Цена Продажа]]-Таблица1[[#This Row],[Цена Приход]] -> 75000 | Q54: Фойда | R54: =Таблица1[[#This Row],[Блок Куб]]*Таблица1[[#This Row],[Цена Продажа]] -> 22982400 | S54: клентдан | T54: =Таблица1[[#This Row],[Сумма Продажа]]-Таблица1[[#This Row],[Сумма Приход]] -> 2462400
A55: =A54+1 -> 52 | B55: Газоблок | C55: Жамол 22-22 | D55: Фидато Груп | E55: 46210 | F55: 90 N 972 QA | G55: 600x240x200 | H55: 32.832 | I55: 500000 | J55: =Таблица1[[#This Row],[Блок Куб]]*Таблица1[[#This Row],[Цена Приход]] -> 16416000 | K55: 19 | L55: 130000 | M55: =Таблица1[[#This Row],[Поддон Шт]]*Таблица1[[#This Row],[Цена Поддон]] -> 2470000 | N55: =Таблица1[[#This Row],[Сумма Приход]]+Таблица1[[#This Row],[Сумма Поддон]] -> 18886000 | O55: 700000 | P55: =Таблица1[[#This Row],[Цена Продажа]]-Таблица1[[#This Row],[Цена Приход]] -> 200000 | Q55: Фойда | R55: =Таблица1[[#This Row],[Блок Куб]]*Таблица1[[#This Row],[Цена Продажа]] -> 22982400 | S55: Х | T55: =Таблица1[[#This Row],[Сумма Продажа]]-Таблица1[[#This Row],[Сумма Приход]] -> 6566400 | U55: Туланди
A56: =A55+1 -> 53 | B56: Газоблок | C56: Сардор ога | D56: Отабек дамирчи | E56: 46210 | F56: 90 340 FBA | G56: 600x300x100 | H56: 32.832 | I56: 625000 | J56: =Таблица1[[#This Row],[Блок Куб]]*Таблица1[[#This Row],[Цена Приход]] -> 20520000 | K56: 19 | L56: 130000 | M56: =Таблица1[[#This Row],[Поддон Шт]]*Таблица1[[#This Row],[Цена Поддон]] -> 2470000 | N56: =Таблица1[[#This Row],[Сумма Приход]]+Таблица1[[#This Row],[Сумма Поддон]] -> 22990000 | O56: 700000 | P56: =Таблица1[[#This Row],[Цена Продажа]]-Таблица1[[#This Row],[Цена Приход]] -> 75000 | Q56: Фойда | R56: =Таблица1[[#This Row],[Блок Куб]]*Таблица1[[#This Row],[Цена Продажа]] -> 22982400 | S56: клентдан | T56: =Таблица1[[#This Row],[Сумма Продажа]]-Таблица1[[#This Row],[Сумма Приход]] -> 2462400
A57: =A56+1 -> 54 | B57: Газоблок | C57: Сардор ога | D57: Уткир мини | E57: 46211 | F57: 90 779 EBA | G57: 600x300x200 | H57: 32.832 | I57: 625000 | J57: =Таблица1[[#This Row],[Блок Куб]]*Таблица1[[#This Row],[Цена Приход]] -> 20520000 | K57: 19 | L57: 130000 | M57: =Таблица1[[#This Row],[Поддон Шт]]*Таблица1[[#This Row],[Цена Поддон]] -> 2470000 | N57: =Таблица1[[#This Row],[Сумма Приход]]+Таблица1[[#This Row],[Сумма Поддон]] -> 22990000 | O57: 700000 | P57: =Таблица1[[#This Row],[Цена Продажа]]-Таблица1[[#This Row],[Цена Приход]] -> 75000 | Q57: Фойда | R57: =Таблица1[[#This Row],[Блок Куб]]*Таблица1[[#This Row],[Цена Продажа]] -> 22982400 | S57: клентдан | T57: =Таблица1[[#This Row],[Сумма Продажа]]-Таблица1[[#This Row],[Сумма Приход]] -> 2462400
A58: =A57+1 -> 55 | B58: Газоблок | C58: Темур | D58: Жасур Версал | E58: 46211 | F58: 95 G 198 SA | G58: 600x300x200 | H58: 32.832 | I58: 625000 | J58: =Таблица1[[#This Row],[Блок Куб]]*Таблица1[[#This Row],[Цена Приход]] -> 20520000 | K58: 19 | L58: 130000 | M58: =Таблица1[[#This Row],[Поддон Шт]]*Таблица1[[#This Row],[Цена Поддон]] -> 2470000 | N58: =Таблица1[[#This Row],[Сумма Приход]]+Таблица1[[#This Row],[Сумма Поддон]] -> 22990000 | O58: 700000 | P58: =Таблица1[[#This Row],[Цена Продажа]]-Таблица1[[#This Row],[Цена Приход]] -> 75000 | Q58: Фойда | R58: =Таблица1[[#This Row],[Блок Куб]]*Таблица1[[#This Row],[Цена Продажа]] -> 22982400 | S58: клентдан | T58: =Таблица1[[#This Row],[Сумма Продажа]]-Таблица1[[#This Row],[Сумма Приход]] -> 2462400
A59: =A58+1 -> 56 | B59: Газоблок | C59: Зафар ога | D59: Сулаймон Ога Хазарасп | E59: 46211 | F59: 80 726 ACA | G59: 600x300x200 | H59: 32.832 | I59: 625000 | J59: =Таблица1[[#This Row],[Блок Куб]]*Таблица1[[#This Row],[Цена Приход]] -> 20520000 | K59: 19 | L59: 130000 | M59: =Таблица1[[#This Row],[Поддон Шт]]*Таблица1[[#This Row],[Цена Поддон]] -> 2470000 | N59: =Таблица1[[#This Row],[Сумма Приход]]+Таблица1[[#This Row],[Сумма Поддон]] -> 22990000 | O59: 700000 | P59: =Таблица1[[#This Row],[Цена Продажа]]-Таблица1[[#This Row],[Цена Приход]] -> 75000 | Q59: Фойда | R59: =Таблица1[[#This Row],[Блок Куб]]*Таблица1[[#This Row],[Цена Продажа]] -> 22982400 | S59: клентдан | T59: =Таблица1[[#This Row],[Сумма Продажа]]-Таблица1[[#This Row],[Сумма Приход]] -> 2462400
A60: =A59+1 -> 57 | B60: Газоблок | C60: Темур | D60: Одилбек ога Ера хоус | E60: 46212 | F60: 80 C 385 CB | G60: 600x300x100 | H60: 32.832 | I60: 625000 | J60: =Таблица1[[#This Row],[Блок Куб]]*Таблица1[[#This Row],[Цена Приход]] -> 20520000 | K60: 19 | L60: 130000 | M60: =Таблица1[[#This Row],[Поддон Шт]]*Таблица1[[#This Row],[Цена Поддон]] -> 2470000 | N60: =Таблица1[[#This Row],[Сумма Приход]]+Таблица1[[#This Row],[Сумма Поддон]] -> 22990000 | O60: 700000 | P60: =Таблица1[[#This Row],[Цена Продажа]]-Таблица1[[#This Row],[Цена Приход]] -> 75000 | Q60: Фойда | R60: =Таблица1[[#This Row],[Блок Куб]]*Таблица1[[#This Row],[Цена Продажа]] -> 22982400 | S60: клентдан | T60: =Таблица1[[#This Row],[Сумма Продажа]]-Таблица1[[#This Row],[Сумма Приход]] -> 2462400
A61: =A60+1 -> 58 | B61: Газоблок | C61: Жамол 22-22 | D61: Фидато | E61: 46212 | F61: 95 194 LBA | G61: 600x240x200 | H61: 32.832 | I61: 625000 | J61: =Таблица1[[#This Row],[Блок Куб]]*Таблица1[[#This Row],[Цена Приход]] -> 20520000 | K61: 19 | L61: 130000 | M61: =Таблица1[[#This Row],[Поддон Шт]]*Таблица1[[#This Row],[Цена Поддон]] -> 2470000 | N61: =Таблица1[[#This Row],[Сумма Приход]]+Таблица1[[#This Row],[Сумма Поддон]] -> 22990000 | O61: 700000 | P61: =Таблица1[[#This Row],[Цена Продажа]]-Таблица1[[#This Row],[Цена Приход]] -> 75000 | Q61: Фойда | R61: =Таблица1[[#This Row],[Блок Куб]]*Таблица1[[#This Row],[Цена Продажа]] -> 22982400 | S61: клентдан | T61: =Таблица1[[#This Row],[Сумма Продажа]]-Таблица1[[#This Row],[Сумма Приход]] -> 2462400
A62: =A61+1 -> 59 | B62: Газоблок | C62: Темур | D62: Одилбек ога Ера хоус | E62: 46213 | F62: 90 S 196 AB | G62: 600x300x200 | H62: 32.832 | I62: 625000 | J62: =Таблица1[[#This Row],[Блок Куб]]*Таблица1[[#This Row],[Цена Приход]] -> 20520000 | K62: 19 | L62: 130000 | M62: =Таблица1[[#This Row],[Поддон Шт]]*Таблица1[[#This Row],[Цена Поддон]] -> 2470000 | N62: =Таблица1[[#This Row],[Сумма Приход]]+Таблица1[[#This Row],[Сумма Поддон]] -> 22990000 | O62: 700000 | P62: =Таблица1[[#This Row],[Цена Продажа]]-Таблица1[[#This Row],[Цена Приход]] -> 75000 | Q62: Фойда | R62: =Таблица1[[#This Row],[Блок Куб]]*Таблица1[[#This Row],[Цена Продажа]] -> 22982400 | S62: клентдан | T62: =Таблица1[[#This Row],[Сумма Продажа]]-Таблица1[[#This Row],[Сумма Приход]] -> 2462400
A63: =A62+1 -> 60 | B63: Газоблок | C63: Темур | D63: Мустофо Машал | E63: 46213 | F63: 95 A 242 TA | G63: 600x300x100 | H63: 32.832 | I63: 625000 | J63: =Таблица1[[#This Row],[Блок Куб]]*Таблица1[[#This Row],[Цена Приход]] -> 20520000 | K63: 19 | L63: 130000 | M63: =Таблица1[[#This Row],[Поддон Шт]]*Таблица1[[#This Row],[Цена Поддон]] -> 2470000 | N63: =Таблица1[[#This Row],[Сумма Приход]]+Таблица1[[#This Row],[Сумма Поддон]] -> 22990000 | O63: 700000 | P63: =Таблица1[[#This Row],[Цена Продажа]]-Таблица1[[#This Row],[Цена Приход]] -> 75000 | Q63: Фойда | R63: =Таблица1[[#This Row],[Блок Куб]]*Таблица1[[#This Row],[Цена Продажа]] -> 22982400 | S63: клентдан | T63: =Таблица1[[#This Row],[Сумма Продажа]]-Таблица1[[#This Row],[Сумма Приход]] -> 2462400
A64: =A67+1 -> 64 | B64: Газоблок | C64: Темур | D64: Журат Хонка | E64: 46213 | F64: 95 B 760 QA | G64: 600x300x200 | H64: 32.832 | I64: 625000 | J64: =Таблица1[[#This Row],[Блок Куб]]*Таблица1[[#This Row],[Цена Приход]] -> 20520000 | K64: 19 | L64: 130000 | M64: =Таблица1[[#This Row],[Поддон Шт]]*Таблица1[[#This Row],[Цена Поддон]] -> 2470000 | N64: =Таблица1[[#This Row],[Сумма Приход]]+Таблица1[[#This Row],[Сумма Поддон]] -> 22990000 | O64: 700000 | P64: =Таблица1[[#This Row],[Цена Продажа]]-Таблица1[[#This Row],[Цена Приход]] -> 75000 | Q64: Фойда | R64: =Таблица1[[#This Row],[Блок Куб]]*Таблица1[[#This Row],[Цена Продажа]] -> 22982400 | S64: клентдан | T64: =Таблица1[[#This Row],[Сумма Продажа]]-Таблица1[[#This Row],[Сумма Приход]] -> 2462400
A65: =A63+1 -> 61 | B65: Газоблок | C65: Жамол 22-22 | D65: Фидато | E65: 46214 | F65: 80 C 385 CB | G65: 600x240x200 | H65: 32.832 | I65: 625000 | J65: =Таблица1[[#This Row],[Блок Куб]]*Таблица1[[#This Row],[Цена Приход]] -> 20520000 | K65: 19 | L65: 130000 | M65: =Таблица1[[#This Row],[Поддон Шт]]*Таблица1[[#This Row],[Цена Поддон]] -> 2470000 | N65: =Таблица1[[#This Row],[Сумма Приход]]+Таблица1[[#This Row],[Сумма Поддон]] -> 22990000 | O65: 700000 | P65: =Таблица1[[#This Row],[Цена Продажа]]-Таблица1[[#This Row],[Цена Приход]] -> 75000 | Q65: Фойда | R65: =Таблица1[[#This Row],[Блок Куб]]*Таблица1[[#This Row],[Цена Продажа]] -> 22982400 | S65: клентдан | T65: =Таблица1[[#This Row],[Сумма Продажа]]-Таблица1[[#This Row],[Сумма Приход]] -> 2462400
A66: =A65+1 -> 62 | B66: Газоблок | C66: Шохрух ога | D66: Бунёдкор | E66: 46214 | F66: 30 N 341 SB | G66: 600x300x200 | H66: 32.832 | I66: 625000 | J66: =Таблица1[[#This Row],[Блок Куб]]*Таблица1[[#This Row],[Цена Приход]] -> 20520000 | K66: 19 | L66: 130000 | M66: =Таблица1[[#This Row],[Поддон Шт]]*Таблица1[[#This Row],[Цена Поддон]] -> 2470000 | N66: =Таблица1[[#This Row],[Сумма Приход]]+Таблица1[[#This Row],[Сумма Поддон]] -> 22990000 | O66: 700000 | P66: =Таблица1[[#This Row],[Цена Продажа]]-Таблица1[[#This Row],[Цена Приход]] -> 75000 | Q66: Фойда | R66: =Таблица1[[#This Row],[Блок Куб]]*Таблица1[[#This Row],[Цена Продажа]] -> 22982400 | S66: клентдан | T66: =Таблица1[[#This Row],[Сумма Продажа]]-Таблица1[[#This Row],[Сумма Приход]] -> 2462400
A67: =A66+1 -> 63 | B67: Газоблок | C67: Зафар ога | D67: Сулаймон ога Хазарасп | E67: 46214 | F67: 90 388 CBA | G67: 600x300x200 | H67: 32.832 | I67: 625000 | J67: =Таблица1[[#This Row],[Блок Куб]]*Таблица1[[#This Row],[Цена Приход]] -> 20520000 | K67: 19 | L67: 130000 | M67: =Таблица1[[#This Row],[Поддон Шт]]*Таблица1[[#This Row],[Цена Поддон]] -> 2470000 | N67: =Таблица1[[#This Row],[Сумма Приход]]+Таблица1[[#This Row],[Сумма Поддон]] -> 22990000 | O67: 700000 | P67: =Таблица1[[#This Row],[Цена Продажа]]-Таблица1[[#This Row],[Цена Приход]] -> 75000 | Q67: Фойда | R67: =Таблица1[[#This Row],[Блок Куб]]*Таблица1[[#This Row],[Цена Продажа]] -> 22982400 | S67: клентдан | T67: =Таблица1[[#This Row],[Сумма Продажа]]-Таблица1[[#This Row],[Сумма Приход]] -> 2462400
A68: =A64+1 -> 65 | B68: Газоблок | C68: Арслон ога | D68: Нахт клиент | E68: 08.07.2026 | F68: 90 G 991 FA | G68: 600x300x200 | H68: 34.56 | I68: 625000 | J68: =Таблица1[[#This Row],[Блок Куб]]*Таблица1[[#This Row],[Цена Приход]] -> 21600000 | K68: 20 | L68: 130000 | M68: =Таблица1[[#This Row],[Поддон Шт]]*Таблица1[[#This Row],[Цена Поддон]] -> 2600000 | N68: =Таблица1[[#This Row],[Сумма Приход]]+Таблица1[[#This Row],[Сумма Поддон]] -> 24200000 | O68: 700000 | P68: =Таблица1[[#This Row],[Цена Продажа]]-Таблица1[[#This Row],[Цена Приход]] -> 75000 | Q68: Фойда | R68: =Таблица1[[#This Row],[Блок Куб]]*Таблица1[[#This Row],[Цена Продажа]] -> 24192000 | T68: =Таблица1[[#This Row],[Сумма Продажа]]-Таблица1[[#This Row],[Сумма Приход]] -> 2592000
A69: =A68+1 -> 66 | B69: Газоблок | C69: Арслон ога | E69: 09.07.2026 | F69: 01 C 487 CB | G69: 600x300x100 | H69: 32.832 | I69: 625000 | J69: =Таблица1[[#This Row],[Блок Куб]]*Таблица1[[#This Row],[Цена Приход]] -> 20520000 | K69: 19 | L69: 130000 | M69: =Таблица1[[#This Row],[Поддон Шт]]*Таблица1[[#This Row],[Цена Поддон]] -> 2470000 | N69: =Таблица1[[#This Row],[Сумма Приход]]+Таблица1[[#This Row],[Сумма Поддон]] -> 22990000 | O69: 700000 | P69: =Таблица1[[#This Row],[Цена Продажа]]-Таблица1[[#This Row],[Цена Приход]] -> 75000 | Q69: Фойда | R69: =Таблица1[[#This Row],[Блок Куб]]*Таблица1[[#This Row],[Цена Продажа]] -> 22982400 | T69: =Таблица1[[#This Row],[Сумма Продажа]]-Таблица1[[#This Row],[Сумма Приход]] -> 2462400
A70: =A69+1 -> 67 | B70: Газоблок | C70: Арслон ога | E70: 09.07.2026 | F70: 90 L 555 TA | G70: 600x240x200 | H70: 32.832 | I70: 625000 | J70: =Таблица1[[#This Row],[Блок Куб]]*Таблица1[[#This Row],[Цена Приход]] -> 20520000 | K70: 19 | L70: 130000 | M70: =Таблица1[[#This Row],[Поддон Шт]]*Таблица1[[#This Row],[Цена Поддон]] -> 2470000 | N70: =Таблица1[[#This Row],[Сумма Приход]]+Таблица1[[#This Row],[Сумма Поддон]] -> 22990000 | O70: 700000 | P70: =Таблица1[[#This Row],[Цена Продажа]]-Таблица1[[#This Row],[Цена Приход]] -> 75000 | Q70: Фойда | R70: =Таблица1[[#This Row],[Блок Куб]]*Таблица1[[#This Row],[Цена Продажа]] -> 22982400 | T70: =Таблица1[[#This Row],[Сумма Продажа]]-Таблица1[[#This Row],[Сумма Приход]] -> 2462400
A71: =A70+1 -> 68 | B71: Газоблок | C71: Арслон ога | E71: 11.07.2026 | F71: 90 452 PBA | G71: 600x300x200 | H71: 32.832 | I71: 625000 | J71: =Таблица1[[#This Row],[Блок Куб]]*Таблица1[[#This Row],[Цена Приход]] -> 20520000 | K71: 19 | L71: 130000 | M71: =Таблица1[[#This Row],[Поддон Шт]]*Таблица1[[#This Row],[Цена Поддон]] -> 2470000 | N71: =Таблица1[[#This Row],[Сумма Приход]]+Таблица1[[#This Row],[Сумма Поддон]] -> 22990000 | O71: 700000 | P71: =Таблица1[[#This Row],[Цена Продажа]]-Таблица1[[#This Row],[Цена Приход]] -> 75000 | Q71: Фойда | R71: =Таблица1[[#This Row],[Блок Куб]]*Таблица1[[#This Row],[Цена Продажа]] -> 22982400 | T71: =Таблица1[[#This Row],[Сумма Продажа]]-Таблица1[[#This Row],[Сумма Приход]] -> 2462400
A72: =A71+1 -> 69 | B72: Газоблок | C72: Сардор ога | D72: Отабек дамирчи | E72: 46214 | F72: 90 M 660 LA | G72: 600x300x200 | H72: 32.832 | I72: 625000 | J72: =Таблица1[[#This Row],[Блок Куб]]*Таблица1[[#This Row],[Цена Приход]] -> 20520000 | K72: 19 | L72: 130000 | M72: =Таблица1[[#This Row],[Поддон Шт]]*Таблица1[[#This Row],[Цена Поддон]] -> 2470000 | N72: =Таблица1[[#This Row],[Сумма Приход]]+Таблица1[[#This Row],[Сумма Поддон]] -> 22990000 | O72: 700000 | P72: =Таблица1[[#This Row],[Цена Продажа]]-Таблица1[[#This Row],[Цена Приход]] -> 75000 | Q72: Фойда | R72: =Таблица1[[#This Row],[Блок Куб]]*Таблица1[[#This Row],[Цена Продажа]] -> 22982400 | S72: клентдан | T72: =Таблица1[[#This Row],[Сумма Продажа]]-Таблица1[[#This Row],[Сумма Приход]] -> 2462400 | U72: 2500000
A73: =A72+1 -> 70 | B73: Газоблок | C73: Темур | D73: Жасур Версал | E73: 46214 | F73: 95 O 144 GA | G73: 600x300x200 | H73: 32.832 | I73: 625000 | J73: =Таблица1[[#This Row],[Блок Куб]]*Таблица1[[#This Row],[Цена Приход]] -> 20520000 | K73: 19 | L73: 130000 | M73: =Таблица1[[#This Row],[Поддон Шт]]*Таблица1[[#This Row],[Цена Поддон]] -> 2470000 | N73: =Таблица1[[#This Row],[Сумма Приход]]+Таблица1[[#This Row],[Сумма Поддон]] -> 22990000 | O73: 700000 | P73: =Таблица1[[#This Row],[Цена Продажа]]-Таблица1[[#This Row],[Цена Приход]] -> 75000 | Q73: Фойда | R73: =Таблица1[[#This Row],[Блок Куб]]*Таблица1[[#This Row],[Цена Продажа]] -> 22982400 | S73: клентдан | T73: =Таблица1[[#This Row],[Сумма Продажа]]-Таблица1[[#This Row],[Сумма Приход]] -> 2462400 | U73: 2200000
A74: =A73+1 -> 71 | B74: Газоблок | C74: Шохрух ога | D74: Рустам Шпик | E74: 46214 | F74: 95 641 MBA | G74: 600x300x200 | H74: 32.832 | I74: 625000 | J74: =Таблица1[[#This Row],[Блок Куб]]*Таблица1[[#This Row],[Цена Приход]] -> 20520000 | K74: 19 | L74: 130000 | M74: =Таблица1[[#This Row],[Поддон Шт]]*Таблица1[[#This Row],[Цена Поддон]] -> 2470000 | N74: =Таблица1[[#This Row],[Сумма Приход]]+Таблица1[[#This Row],[Сумма Поддон]] -> 22990000 | O74: 700000 | P74: =Таблица1[[#This Row],[Цена Продажа]]-Таблица1[[#This Row],[Цена Приход]] -> 75000 | Q74: Фойда | R74: =Таблица1[[#This Row],[Блок Куб]]*Таблица1[[#This Row],[Цена Продажа]] -> 22982400 | T74: =Таблица1[[#This Row],[Сумма Продажа]]-Таблица1[[#This Row],[Сумма Приход]] -> 2462400
A75: =A74+1 -> 72 | B75: Газоблок | C75: Зафар ога | D75: Сулаймон ога Хазарасп | E75: 46214 | F75: 90 358 MBA | G75: 600x300x100 | H75: 32.832 | I75: 625000 | J75: =Таблица1[[#This Row],[Блок Куб]]*Таблица1[[#This Row],[Цена Приход]] -> 20520000 | K75: 19 | L75: 130000 | M75: =Таблица1[[#This Row],[Поддон Шт]]*Таблица1[[#This Row],[Цена Поддон]] -> 2470000 | N75: =Таблица1[[#This Row],[Сумма Приход]]+Таблица1[[#This Row],[Сумма Поддон]] -> 22990000 | O75: 700000 | P75: =Таблица1[[#This Row],[Цена Продажа]]-Таблица1[[#This Row],[Цена Приход]] -> 75000 | Q75: Фойда | R75: =Таблица1[[#This Row],[Блок Куб]]*Таблица1[[#This Row],[Цена Продажа]] -> 22982400 | S75: клентдан | T75: =Таблица1[[#This Row],[Сумма Продажа]]-Таблица1[[#This Row],[Сумма Приход]] -> 2462400 | U75: 2200000
A76: =A75+1 -> 73 | B76: Газоблок | C76: Зафар ога | D76: Сарвар ога Шовот | E76: 46214 | F76: 90 015 WAA | G76: 600x300x200 | H76: 32.832 | I76: 625000 | J76: =Таблица1[[#This Row],[Блок Куб]]*Таблица1[[#This Row],[Цена Приход]] -> 20520000 | K76: 19 | L76: 130000 | M76: =Таблица1[[#This Row],[Поддон Шт]]*Таблица1[[#This Row],[Цена Поддон]] -> 2470000 | N76: =Таблица1[[#This Row],[Сумма Приход]]+Таблица1[[#This Row],[Сумма Поддон]] -> 22990000 | O76: 700000 | P76: =Таблица1[[#This Row],[Цена Продажа]]-Таблица1[[#This Row],[Цена Приход]] -> 75000 | Q76: Фойда | R76: =Таблица1[[#This Row],[Блок Куб]]*Таблица1[[#This Row],[Цена Продажа]] -> 22982400 | S76: клентдан | T76: =Таблица1[[#This Row],[Сумма Продажа]]-Таблица1[[#This Row],[Сумма Приход]] -> 2462400 | U76: 2200000
A77: =A76+1 -> 74 | B77: Газоблок | C77: Шохрух ога | D77: 94-353-18-02 эликкала бостон | E77: 46215 | F77: 95 F 702 GA | G77: 600x300x200 | H77: 32.832 | I77: 625000 | J77: =Таблица1[[#This Row],[Блок Куб]]*Таблица1[[#This Row],[Цена Приход]] -> 20520000 | K77: 19 | L77: 130000 | M77: =Таблица1[[#This Row],[Поддон Шт]]*Таблица1[[#This Row],[Цена Поддон]] -> 2470000 | N77: =Таблица1[[#This Row],[Сумма Приход]]+Таблица1[[#This Row],[Сумма Поддон]] -> 22990000 | O77: 700000 | P77: =Таблица1[[#This Row],[Цена Продажа]]-Таблица1[[#This Row],[Цена Приход]] -> 75000 | Q77: Фойда | R77: =Таблица1[[#This Row],[Блок Куб]]*Таблица1[[#This Row],[Цена Продажа]] -> 22982400 | S77: Бизадан | T77: =Таблица1[[#This Row],[Сумма Продажа]]-Таблица1[[#This Row],[Сумма Приход]] -> 2462400 | U77: 2600000
A78: =A77+1 -> 75 | B78: Газоблок | C78: Арслон ога | E78: 46215 | F78: 85 L 457 HA | G78: 600x300x200 | H78: 32.832 | I78: 625000 | J78: =Таблица1[[#This Row],[Блок Куб]]*Таблица1[[#This Row],[Цена Приход]] -> 20520000 | K78: 19 | L78: 130000 | M78: =Таблица1[[#This Row],[Поддон Шт]]*Таблица1[[#This Row],[Цена Поддон]] -> 2470000 | N78: =Таблица1[[#This Row],[Сумма Приход]]+Таблица1[[#This Row],[Сумма Поддон]] -> 22990000 | O78: 700000 | P78: =Таблица1[[#This Row],[Цена Продажа]]-Таблица1[[#This Row],[Цена Приход]] -> 75000 | Q78: Фойда | R78: =Таблица1[[#This Row],[Блок Куб]]*Таблица1[[#This Row],[Цена Продажа]] -> 22982400 | T78: =Таблица1[[#This Row],[Сумма Продажа]]-Таблица1[[#This Row],[Сумма Приход]] -> 2462400
A79: =A78+1 -> 76 | B79: Газоблок | C79: Сардор ога | D79: Мамун Университети | E79: 46215 | F79: 90 999 EBA | G79: 600x300x200 | H79: 32.832 | I79: 625000 | J79: =Таблица1[[#This Row],[Блок Куб]]*Таблица1[[#This Row],[Цена Приход]] -> 20520000 | K79: 19 | L79: 130000 | M79: =Таблица1[[#This Row],[Поддон Шт]]*Таблица1[[#This Row],[Цена Поддон]] -> 2470000 | N79: =Таблица1[[#This Row],[Сумма Приход]]+Таблица1[[#This Row],[Сумма Поддон]] -> 22990000 | O79: 700000 | P79: =Таблица1[[#This Row],[Цена Продажа]]-Таблица1[[#This Row],[Цена Приход]] -> 75000 | Q79: Фойда | R79: =Таблица1[[#This Row],[Блок Куб]]*Таблица1[[#This Row],[Цена Продажа]] -> 22982400 | S79: клентдан | T79: =Таблица1[[#This Row],[Сумма Продажа]]-Таблица1[[#This Row],[Сумма Приход]] -> 2462400 | U79: 2200000
A80: =A79+1 -> 77 | B80: Газоблок | C80: Сардор ога | D80: Мамун Университети | E80: 46216 | F80: 90 924 LBA | G80: 600x300x100 | H80: 32.832 | I80: 625000 | J80: =Таблица1[[#This Row],[Блок Куб]]*Таблица1[[#This Row],[Цена Приход]] -> 20520000 | K80: 19 | L80: 130000 | M80: =Таблица1[[#This Row],[Поддон Шт]]*Таблица1[[#This Row],[Цена Поддон]] -> 2470000 | N80: =Таблица1[[#This Row],[Сумма Приход]]+Таблица1[[#This Row],[Сумма Поддон]] -> 22990000 | O80: 700000 | P80: =Таблица1[[#This Row],[Цена Продажа]]-Таблица1[[#This Row],[Цена Приход]] -> 75000 | Q80: Фойда | R80: =Таблица1[[#This Row],[Блок Куб]]*Таблица1[[#This Row],[Цена Продажа]] -> 22982400 | S80: клентдан | T80: =Таблица1[[#This Row],[Сумма Продажа]]-Таблица1[[#This Row],[Сумма Приход]] -> 2462400 | U80: 2200000
A81: =A80+1 -> 78 | B81: Газоблок | C81: Зафар ога | D81: Сулаймон ога Хазарасп | E81: 46216 | F81: 50 E 093 GB | G81: 600x300x200 | H81: 32.832 | I81: 625000 | J81: =Таблица1[[#This Row],[Блок Куб]]*Таблица1[[#This Row],[Цена Приход]] -> 20520000 | K81: 19 | L81: 130000 | M81: =Таблица1[[#This Row],[Поддон Шт]]*Таблица1[[#This Row],[Цена Поддон]] -> 2470000 | N81: =Таблица1[[#This Row],[Сумма Приход]]+Таблица1[[#This Row],[Сумма Поддон]] -> 22990000 | O81: 700000 | P81: =Таблица1[[#This Row],[Цена Продажа]]-Таблица1[[#This Row],[Цена Приход]] -> 75000 | Q81: Фойда | R81: =Таблица1[[#This Row],[Блок Куб]]*Таблица1[[#This Row],[Цена Продажа]] -> 22982400 | S81: клентдан | T81: =Таблица1[[#This Row],[Сумма Продажа]]-Таблица1[[#This Row],[Сумма Приход]] -> 2462400 | U81: 2500000
A82: =A81+1 -> 79 | B82: Газоблок | C82: Зафар ога | D82: Сарвар ога Шовот | E82: 46217 | F82: 75 084 GBA | G82: 600x300x100 | H82: 32.832 | I82: 625000 | J82: =Таблица1[[#This Row],[Блок Куб]]*Таблица1[[#This Row],[Цена Приход]] -> 20520000 | K82: 19 | L82: 130000 | M82: =Таблица1[[#This Row],[Поддон Шт]]*Таблица1[[#This Row],[Цена Поддон]] -> 2470000 | N82: =Таблица1[[#This Row],[Сумма Приход]]+Таблица1[[#This Row],[Сумма Поддон]] -> 22990000 | O82: 700000 | P82: =Таблица1[[#This Row],[Цена Продажа]]-Таблица1[[#This Row],[Цена Приход]] -> 75000 | Q82: Фойда | R82: =Таблица1[[#This Row],[Блок Куб]]*Таблица1[[#This Row],[Цена Продажа]] -> 22982400 | S82: клентдан | T82: =Таблица1[[#This Row],[Сумма Продажа]]-Таблица1[[#This Row],[Сумма Приход]] -> 2462400 | U82: 2500000
A83: =A82+1 -> 80 | B83: Газоблок | C83: Темур | D83: Жасур Версал | E83: 46216 | F83: 70 M 307 HB | G83: 600x300x100 | H83: 32.832 | I83: 625000 | J83: =Таблица1[[#This Row],[Блок Куб]]*Таблица1[[#This Row],[Цена Приход]] -> 20520000 | K83: 19 | L83: 130000 | M83: =Таблица1[[#This Row],[Поддон Шт]]*Таблица1[[#This Row],[Цена Поддон]] -> 2470000 | N83: =Таблица1[[#This Row],[Сумма Приход]]+Таблица1[[#This Row],[Сумма Поддон]] -> 22990000 | O83: 700000 | P83: =Таблица1[[#This Row],[Цена Продажа]]-Таблица1[[#This Row],[Цена Приход]] -> 75000 | Q83: Фойда | R83: =Таблица1[[#This Row],[Блок Куб]]*Таблица1[[#This Row],[Цена Продажа]] -> 22982400 | S83: клентдан | T83: =Таблица1[[#This Row],[Сумма Продажа]]-Таблица1[[#This Row],[Сумма Приход]] -> 2462400 | U83: 2300000
A84: =A83+1 -> 81 | B84: Газоблок | C84: Темур | D84: Жасур Версал | E84: 46216 | F84: 95 F 702 GA | G84: 600x300x200 | H84: 32.832 | I84: 625000 | J84: =Таблица1[[#This Row],[Блок Куб]]*Таблица1[[#This Row],[Цена Приход]] -> 20520000 | K84: 19 | L84: 130000 | M84: =Таблица1[[#This Row],[Поддон Шт]]*Таблица1[[#This Row],[Цена Поддон]] -> 2470000 | N84: =Таблица1[[#This Row],[Сумма Приход]]+Таблица1[[#This Row],[Сумма Поддон]] -> 22990000 | O84: 700000 | P84: =Таблица1[[#This Row],[Цена Продажа]]-Таблица1[[#This Row],[Цена Приход]] -> 75000 | Q84: Фойда | R84: =Таблица1[[#This Row],[Блок Куб]]*Таблица1[[#This Row],[Цена Продажа]] -> 22982400 | S84: клентдан | T84: =Таблица1[[#This Row],[Сумма Продажа]]-Таблица1[[#This Row],[Сумма Приход]] -> 2462400 | U84: 2300000
A85: =A84+1 -> 82 | B85: Газоблок | C85: Темур | D85: Одилбек ога Ера хоус | E85: 46216 | F85: 30 100 MAN | G85: 600x300x200 | H85: 32.832 | I85: 625000 | J85: =Таблица1[[#This Row],[Блок Куб]]*Таблица1[[#This Row],[Цена Приход]] -> 20520000 | K85: 19 | L85: 130000 | M85: =Таблица1[[#This Row],[Поддон Шт]]*Таблица1[[#This Row],[Цена Поддон]] -> 2470000 | N85: =Таблица1[[#This Row],[Сумма Приход]]+Таблица1[[#This Row],[Сумма Поддон]] -> 22990000 | O85: 700000 | P85: =Таблица1[[#This Row],[Цена Продажа]]-Таблица1[[#This Row],[Цена Приход]] -> 75000 | Q85: Фойда | R85: =Таблица1[[#This Row],[Блок Куб]]*Таблица1[[#This Row],[Цена Продажа]] -> 22982400 | S85: клентдан | T85: =Таблица1[[#This Row],[Сумма Продажа]]-Таблица1[[#This Row],[Сумма Приход]] -> 2462400 | U85: 2300000
A86: =A85+1 -> 83 | B86: Газоблок | C86: Темур | D86: Одилбек ога Ера хоус | E86: 46217 | F86: 25 S 005 FA | G86: 600x300x200 | H86: 32.832 | I86: 625000 | J86: =Таблица1[[#This Row],[Блок Куб]]*Таблица1[[#This Row],[Цена Приход]] -> 20520000 | K86: 19 | L86: 130000 | M86: =Таблица1[[#This Row],[Поддон Шт]]*Таблица1[[#This Row],[Цена Поддон]] -> 2470000 | N86: =Таблица1[[#This Row],[Сумма Приход]]+Таблица1[[#This Row],[Сумма Поддон]] -> 22990000 | O86: 700000 | P86: =Таблица1[[#This Row],[Цена Продажа]]-Таблица1[[#This Row],[Цена Приход]] -> 75000 | Q86: Фойда | R86: =Таблица1[[#This Row],[Блок Куб]]*Таблица1[[#This Row],[Цена Продажа]] -> 22982400 | S86: клентдан | T86: =Таблица1[[#This Row],[Сумма Продажа]]-Таблица1[[#This Row],[Сумма Приход]] -> 2462400 | U86: 2300000
A87: =A86+1 -> 84 | B87: Газоблок | C87: Жамол 22-22 | E87: 46216 | F87: 80 591 FCA | G87: 600x300x200 | H87: 32.832 | I87: 625000 | J87: =Таблица1[[#This Row],[Блок Куб]]*Таблица1[[#This Row],[Цена Приход]] -> 20520000 | K87: 19 | L87: 130000 | M87: =Таблица1[[#This Row],[Поддон Шт]]*Таблица1[[#This Row],[Цена Поддон]] -> 2470000 | N87: =Таблица1[[#This Row],[Сумма Приход]]+Таблица1[[#This Row],[Сумма Поддон]] -> 22990000 | O87: 700000 | P87: =Таблица1[[#This Row],[Цена Продажа]]-Таблица1[[#This Row],[Цена Приход]] -> 75000 | Q87: Фойда | R87: =Таблица1[[#This Row],[Блок Куб]]*Таблица1[[#This Row],[Цена Продажа]] -> 22982400 | T87: =Таблица1[[#This Row],[Сумма Продажа]]-Таблица1[[#This Row],[Сумма Приход]] -> 2462400
A88: =A87+1 -> 85 | B88: Газоблок | C88: Жамол 22-22 | E88: 46216 | F88: 90 K 034 BB | G88: 600x300x200 | H88: 32.832 | I88: 625000 | J88: =Таблица1[[#This Row],[Блок Куб]]*Таблица1[[#This Row],[Цена Приход]] -> 20520000 | K88: 19 | L88: 130000 | M88: =Таблица1[[#This Row],[Поддон Шт]]*Таблица1[[#This Row],[Цена Поддон]] -> 2470000 | N88: =Таблица1[[#This Row],[Сумма Приход]]+Таблица1[[#This Row],[Сумма Поддон]] -> 22990000 | O88: 700000 | P88: =Таблица1[[#This Row],[Цена Продажа]]-Таблица1[[#This Row],[Цена Приход]] -> 75000 | Q88: Фойда | R88: =Таблица1[[#This Row],[Блок Куб]]*Таблица1[[#This Row],[Цена Продажа]] -> 22982400 | T88: =Таблица1[[#This Row],[Сумма Продажа]]-Таблица1[[#This Row],[Сумма Приход]] -> 2462400
A89: =A88+1 -> 86 | B89: Газоблок | C89: Шохрух ога | E89: 46125 | F89: 95 044 WAA | G89: 600x300x200 | H89: 32.832 | I89: 625000 | J89: =Таблица1[[#This Row],[Блок Куб]]*Таблица1[[#This Row],[Цена Приход]] -> 20520000 | K89: 19 | L89: 130000 | M89: =Таблица1[[#This Row],[Поддон Шт]]*Таблица1[[#This Row],[Цена Поддон]] -> 2470000 | N89: =Таблица1[[#This Row],[Сумма Приход]]+Таблица1[[#This Row],[Сумма Поддон]] -> 22990000 | O89: 700000 | P89: =Таблица1[[#This Row],[Цена Продажа]]-Таблица1[[#This Row],[Цена Приход]] -> 75000 | Q89: Фойда | R89: =Таблица1[[#This Row],[Блок Куб]]*Таблица1[[#This Row],[Цена Продажа]] -> 22982400 | S89: клентдан | T89: =Таблица1[[#This Row],[Сумма Продажа]]-Таблица1[[#This Row],[Сумма Приход]] -> 2462400 | U89: 2400000
A90: =A89+1 -> 87 | B90: Газоблок | C90: Сардор ога | D90: накд клент | E90: 46216 | F90: 90 699 EBA | G90: 600x300x200 | H90: 25.92 | I90: 625000 | J90: =Таблица1[[#This Row],[Блок Куб]]*Таблица1[[#This Row],[Цена Приход]] -> 16200000 | K90: 15 | L90: 130000 | M90: =Таблица1[[#This Row],[Поддон Шт]]*Таблица1[[#This Row],[Цена Поддон]] -> 1950000 | N90: =Таблица1[[#This Row],[Сумма Приход]]+Таблица1[[#This Row],[Сумма Поддон]] -> 18150000 | O90: 700000 | P90: =Таблица1[[#This Row],[Цена Продажа]]-Таблица1[[#This Row],[Цена Приход]] -> 75000 | Q90: Фойда | R90: =Таблица1[[#This Row],[Блок Куб]]*Таблица1[[#This Row],[Цена Продажа]] -> 18144000 | S90: клентдан | T90: =Таблица1[[#This Row],[Сумма Продажа]]-Таблица1[[#This Row],[Сумма Приход]] -> 1944000 | U90: 2250000
A91: =A90+1 -> 88 | B91: Газоблок | C91: Шохрух ога | E91: 46216 | F91: 90 699 EBA | G91: 600x300x200 | H91: 6.912 | I91: 625000 | J91: =Таблица1[[#This Row],[Блок Куб]]*Таблица1[[#This Row],[Цена Приход]] -> 4320000 | K91: 4 | L91: 130000 | M91: =Таблица1[[#This Row],[Поддон Шт]]*Таблица1[[#This Row],[Цена Поддон]] -> 520000 | N91: =Таблица1[[#This Row],[Сумма Приход]]+Таблица1[[#This Row],[Сумма Поддон]] -> 4840000 | O91: 700000 | P91: =Таблица1[[#This Row],[Цена Продажа]]-Таблица1[[#This Row],[Цена Приход]] -> 75000 | Q91: Фойда | R91: =Таблица1[[#This Row],[Блок Куб]]*Таблица1[[#This Row],[Цена Продажа]] -> 4838400 | S91: клентдан | T91: =Таблица1[[#This Row],[Сумма Продажа]]-Таблица1[[#This Row],[Сумма Приход]] -> 518400 | U91: 450000
A92: =A91+1 -> 89 | J92: =Таблица1[[#This Row],[Блок Куб]]*Таблица1[[#This Row],[Цена Приход]] -> 0 | M92: =Таблица1[[#This Row],[Поддон Шт]]*Таблица1[[#This Row],[Цена Поддон]] -> 0 | N92: =Таблица1[[#This Row],[Сумма Приход]]+Таблица1[[#This Row],[Сумма Поддон]] -> 0 | P92: =Таблица1[[#This Row],[Цена Продажа]]-Таблица1[[#This Row],[Цена Приход]] -> 0 | R92: =Таблица1[[#This Row],[Блок Куб]]*Таблица1[[#This Row],[Цена Продажа]] -> 0 | T92: =Таблица1[[#This Row],[Сумма Продажа]]-Таблица1[[#This Row],[Сумма Приход]] -> 0
A93: =A92+1 -> 90 | J93: =Таблица1[[#This Row],[Блок Куб]]*Таблица1[[#This Row],[Цена Приход]] -> 0 | M93: =Таблица1[[#This Row],[Поддон Шт]]*Таблица1[[#This Row],[Цена Поддон]] -> 0 | N93: =Таблица1[[#This Row],[Сумма Приход]]+Таблица1[[#This Row],[Сумма Поддон]] -> 0 | P93: =Таблица1[[#This Row],[Цена Продажа]]-Таблица1[[#This Row],[Цена Приход]] -> 0 | R93: =Таблица1[[#This Row],[Блок Куб]]*Таблица1[[#This Row],[Цена Продажа]] -> 0 | T93: =Таблица1[[#This Row],[Сумма Продажа]]-Таблица1[[#This Row],[Сумма Приход]] -> 0
A94: =A93+1 -> 91 | J94: =Таблица1[[#This Row],[Блок Куб]]*Таблица1[[#This Row],[Цена Приход]] -> 0 | M94: =Таблица1[[#This Row],[Поддон Шт]]*Таблица1[[#This Row],[Цена Поддон]] -> 0 | N94: =Таблица1[[#This Row],[Сумма Приход]]+Таблица1[[#This Row],[Сумма Поддон]] -> 0 | P94: =Таблица1[[#This Row],[Цена Продажа]]-Таблица1[[#This Row],[Цена Приход]] -> 0 | R94: =Таблица1[[#This Row],[Блок Куб]]*Таблица1[[#This Row],[Цена Продажа]] -> 0 | T94: =Таблица1[[#This Row],[Сумма Продажа]]-Таблица1[[#This Row],[Сумма Приход]] -> 0
A95: =A94+1 -> 92 | J95: =Таблица1[[#This Row],[Блок Куб]]*Таблица1[[#This Row],[Цена Приход]] -> 0 | M95: =Таблица1[[#This Row],[Поддон Шт]]*Таблица1[[#This Row],[Цена Поддон]] -> 0 | N95: =Таблица1[[#This Row],[Сумма Приход]]+Таблица1[[#This Row],[Сумма Поддон]] -> 0 | P95: =Таблица1[[#This Row],[Цена Продажа]]-Таблица1[[#This Row],[Цена Приход]] -> 0 | R95: =Таблица1[[#This Row],[Блок Куб]]*Таблица1[[#This Row],[Цена Продажа]] -> 0 | T95: =Таблица1[[#This Row],[Сумма Продажа]]-Таблица1[[#This Row],[Сумма Приход]] -> 0
A96: =A95+1 -> 93 | J96: =Таблица1[[#This Row],[Блок Куб]]*Таблица1[[#This Row],[Цена Приход]] -> 0 | M96: =Таблица1[[#This Row],[Поддон Шт]]*Таблица1[[#This Row],[Цена Поддон]] -> 0 | N96: =Таблица1[[#This Row],[Сумма Приход]]+Таблица1[[#This Row],[Сумма Поддон]] -> 0 | P96: =Таблица1[[#This Row],[Цена Продажа]]-Таблица1[[#This Row],[Цена Приход]] -> 0 | R96: =Таблица1[[#This Row],[Блок Куб]]*Таблица1[[#This Row],[Цена Продажа]] -> 0 | T96: =Таблица1[[#This Row],[Сумма Продажа]]-Таблица1[[#This Row],[Сумма Приход]] -> 0
A97: =A96+1 -> 94 | J97: =Таблица1[[#This Row],[Блок Куб]]*Таблица1[[#This Row],[Цена Приход]] -> 0 | M97: =Таблица1[[#This Row],[Поддон Шт]]*Таблица1[[#This Row],[Цена Поддон]] -> 0 | N97: =Таблица1[[#This Row],[Сумма Приход]]+Таблица1[[#This Row],[Сумма Поддон]] -> 0 | P97: =Таблица1[[#This Row],[Цена Продажа]]-Таблица1[[#This Row],[Цена Приход]] -> 0 | R97: =Таблица1[[#This Row],[Блок Куб]]*Таблица1[[#This Row],[Цена Продажа]] -> 0 | T97: =Таблица1[[#This Row],[Сумма Продажа]]-Таблица1[[#This Row],[Сумма Приход]] -> 0
A98: =A97+1 -> 95 | J98: =Таблица1[[#This Row],[Блок Куб]]*Таблица1[[#This Row],[Цена Приход]] -> 0 | M98: =Таблица1[[#This Row],[Поддон Шт]]*Таблица1[[#This Row],[Цена Поддон]] -> 0 | N98: =Таблица1[[#This Row],[Сумма Приход]]+Таблица1[[#This Row],[Сумма Поддон]] -> 0 | P98: =Таблица1[[#This Row],[Цена Продажа]]-Таблица1[[#This Row],[Цена Приход]] -> 0 | R98: =Таблица1[[#This Row],[Блок Куб]]*Таблица1[[#This Row],[Цена Продажа]] -> 0 | T98: =Таблица1[[#This Row],[Сумма Продажа]]-Таблица1[[#This Row],[Сумма Приход]] -> 0
A99: =A98+1 -> 96 | J99: =Таблица1[[#This Row],[Блок Куб]]*Таблица1[[#This Row],[Цена Приход]] -> 0 | M99: =Таблица1[[#This Row],[Поддон Шт]]*Таблица1[[#This Row],[Цена Поддон]] -> 0 | N99: =Таблица1[[#This Row],[Сумма Приход]]+Таблица1[[#This Row],[Сумма Поддон]] -> 0 | P99: =Таблица1[[#This Row],[Цена Продажа]]-Таблица1[[#This Row],[Цена Приход]] -> 0 | R99: =Таблица1[[#This Row],[Блок Куб]]*Таблица1[[#This Row],[Цена Продажа]] -> 0 | T99: =Таблица1[[#This Row],[Сумма Продажа]]-Таблица1[[#This Row],[Сумма Приход]] -> 0
A100: =A99+1 -> 97 | J100: =Таблица1[[#This Row],[Блок Куб]]*Таблица1[[#This Row],[Цена Приход]] -> 0 | M100: =Таблица1[[#This Row],[Поддон Шт]]*Таблица1[[#This Row],[Цена Поддон]] -> 0 | N100: =Таблица1[[#This Row],[Сумма Приход]]+Таблица1[[#This Row],[Сумма Поддон]] -> 0 | P100: =Таблица1[[#This Row],[Цена Продажа]]-Таблица1[[#This Row],[Цена Приход]] -> 0 | R100: =Таблица1[[#This Row],[Блок Куб]]*Таблица1[[#This Row],[Цена Продажа]] -> 0 | T100: =Таблица1[[#This Row],[Сумма Продажа]]-Таблица1[[#This Row],[Сумма Приход]] -> 0
A101: =A100+1 -> 98 | J101: =Таблица1[[#This Row],[Блок Куб]]*Таблица1[[#This Row],[Цена Приход]] -> 0 | M101: =Таблица1[[#This Row],[Поддон Шт]]*Таблица1[[#This Row],[Цена Поддон]] -> 0 | N101: =Таблица1[[#This Row],[Сумма Приход]]+Таблица1[[#This Row],[Сумма Поддон]] -> 0 | P101: =Таблица1[[#This Row],[Цена Продажа]]-Таблица1[[#This Row],[Цена Приход]] -> 0 | R101: =Таблица1[[#This Row],[Блок Куб]]*Таблица1[[#This Row],[Цена Продажа]] -> 0 | T101: =Таблица1[[#This Row],[Сумма Продажа]]-Таблица1[[#This Row],[Сумма Приход]] -> 0
A102: =A101+1 -> 99 | J102: =Таблица1[[#This Row],[Блок Куб]]*Таблица1[[#This Row],[Цена Приход]] -> 0 | M102: =Таблица1[[#This Row],[Поддон Шт]]*Таблица1[[#This Row],[Цена Поддон]] -> 0 | N102: =Таблица1[[#This Row],[Сумма Приход]]+Таблица1[[#This Row],[Сумма Поддон]] -> 0 | P102: =Таблица1[[#This Row],[Цена Продажа]]-Таблица1[[#This Row],[Цена Приход]] -> 0 | R102: =Таблица1[[#This Row],[Блок Куб]]*Таблица1[[#This Row],[Цена Продажа]] -> 0 | T102: =Таблица1[[#This Row],[Сумма Продажа]]-Таблица1[[#This Row],[Сумма Приход]] -> 0
A103: =A102+1 -> 100 | J103: =Таблица1[[#This Row],[Блок Куб]]*Таблица1[[#This Row],[Цена Приход]] -> 0 | M103: =Таблица1[[#This Row],[Поддон Шт]]*Таблица1[[#This Row],[Цена Поддон]] -> 0 | N103: =Таблица1[[#This Row],[Сумма Приход]]+Таблица1[[#This Row],[Сумма Поддон]] -> 0 | P103: =Таблица1[[#This Row],[Цена Продажа]]-Таблица1[[#This Row],[Цена Приход]] -> 0 | R103: =Таблица1[[#This Row],[Блок Куб]]*Таблица1[[#This Row],[Цена Продажа]] -> 0 | T103: =Таблица1[[#This Row],[Сумма Продажа]]-Таблица1[[#This Row],[Сумма Приход]] -> 0
... A1118: =A1117+1 -> 1115 | J1118: =Таблица1[[#This Row],[Блок Куб]]*Таблица1[[#This Row],[Цена Приход]] -> 0 | M1118: =Таблица1[[#This Row],[Поддон Шт]]*Таблица1[[#This Row],[Цена Поддон]] -> 0 | N1118: =Таблица1[[#This Row],[Сумма Приход]]+Таблица1[[#This Row],[Сумма Поддон]] -> 0 | P1118: =Таблица1[[#This Row],[Цена Продажа]]-Таблица1[[#This Row],[Цена Приход]] -> 0 | R1118: =Таблица1[[#This Row],[Блок Куб]]*Таблица1[[#This Row],[Цена Продажа]] -> 0 | T1118: =Таблица1[[#This Row],[Сумма Продажа]]-Таблица1[[#This Row],[Сумма Приход]] -> 0

Sheet 1-Урганч Тамирлаш
D1: 1-Урганч Тамирлаш
A2: ID-Клиента | F2: =Таблица2133990[[#Totals],[2]]+-Таблица2133990[[#Totals],[16]] -> -6929600
A3: № | B3: Дата | C3: Сумма | D3: Перемечание | E3: Возврат паддон | F3: № | G3: Дата | H3: Авто | I3: Размер | J3: Блок Куб | K3: Поддон Шт | L3: Цена Продажа | M3: Сумма
C5: =Таблица2133990[[#Totals],[2]] -> 130570000 | E5: =SUM(Таблица2133990[4]) -> 0 | K5: =Таблица2133990[[#Totals],[1132]] -> 112 | M5: =Таблица2133990[[#Totals],[16]] -> 1.374996e+08
B6: 1 | C6: 2 | D6: 3 | E6: 4 | F6: 9 | G6: 10 | H6: 11 | I6: 114 | J6: 113 | K6: 1132 | L6: 15 | M6: 16
A7: 1 | C7: 45570000 | F7: =Таблица2133990[[#This Row],[ ]] -> 1 | G7: 46197 | H7: 95 G 851 NA | I7: 600x300x200 | J7: 31.104 | K7: 18 | L7: 732542.44 | M7: =Таблица2133990[[#This Row],[113]]*(Таблица2133990[[#This Row],[15]]) -> 22785000
A8: 2 | B8: 46206 | C8: 85000000 | D8: URGANCH TAMIRLASH | F8: =Таблица2133990[[#This Row],[ ]] -> 2 | G8: 46197 | H8: 40 Y 173 KB | I8: 600x300x200 | J8: 31.104 | K8: 18 | L8: 732542.44 | M8: =Таблица2133990[[#This Row],[113]]*(Таблица2133990[[#This Row],[15]]) -> 22785000
A9: 3 | F9: =Таблица2133990[[#This Row],[ ]] -> 3 | G9: 46206 | H9: 40 F 105 RB | I9: 600x300x200 | J9: 32.832 | K9: 19 | L9: 700000 | M9: =Таблица2133990[[#This Row],[113]]*(Таблица2133990[[#This Row],[15]]) -> 22982400
A10: 4 | F10: =Таблица2133990[[#This Row],[ ]] -> 4 | G10: 46206 | H10: 90 K 295 QA | I10: 600x300x200 | J10: 32.832 | K10: 19 | L10: 700000 | M10: =Таблица2133990[[#This Row],[113]]*(Таблица2133990[[#This Row],[15]]) -> 22982400
A11: 5 | F11: =Таблица2133990[[#This Row],[ ]] -> 5 | G11: 46206 | H11: 90 N 831 HA | I11: 600x300x200 | J11: 32.832 | K11: 19 | L11: 700000 | M11: =Таблица2133990[[#This Row],[113]]*(Таблица2133990[[#This Row],[15]]) -> 22982400
A12: 6 | F12: =Таблица2133990[[#This Row],[ ]] -> 6 | G12: 46206 | H12: 90 255 FBA | I12: 600x300x200 | J12: 32.832 | K12: 19 | L12: 700000 | M12: =Таблица2133990[[#This Row],[113]]*(Таблица2133990[[#This Row],[15]]) -> 22982400
A13: 7 | F13: =Таблица2133990[[#This Row],[ ]] -> 7 | M13: =Таблица2133990[[#This Row],[113]]*(Таблица2133990[[#This Row],[15]]) -> 0
A14: 8 | F14: =Таблица2133990[[#This Row],[ ]] -> 8 | M14: =Таблица2133990[[#This Row],[113]]*(Таблица2133990[[#This Row],[15]]) -> 0
A15: 9 | F15: =Таблица2133990[[#This Row],[ ]] -> 9 | M15: =Таблица2133990[[#This Row],[113]]*(Таблица2133990[[#This Row],[15]]) -> 0
A16: 10 | F16: =Таблица2133990[[#This Row],[ ]] -> 10 | M16: =Таблица2133990[[#This Row],[113]]*(Таблица2133990[[#This Row],[15]]) -> 0
A17: 11 | F17: =Таблица2133990[[#This Row],[ ]] -> 11 | M17: =Таблица2133990[[#This Row],[113]]*(Таблица2133990[[#This Row],[15]]) -> 0
A18: 12 | F18: =Таблица2133990[[#This Row],[ ]] -> 12 | M18: =Таблица2133990[[#This Row],[113]]*(Таблица2133990[[#This Row],[15]]) -> 0
A19: 13 | F19: =Таблица2133990[[#This Row],[ ]] -> 13 | M19: =Таблица2133990[[#This Row],[113]]*(Таблица2133990[[#This Row],[15]]) -> 0
A20: 14 | F20: =Таблица2133990[[#This Row],[ ]] -> 14 | M20: =Таблица2133990[[#This Row],[113]]*(Таблица2133990[[#This Row],[15]]) -> 0
A21: 15 | F21: =Таблица2133990[[#This Row],[ ]] -> 15 | M21: =Таблица2133990[[#This Row],[113]]*(Таблица2133990[[#This Row],[15]]) -> 0
A22: 16 | F22: =Таблица2133990[[#This Row],[ ]] -> 16 | M22: =Таблица2133990[[#This Row],[113]]*(Таблица2133990[[#This Row],[15]]) -> 0
A23: 17 | F23: =Таблица2133990[[#This Row],[ ]] -> 17 | M23: =Таблица2133990[[#This Row],[113]]*(Таблица2133990[[#This Row],[15]]) -> 0
A24: 18 | F24: =Таблица2133990[[#This Row],[ ]] -> 18 | M24: =Таблица2133990[[#This Row],[113]]*(Таблица2133990[[#This Row],[15]]) -> 0
... A49: 43 | F49: =Таблица2133990[[#This Row],[ ]] -> 43 | M49: =Таблица2133990[[#This Row],[113]]*(Таблица2133990[[#This Row],[15]]) -> 0
C50: =SUBTOTAL(109,Таблица2133990[2]) -> 130570000 | K50: =SUBTOTAL(109,Таблица2133990[1132]) -> 112 | M50: =SUBTOTAL(109,Таблица2133990[16]) -> 1.374996e+08

Sheet 1-Инвест Холдинг
D1: 1-Инвест Холдинг
A2: ID-Клиента | F2: =Таблица213399028[[#Totals],[2]]+-Таблица213399028[[#Totals],[16]] -> 0
A3: № | B3: Дата | C3: Сумма | D3: Примечание | E3: Возврат паддон | F3: № | G3: Дата | H3: Авто | I3: Размер | J3: Блок Куб | K3: Поддон Шт | L3: От | M3: Сумма
C5: =Таблица213399028[[#Totals],[2]] -> 67737600 | E5: =SUM(Таблица213399028[4]) -> 0 | K5: =Таблица213399028[[#Totals],[1132]] -> 56 | M5: =Таблица213399028[[#Totals],[16]] -> 67737600
B6: 1 | C6: 2 | D6: 3 | E6: 4 | F6: 9 | G6: 10 | H6: 11 | I6: 114 | J6: 113 | K6: 1132 | L6: 15 | M6: 16
A7: 1 | B7: 46205 | C7: 67737600 | D7: Хоразм Инвест Холдинг | F7: =Таблица213399028[[#This Row],[ ]] -> 1 | G7: 46197 | H7: 90 X 700 CA | I7: 600x300x200 | J7: 31.104 | K7: 18 | L7: 700000 | M7: =Таблица213399028[[#This Row],[113]]*Таблица213399028[[#This Row],[15]] -> 21772800
A8: 2 | F8: =Таблица213399028[[#This Row],[ ]] -> 2 | G8: 46197 | H8: 90 G 429 CA | I8: 600x300x200 | J8: 32.832 | K8: 19 | L8: 700000 | M8: =Таблица213399028[[#This Row],[113]]*Таблица213399028[[#This Row],[15]] -> 22982400
A9: 3 | F9: =Таблица213399028[[#This Row],[ ]] -> 3 | G9: 46198 | H9: 30 N 113 MB | I9: 600x300x200 | J9: 32.832 | K9: 19 | L9: 700000 | M9: =Таблица213399028[[#This Row],[113]]*Таблица213399028[[#This Row],[15]] -> 22982400
A10: 4 | F10: =Таблица213399028[[#This Row],[ ]] -> 4 | M10: =Таблица213399028[[#This Row],[113]]*Таблица213399028[[#This Row],[15]] -> 0
A11: 5 | F11: =Таблица213399028[[#This Row],[ ]] -> 5 | M11: =Таблица213399028[[#This Row],[113]]*Таблица213399028[[#This Row],[15]] -> 0
A12: 6 | F12: =Таблица213399028[[#This Row],[ ]] -> 6 | M12: =Таблица213399028[[#This Row],[113]]*Таблица213399028[[#This Row],[15]] -> 0
A13: 7 | F13: =Таблица213399028[[#This Row],[ ]] -> 7 | M13: =Таблица213399028[[#This Row],[113]]*Таблица213399028[[#This Row],[15]] -> 0
A14: 8 | F14: =Таблица213399028[[#This Row],[ ]] -> 8 | M14: =Таблица213399028[[#This Row],[113]]*Таблица213399028[[#This Row],[15]] -> 0
A15: 9 | F15: =Таблица213399028[[#This Row],[ ]] -> 9 | M15: =Таблица213399028[[#This Row],[113]]*Таблица213399028[[#This Row],[15]] -> 0
A16: 10 | F16: =Таблица213399028[[#This Row],[ ]] -> 10 | M16: =Таблица213399028[[#This Row],[113]]*Таблица213399028[[#This Row],[15]] -> 0
A17: 11 | F17: =Таблица213399028[[#This Row],[ ]] -> 11 | M17: =Таблица213399028[[#This Row],[113]]*Таблица213399028[[#This Row],[15]] -> 0
A18: 12 | F18: =Таблица213399028[[#This Row],[ ]] -> 12 | M18: =Таблица213399028[[#This Row],[113]]*Таблица213399028[[#This Row],[15]] -> 0
A19: 13 | F19: =Таблица213399028[[#This Row],[ ]] -> 13 | M19: =Таблица213399028[[#This Row],[113]]*Таблица213399028[[#This Row],[15]] -> 0
A20: 14 | F20: =Таблица213399028[[#This Row],[ ]] -> 14 | M20: =Таблица213399028[[#This Row],[113]]*Таблица213399028[[#This Row],[15]] -> 0
A21: 15 | F21: =Таблица213399028[[#This Row],[ ]] -> 15 | M21: =Таблица213399028[[#This Row],[113]]*Таблица213399028[[#This Row],[15]] -> 0
... A49: 43 | F49: =Таблица213399028[[#This Row],[ ]] -> 43 | M49: =Таблица213399028[[#This Row],[113]]*Таблица213399028[[#This Row],[15]] -> 0
C50: =SUBTOTAL(109,Таблица213399028[2]) -> 67737600 | K50: =SUBTOTAL(109,Таблица213399028[1132]) -> 56 | M50: =SUBTOTAL(109,Таблица213399028[16]) -> 67737600

Sheet 1-Нормат Умидбек
D1: 1-Нормат Умидбек
A2: ID-Клиента | F2: =Таблица213399029[[#Totals],[2]]+-Таблица213399029[[#Totals],[16]] -> 0
A3: № | B3: Дата | C3: Сумма | D3: Примечание | E3: Возврат паддон | F3: № | G3: Дата | H3: Авто | I3: Размер | J3: Блок Куб | K3: Поддон Шт | L3: От | M3: Сумма
C5: =Таблица213399029[[#Totals],[2]] -> 72394560 | E5: =SUM(Таблица213399029[4]) -> 0 | K5: =Таблица213399029[[#Totals],[1132]] -> 57 | M5: =Таблица213399029[[#Totals],[16]] -> 72394560
B6: 1 | C6: 2 | D6: 3 | E6: 4 | F6: 9 | G6: 10 | H6: 11 | I6: 114 | J6: 113 | K6: 1132 | L6: 15 | M6: 16
A7: 1 | B7: 46205 | C7: 72394560 | D7: NORMAT UMIDBEK MCHJ | F7: =Таблица213399029[[#This Row],[ ]] -> 1 | G7: 46198 | H7: 50 R 575 CB | I7: 600x300x200 | J7: 32.832 | K7: 19 | L7: 735000 | M7: =Таблица213399029[[#This Row],[113]]*Таблица213399029[[#This Row],[15]] -> 24131520
A8: 2 | F8: =Таблица213399029[[#This Row],[ ]] -> 2 | G8: 46198 | H8: 30 784 WBA | I8: 600x300x200 | J8: 32.832 | K8: 19 | L8: 735000 | M8: =Таблица213399029[[#This Row],[113]]*Таблица213399029[[#This Row],[15]] -> 24131520
A9: 3 | F9: =Таблица213399029[[#This Row],[ ]] -> 3 | G9: 46198 | H9: VI-004-KT | I9: 600x300x200 | J9: 32.832 | K9: 19 | L9: 735000 | M9: =Таблица213399029[[#This Row],[113]]*Таблица213399029[[#This Row],[15]] -> 24131520
A10: 4 | F10: =Таблица213399029[[#This Row],[ ]] -> 4 | M10: =Таблица213399029[[#This Row],[113]]*Таблица213399029[[#This Row],[15]] -> 0
A11: 5 | F11: =Таблица213399029[[#This Row],[ ]] -> 5 | M11: =Таблица213399029[[#This Row],[113]]*Таблица213399029[[#This Row],[15]] -> 0
A12: 6 | F12: =Таблица213399029[[#This Row],[ ]] -> 6 | M12: =Таблица213399029[[#This Row],[113]]*Таблица213399029[[#This Row],[15]] -> 0
A13: 7 | F13: =Таблица213399029[[#This Row],[ ]] -> 7 | M13: =Таблица213399029[[#This Row],[113]]*Таблица213399029[[#This Row],[15]] -> 0
A14: 8 | F14: =Таблица213399029[[#This Row],[ ]] -> 8 | M14: =Таблица213399029[[#This Row],[113]]*Таблица213399029[[#This Row],[15]] -> 0
A15: 9 | F15: =Таблица213399029[[#This Row],[ ]] -> 9 | M15: =Таблица213399029[[#This Row],[113]]*Таблица213399029[[#This Row],[15]] -> 0
A16: 10 | F16: =Таблица213399029[[#This Row],[ ]] -> 10 | M16: =Таблица213399029[[#This Row],[113]]*Таблица213399029[[#This Row],[15]] -> 0
A17: 11 | F17: =Таблица213399029[[#This Row],[ ]] -> 11 | M17: =Таблица213399029[[#This Row],[113]]*Таблица213399029[[#This Row],[15]] -> 0
A18: 12 | F18: =Таблица213399029[[#This Row],[ ]] -> 12 | M18: =Таблица213399029[[#This Row],[113]]*Таблица213399029[[#This Row],[15]] -> 0
A19: 13 | F19: =Таблица213399029[[#This Row],[ ]] -> 13 | M19: =Таблица213399029[[#This Row],[113]]*Таблица213399029[[#This Row],[15]] -> 0
A20: 14 | F20: =Таблица213399029[[#This Row],[ ]] -> 14 | M20: =Таблица213399029[[#This Row],[113]]*Таблица213399029[[#This Row],[15]] -> 0
A21: 15 | F21: =Таблица213399029[[#This Row],[ ]] -> 15 | M21: =Таблица213399029[[#This Row],[113]]*Таблица213399029[[#This Row],[15]] -> 0
... A49: 43 | F49: =Таблица213399029[[#This Row],[ ]] -> 43 | M49: =Таблица213399029[[#This Row],[113]]*Таблица213399029[[#This Row],[15]] -> 0
C50: =SUBTOTAL(109,Таблица213399029[2]) -> 72394560 | K50: =SUBTOTAL(109,Таблица213399029[1132]) -> 57 | M50: =SUBTOTAL(109,Таблица213399029[16]) -> 72394560

Sheet 1-Ирригатсия темир бетон
D1: 1-Ирригатсия темир бетон
A2: ID-Клиента | F2: =Таблица2133990291011[[#Totals],[2]]+-Таблица2133990291011[[#Totals],[16]] -> 8700480
A3: № | B3: Дата | C3: Сумма | D3: Примечание | E3: Возврат паддон | F3: № | G3: Дата | H3: Авто | I3: Размер | J3: Блок Куб | K3: Поддон Шт | L3: От | M3: Сумма
C5: =Таблица2133990291011[[#Totals],[2]] -> 32832000 | E5: =SUM(Таблица2133990291011[4]) -> 0 | K5: =Таблица2133990291011[[#Totals],[1132]] -> 19 | M5: =Таблица2133990291011[[#Totals],[16]] -> 24131520
B6: 1 | C6: 2 | D6: 3 | E6: 4 | F6: 9 | G6: 10 | H6: 11 | I6: 114 | J6: 113 | K6: 1132 | L6: 15 | M6: 16
A7: 1 | B7: 46211 | C7: 32832000 | D7: Ирригатсия темир бетон | F7: =Таблица2133990291011[[#This Row],[ ]] -> 1 | G7: 46203 | H7: 25 Q 068 OA | I7: 600x300x200 | J7: 32.832 | K7: 19 | L7: 735000 | M7: =Таблица2133990291011[[#This Row],[113]]*Таблица2133990291011[[#This Row],[15]] -> 24131520
A8: 2 | F8: =Таблица2133990291011[[#This Row],[ ]] -> 2 | M8: =Таблица2133990291011[[#This Row],[113]]*Таблица2133990291011[[#This Row],[15]] -> 0
A9: 3 | F9: =Таблица2133990291011[[#This Row],[ ]] -> 3 | M9: =Таблица2133990291011[[#This Row],[113]]*Таблица2133990291011[[#This Row],[15]] -> 0
A10: 4 | F10: =Таблица2133990291011[[#This Row],[ ]] -> 4 | M10: =Таблица2133990291011[[#This Row],[113]]*Таблица2133990291011[[#This Row],[15]] -> 0
A11: 5 | F11: =Таблица2133990291011[[#This Row],[ ]] -> 5 | M11: =Таблица2133990291011[[#This Row],[113]]*Таблица2133990291011[[#This Row],[15]] -> 0
A12: 6 | F12: =Таблица2133990291011[[#This Row],[ ]] -> 6 | M12: =Таблица2133990291011[[#This Row],[113]]*Таблица2133990291011[[#This Row],[15]] -> 0
A13: 7 | F13: =Таблица2133990291011[[#This Row],[ ]] -> 7 | M13: =Таблица2133990291011[[#This Row],[113]]*Таблица2133990291011[[#This Row],[15]] -> 0
A14: 8 | F14: =Таблица2133990291011[[#This Row],[ ]] -> 8 | M14: =Таблица2133990291011[[#This Row],[113]]*Таблица2133990291011[[#This Row],[15]] -> 0
A15: 9 | F15: =Таблица2133990291011[[#This Row],[ ]] -> 9 | M15: =Таблица2133990291011[[#This Row],[113]]*Таблица2133990291011[[#This Row],[15]] -> 0
A16: 10 | F16: =Таблица2133990291011[[#This Row],[ ]] -> 10 | M16: =Таблица2133990291011[[#This Row],[113]]*Таблица2133990291011[[#This Row],[15]] -> 0
A17: 11 | F17: =Таблица2133990291011[[#This Row],[ ]] -> 11 | M17: =Таблица2133990291011[[#This Row],[113]]*Таблица2133990291011[[#This Row],[15]] -> 0
A18: 12 | F18: =Таблица2133990291011[[#This Row],[ ]] -> 12 | M18: =Таблица2133990291011[[#This Row],[113]]*Таблица2133990291011[[#This Row],[15]] -> 0
A19: 13 | F19: =Таблица2133990291011[[#This Row],[ ]] -> 13 | M19: =Таблица2133990291011[[#This Row],[113]]*Таблица2133990291011[[#This Row],[15]] -> 0
... A49: 43 | F49: =Таблица2133990291011[[#This Row],[ ]] -> 43 | M49: =Таблица2133990291011[[#This Row],[113]]*Таблица2133990291011[[#This Row],[15]] -> 0
C50: =SUBTOTAL(109,Таблица2133990291011[2]) -> 32832000 | K50: =SUBTOTAL(109,Таблица2133990291011[1132]) -> 19 | M50: =SUBTOTAL(109,Таблица2133990291011[16]) -> 24131520

Sheet 1-Фидато Груп
D1: 1-Фидато Груп
A2: ID-Клиента | F2: =Таблица21339902910[[#Totals],[2]]+-Таблица21339902910[[#Totals],[16]] -> -24983520
A3: № | B3: Дата | C3: Сумма | D3: Примечание | E3: Возврат паддон | F3: № | G3: Дата | H3: Авто | I3: Размер | J3: Блок Куб | K3: Поддон Шт | L3: От | M3: Сумма
C5: =Таблица21339902910[[#Totals],[2]] -> 68916000 | E5: =SUM(Таблица21339902910[4]) -> 0 | K5: =Таблица21339902910[[#Totals],[1132]] -> 76 | M5: =Таблица21339902910[[#Totals],[16]] -> 93899520
B6: 1 | C6: 2 | D6: 3 | E6: 4 | F6: 9 | G6: 10 | H6: 11 | I6: 114 | J6: 113 | K6: 1132 | L6: 15 | M6: 16
A7: 1 | B7: 46203 | C7: 22703000 | D7: ООО "FIDATO GROUP" | F7: =Таблица21339902910[[#This Row],[ ]] -> 1 | G7: 46204 | H7: 90 682 FBA | I7: 600x300x200 | J7: 32.832 | K7: 19 | L7: 730000 | M7: =Таблица21339902910[[#This Row],[113]]*Таблица21339902910[[#This Row],[15]] -> 23967360
A8: 2 | B8: 46203 | C8: 25231000 | D8: ООО "FIDATO GROUP" | F8: =Таблица21339902910[[#This Row],[ ]] -> 2 | G8: 46205 | H8: 90 S 954 OA | I8: 600x300x100 | J8: 32.832 | K8: 19 | L8: 730000 | M8: =Таблица21339902910[[#This Row],[113]]*Таблица21339902910[[#This Row],[15]] -> 23967360
A9: 3 | B9: 46241 | C9: 20982000 | D9: ООО "FIDATO GROUP" | F9: =Таблица21339902910[[#This Row],[ ]] -> 3 | G9: 46214 | H9: 80 C 385 CB | I9: 600x240x200 | J9: 32.832 | K9: 19 | L9: 700000 | M9: =Таблица21339902910[[#This Row],[113]]*Таблица21339902910[[#This Row],[15]] -> 22982400
A10: 4 | F10: =Таблица21339902910[[#This Row],[ ]] -> 4 | G10: 46212 | H10: 95 194 LBA | I10: 600x240x200 | J10: 32.832 | K10: 19 | L10: 700000 | M10: =Таблица21339902910[[#This Row],[113]]*Таблица21339902910[[#This Row],[15]] -> 22982400
A11: 5 | F11: =Таблица21339902910[[#This Row],[ ]] -> 5 | M11: =Таблица21339902910[[#This Row],[113]]*Таблица21339902910[[#This Row],[15]] -> 0
A12: 6 | F12: =Таблица21339902910[[#This Row],[ ]] -> 6 | M12: =Таблица21339902910[[#This Row],[113]]*Таблица21339902910[[#This Row],[15]] -> 0
A13: 7 | F13: =Таблица21339902910[[#This Row],[ ]] -> 7 | M13: =Таблица21339902910[[#This Row],[113]]*Таблица21339902910[[#This Row],[15]] -> 0
A14: 8 | F14: =Таблица21339902910[[#This Row],[ ]] -> 8 | M14: =Таблица21339902910[[#This Row],[113]]*Таблица21339902910[[#This Row],[15]] -> 0
A15: 9 | F15: =Таблица21339902910[[#This Row],[ ]] -> 9 | M15: =Таблица21339902910[[#This Row],[113]]*Таблица21339902910[[#This Row],[15]] -> 0
A16: 10 | F16: =Таблица21339902910[[#This Row],[ ]] -> 10 | M16: =Таблица21339902910[[#This Row],[113]]*Таблица21339902910[[#This Row],[15]] -> 0
A17: 11 | F17: =Таблица21339902910[[#This Row],[ ]] -> 11 | M17: =Таблица21339902910[[#This Row],[113]]*Таблица21339902910[[#This Row],[15]] -> 0
A18: 12 | F18: =Таблица21339902910[[#This Row],[ ]] -> 12 | M18: =Таблица21339902910[[#This Row],[113]]*Таблица21339902910[[#This Row],[15]] -> 0
A19: 13 | F19: =Таблица21339902910[[#This Row],[ ]] -> 13 | M19: =Таблица21339902910[[#This Row],[113]]*Таблица21339902910[[#This Row],[15]] -> 0
A20: 14 | F20: =Таблица21339902910[[#This Row],[ ]] -> 14 | M20: =Таблица21339902910[[#This Row],[113]]*Таблица21339902910[[#This Row],[15]] -> 0
A21: 15 | F21: =Таблица21339902910[[#This Row],[ ]] -> 15 | M21: =Таблица21339902910[[#This Row],[113]]*Таблица21339902910[[#This Row],[15]] -> 0
A22: 16 | F22: =Таблица21339902910[[#This Row],[ ]] -> 16 | M22: =Таблица21339902910[[#This Row],[113]]*Таблица21339902910[[#This Row],[15]] -> 0
... A49: 43 | F49: =Таблица21339902910[[#This Row],[ ]] -> 43 | M49: =Таблица21339902910[[#This Row],[113]]*Таблица21339902910[[#This Row],[15]] -> 0
C50: =SUBTOTAL(109,Таблица21339902910[2]) -> 68916000 | K50: =SUBTOTAL(109,Таблица21339902910[1132]) -> 76 | M50: =SUBTOTAL(109,Таблица21339902910[16]) -> 93899520

Sheet 1-Хонкага
D1: 1-Хонкага
A2: ID-Клиента | F2: =Таблица2133990291012[[#Totals],[2]]+-Таблица2133990291012[[#Totals],[16]] -> -23967360
A3: № | B3: Дата | C3: Сумма | D3: Примечание | E3: Возврат паддон | F3: № | G3: Дата | H3: Авто | I3: Размер | J3: Блок Куб | K3: Поддон Шт | L3: От | M3: Сумма
C5: =Таблица2133990291012[[#Totals],[2]] -> 0 | E5: =SUM(Таблица2133990291012[4]) -> 0 | K5: =Таблица2133990291012[[#Totals],[1132]] -> 19 | M5: =Таблица2133990291012[[#Totals],[16]] -> 23967360
B6: 1 | C6: 2 | D6: 3 | E6: 4 | F6: 9 | G6: 10 | H6: 11 | I6: 114 | J6: 113 | K6: 1132 | L6: 15 | M6: 16
A7: 1 | F7: =Таблица2133990291012[[#This Row],[ ]] -> 1 | G7: 46204 | H7: 80 M 667 YA | I7: 600x300x200 | J7: 32.832 | K7: 19 | L7: 730000 | M7: =Таблица2133990291012[[#This Row],[113]]*Таблица2133990291012[[#This Row],[15]] -> 23967360
A8: 2 | F8: =Таблица2133990291012[[#This Row],[ ]] -> 2 | M8: =Таблица2133990291012[[#This Row],[113]]*Таблица2133990291012[[#This Row],[15]] -> 0
A9: 3 | F9: =Таблица2133990291012[[#This Row],[ ]] -> 3 | M9: =Таблица2133990291012[[#This Row],[113]]*Таблица2133990291012[[#This Row],[15]] -> 0
A10: 4 | F10: =Таблица2133990291012[[#This Row],[ ]] -> 4 | M10: =Таблица2133990291012[[#This Row],[113]]*Таблица2133990291012[[#This Row],[15]] -> 0
A11: 5 | F11: =Таблица2133990291012[[#This Row],[ ]] -> 5 | M11: =Таблица2133990291012[[#This Row],[113]]*Таблица2133990291012[[#This Row],[15]] -> 0
A12: 6 | F12: =Таблица2133990291012[[#This Row],[ ]] -> 6 | M12: =Таблица2133990291012[[#This Row],[113]]*Таблица2133990291012[[#This Row],[15]] -> 0
A13: 7 | F13: =Таблица2133990291012[[#This Row],[ ]] -> 7 | M13: =Таблица2133990291012[[#This Row],[113]]*Таблица2133990291012[[#This Row],[15]] -> 0
A14: 8 | F14: =Таблица2133990291012[[#This Row],[ ]] -> 8 | M14: =Таблица2133990291012[[#This Row],[113]]*Таблица2133990291012[[#This Row],[15]] -> 0
A15: 9 | F15: =Таблица2133990291012[[#This Row],[ ]] -> 9 | M15: =Таблица2133990291012[[#This Row],[113]]*Таблица2133990291012[[#This Row],[15]] -> 0
A16: 10 | F16: =Таблица2133990291012[[#This Row],[ ]] -> 10 | M16: =Таблица2133990291012[[#This Row],[113]]*Таблица2133990291012[[#This Row],[15]] -> 0
A17: 11 | F17: =Таблица2133990291012[[#This Row],[ ]] -> 11 | M17: =Таблица2133990291012[[#This Row],[113]]*Таблица2133990291012[[#This Row],[15]] -> 0
A18: 12 | F18: =Таблица2133990291012[[#This Row],[ ]] -> 12 | M18: =Таблица2133990291012[[#This Row],[113]]*Таблица2133990291012[[#This Row],[15]] -> 0
A19: 13 | F19: =Таблица2133990291012[[#This Row],[ ]] -> 13 | M19: =Таблица2133990291012[[#This Row],[113]]*Таблица2133990291012[[#This Row],[15]] -> 0
... A49: 43 | F49: =Таблица2133990291012[[#This Row],[ ]] -> 43 | M49: =Таблица2133990291012[[#This Row],[113]]*Таблица2133990291012[[#This Row],[15]] -> 0
C50: =SUBTOTAL(109,Таблица2133990291012[2]) -> 0 | K50: =SUBTOTAL(109,Таблица2133990291012[1132]) -> 19 | M50: =SUBTOTAL(109,Таблица2133990291012[16]) -> 23967360

Sheet 2-Гофур Хазорасп
D1: 2-Гофур Хазорасп | H1: Клент шопрга барди: | I1: =SUMIFS(C:C,D:D,J1) -> 0 | J1: шопр учун барди
A2: ID-Клиента | F2: =Таблица2133990294[[#Totals],[2]]+-Таблица2133990294[[#Totals],[16]] -> 0
A3: № | B3: Дата | C3: Сумма | D3: Примечание | E3: Возврат паддон | F3: № | G3: Дата | H3: Авто | I3: Размер | J3: Блок Куб | K3: Поддон Шт | L3: От | M3: Сумма
C5: =Таблица2133990294[[#Totals],[2]] -> 121824000 | E5: =SUM(Таблица2133990294[4]) -> 0 | K5: =Таблица2133990294[[#Totals],[1132]] -> 94 | M5: =Таблица2133990294[[#Totals],[16]] -> 121824000
B6: 1 | C6: 2 | D6: 3 | E6: 4 | F6: 9 | G6: 10 | H6: 11 | I6: 114 | J6: 113 | K6: 1132 | L6: 15 | M6: 16
A7: 1 | B7: 46202 | C7: 47952000 | D7: "EZVIZ CITY"Mchj | F7: =Таблица2133990294[[#This Row],[ ]] -> 1 | G7: 46198 | H7: 01 U 917 XC | I7: 600x300x200 | J7: 32.832 | K7: 19 | L7: 750000 | M7: =Таблица2133990294[[#This Row],[113]]*Таблица2133990294[[#This Row],[15]] -> 24624000
A8: 2 | B8: 46205 | C8: 73872000 | D8: "DOMEX GROUP" Mchj | F8: =Таблица2133990294[[#This Row],[ ]] -> 2 | G8: 46198 | H8: 95 194 LBA | I8: 600x300x200 | J8: 31.104 | K8: 18 | L8: 750000 | M8: =Таблица2133990294[[#This Row],[113]]*Таблица2133990294[[#This Row],[15]] -> 23328000
A9: 3 | F9: =Таблица2133990294[[#This Row],[ ]] -> 3 | G9: 46204 | H9: 90 206 HBA | I9: 600x300x200 | J9: 32.832 | K9: 19 | L9: 750000 | M9: =Таблица2133990294[[#This Row],[113]]*Таблица2133990294[[#This Row],[15]] -> 24624000
A10: 4 | F10: =Таблица2133990294[[#This Row],[ ]] -> 4 | G10: 46204 | H10: 90 015 WAA | I10: 600x300x100 | J10: 32.832 | K10: 19 | L10: 750000 | M10: =Таблица2133990294[[#This Row],[113]]*Таблица2133990294[[#This Row],[15]] -> 24624000
A11: 5 | F11: =Таблица2133990294[[#This Row],[ ]] -> 5 | G11: 46204 | H11: 70 Y 119 GB | I11: 600x300x100 | J11: 32.832 | K11: 19 | L11: 750000 | M11: =Таблица2133990294[[#This Row],[113]]*Таблица2133990294[[#This Row],[15]] -> 24624000
A12: 6 | F12: =Таблица2133990294[[#This Row],[ ]] -> 6 | M12: =Таблица2133990294[[#This Row],[113]]*Таблица2133990294[[#This Row],[15]] -> 0
A13: 7 | F13: =Таблица2133990294[[#This Row],[ ]] -> 7 | M13: =Таблица2133990294[[#This Row],[113]]*Таблица2133990294[[#This Row],[15]] -> 0
A14: 8 | F14: =Таблица2133990294[[#This Row],[ ]] -> 8 | M14: =Таблица2133990294[[#This Row],[113]]*Таблица2133990294[[#This Row],[15]] -> 0
A15: 9 | F15: =Таблица2133990294[[#This Row],[ ]] -> 9 | M15: =Таблица2133990294[[#This Row],[113]]*Таблица2133990294[[#This Row],[15]] -> 0
A16: 10 | F16: =Таблица2133990294[[#This Row],[ ]] -> 10 | M16: =Таблица2133990294[[#This Row],[113]]*Таблица2133990294[[#This Row],[15]] -> 0
A17: 11 | F17: =Таблица2133990294[[#This Row],[ ]] -> 11 | M17: =Таблица2133990294[[#This Row],[113]]*Таблица2133990294[[#This Row],[15]] -> 0
A18: 12 | F18: =Таблица2133990294[[#This Row],[ ]] -> 12 | M18: =Таблица2133990294[[#This Row],[113]]*Таблица2133990294[[#This Row],[15]] -> 0
A19: 13 | F19: =Таблица2133990294[[#This Row],[ ]] -> 13 | M19: =Таблица2133990294[[#This Row],[113]]*Таблица2133990294[[#This Row],[15]] -> 0
A20: 14 | F20: =Таблица2133990294[[#This Row],[ ]] -> 14 | M20: =Таблица2133990294[[#This Row],[113]]*Таблица2133990294[[#This Row],[15]] -> 0
A21: 15 | F21: =Таблица2133990294[[#This Row],[ ]] -> 15 | M21: =Таблица2133990294[[#This Row],[113]]*Таблица2133990294[[#This Row],[15]] -> 0
A22: 16 | F22: =Таблица2133990294[[#This Row],[ ]] -> 16 | M22: =Таблица2133990294[[#This Row],[113]]*Таблица2133990294[[#This Row],[15]] -> 0
A23: 17 | F23: =Таблица2133990294[[#This Row],[ ]] -> 17 | M23: =Таблица2133990294[[#This Row],[113]]*Таблица2133990294[[#This Row],[15]] -> 0
... A49: 43 | F49: =Таблица2133990294[[#This Row],[ ]] -> 43 | M49: =Таблица2133990294[[#This Row],[113]]*Таблица2133990294[[#This Row],[15]] -> 0
C50: =SUBTOTAL(109,Таблица2133990294[2]) -> 121824000 | K50: =SUBTOTAL(109,Таблица2133990294[1132]) -> 94 | M50: =SUBTOTAL(109,Таблица2133990294[16]) -> 121824000

Sheet 2-Шиддат маналит
D1: 2-Шиддат маналит | H1: Клент шопрга барди: | I1: =SUMIFS(C:C,D:D,J1) -> 0 | J1: шопр учун барди
A2: ID-Клиента | F2: =Таблица213399029414[[#Totals],[2]]+-Таблица213399029414[[#Totals],[16]] -> 86082400
A3: № | B3: Дата | C3: Сумма | D3: Примечание | E3: Возврат паддон | F3: № | G3: Дата | H3: Авто | I3: Размер | J3: Блок Куб | K3: Поддон Шт | L3: От | M3: Сумма
C5: =Таблица213399029414[[#Totals],[2]] -> 86082400 | E5: =SUM(Таблица213399029414[4]) -> 0 | K5: =Таблица213399029414[[#Totals],[1132]] -> 0 | M5: =Таблица213399029414[[#Totals],[16]] -> 0
B6: 1 | C6: 2 | D6: 3 | E6: 4 | F6: 9 | G6: 10 | H6: 11 | I6: 114 | J6: 113 | K6: 1132 | L6: 15 | M6: 16
A7: 1 | B7: 46209 | C7: 20982400 | D7: SHIDDAT MONOLIT MCHJ | F7: =Таблица213399029414[[#This Row],[ ]] -> 1 | M7: =Таблица213399029414[[#This Row],[113]]*Таблица213399029414[[#This Row],[15]] -> 0
A8: 2 | B8: 46209 | C8: 2100000 | D8: SHIDDAT MONOLIT MCHJ бир машин газаблок даставка учун ташоди | F8: =Таблица213399029414[[#This Row],[ ]] -> 2 | M8: =Таблица213399029414[[#This Row],[113]]*Таблица213399029414[[#This Row],[15]] -> 0
A9: 3 | B9: 46211 | C9: 63000000 | D9: SHIDDAT MONOLIT MCHJ | F9: =Таблица213399029414[[#This Row],[ ]] -> 3 | M9: =Таблица213399029414[[#This Row],[113]]*Таблица213399029414[[#This Row],[15]] -> 0
A10: 4 | F10: =Таблица213399029414[[#This Row],[ ]] -> 4 | M10: =Таблица213399029414[[#This Row],[113]]*Таблица213399029414[[#This Row],[15]] -> 0
A11: 5 | F11: =Таблица213399029414[[#This Row],[ ]] -> 5 | M11: =Таблица213399029414[[#This Row],[113]]*Таблица213399029414[[#This Row],[15]] -> 0
A12: 6 | F12: =Таблица213399029414[[#This Row],[ ]] -> 6 | M12: =Таблица213399029414[[#This Row],[113]]*Таблица213399029414[[#This Row],[15]] -> 0
A13: 7 | F13: =Таблица213399029414[[#This Row],[ ]] -> 7 | M13: =Таблица213399029414[[#This Row],[113]]*Таблица213399029414[[#This Row],[15]] -> 0
A14: 8 | F14: =Таблица213399029414[[#This Row],[ ]] -> 8 | M14: =Таблица213399029414[[#This Row],[113]]*Таблица213399029414[[#This Row],[15]] -> 0
A15: 9 | F15: =Таблица213399029414[[#This Row],[ ]] -> 9 | M15: =Таблица213399029414[[#This Row],[113]]*Таблица213399029414[[#This Row],[15]] -> 0
A16: 10 | F16: =Таблица213399029414[[#This Row],[ ]] -> 10 | M16: =Таблица213399029414[[#This Row],[113]]*Таблица213399029414[[#This Row],[15]] -> 0
A17: 11 | F17: =Таблица213399029414[[#This Row],[ ]] -> 11 | M17: =Таблица213399029414[[#This Row],[113]]*Таблица213399029414[[#This Row],[15]] -> 0
A18: 12 | F18: =Таблица213399029414[[#This Row],[ ]] -> 12 | M18: =Таблица213399029414[[#This Row],[113]]*Таблица213399029414[[#This Row],[15]] -> 0
A19: 13 | F19: =Таблица213399029414[[#This Row],[ ]] -> 13 | M19: =Таблица213399029414[[#This Row],[113]]*Таблица213399029414[[#This Row],[15]] -> 0
A20: 14 | F20: =Таблица213399029414[[#This Row],[ ]] -> 14 | M20: =Таблица213399029414[[#This Row],[113]]*Таблица213399029414[[#This Row],[15]] -> 0
A21: 15 | F21: =Таблица213399029414[[#This Row],[ ]] -> 15 | M21: =Таблица213399029414[[#This Row],[113]]*Таблица213399029414[[#This Row],[15]] -> 0
... A49: 43 | F49: =Таблица213399029414[[#This Row],[ ]] -> 43 | M49: =Таблица213399029414[[#This Row],[113]]*Таблица213399029414[[#This Row],[15]] -> 0
C50: =SUBTOTAL(109,Таблица213399029414[2]) -> 86082400 | K50: =SUBTOTAL(109,Таблица213399029414[1132]) -> 0 | M50: =SUBTOTAL(109,Таблица213399029414[16]) -> 0

Sheet 2-Дастон шопир 
D1: 2-Шиддат маналит | H1: Клент шопрга барди: | I1: =SUMIFS(C:C,D:D,J1) -> 0 | J1: шопр учун барди
A2: ID-Клиента | F2: =Таблица21339902941420[[#Totals],[2]]+-Таблица21339902941420[[#Totals],[16]] -> -782400
A3: № | B3: Дата | C3: Сумма | D3: Примечание | E3: Возврат паддон | F3: № | G3: Дата | H3: Авто | I3: Размер | J3: Блок Куб | K3: Поддон Шт | L3: От | M3: Сумма
C5: =Таблица21339902941420[[#Totals],[2]] -> 22200000 | E5: =SUM(Таблица21339902941420[4]) -> 0 | K5: =Таблица21339902941420[[#Totals],[1132]] -> 19 | M5: =Таблица21339902941420[[#Totals],[16]] -> 22982400
B6: 1 | C6: 2 | D6: 3 | E6: 4 | F6: 9 | G6: 10 | H6: 11 | I6: 114 | J6: 113 | K6: 1132 | L6: 15 | M6: 16
A7: 1 | B7: 46212 | C7: 22200000 | D7: Нахт | F7: =Таблица21339902941420[[#This Row],[ ]] -> 1 | G7: 46212 | H7: 80 S 385 SB | I7: 600х300х100 | J7: 32.832 | K7: 19 | L7: 700000 | M7: =Таблица21339902941420[[#This Row],[113]]*Таблица21339902941420[[#This Row],[15]] -> 22982400
A8: 2 | F8: =Таблица21339902941420[[#This Row],[ ]] -> 2 | M8: =Таблица21339902941420[[#This Row],[113]]*Таблица21339902941420[[#This Row],[15]] -> 0
A9: 3 | F9: =Таблица21339902941420[[#This Row],[ ]] -> 3 | M9: =Таблица21339902941420[[#This Row],[113]]*Таблица21339902941420[[#This Row],[15]] -> 0
A10: 4 | F10: =Таблица21339902941420[[#This Row],[ ]] -> 4 | M10: =Таблица21339902941420[[#This Row],[113]]*Таблица21339902941420[[#This Row],[15]] -> 0
A11: 5 | F11: =Таблица21339902941420[[#This Row],[ ]] -> 5 | M11: =Таблица21339902941420[[#This Row],[113]]*Таблица21339902941420[[#This Row],[15]] -> 0
A12: 6 | F12: =Таблица21339902941420[[#This Row],[ ]] -> 6 | M12: =Таблица21339902941420[[#This Row],[113]]*Таблица21339902941420[[#This Row],[15]] -> 0
A13: 7 | F13: =Таблица21339902941420[[#This Row],[ ]] -> 7 | M13: =Таблица21339902941420[[#This Row],[113]]*Таблица21339902941420[[#This Row],[15]] -> 0
A14: 8 | F14: =Таблица21339902941420[[#This Row],[ ]] -> 8 | M14: =Таблица21339902941420[[#This Row],[113]]*Таблица21339902941420[[#This Row],[15]] -> 0
A15: 9 | F15: =Таблица21339902941420[[#This Row],[ ]] -> 9 | M15: =Таблица21339902941420[[#This Row],[113]]*Таблица21339902941420[[#This Row],[15]] -> 0
A16: 10 | F16: =Таблица21339902941420[[#This Row],[ ]] -> 10 | M16: =Таблица21339902941420[[#This Row],[113]]*Таблица21339902941420[[#This Row],[15]] -> 0
A17: 11 | F17: =Таблица21339902941420[[#This Row],[ ]] -> 11 | M17: =Таблица21339902941420[[#This Row],[113]]*Таблица21339902941420[[#This Row],[15]] -> 0
A18: 12 | F18: =Таблица21339902941420[[#This Row],[ ]] -> 12 | M18: =Таблица21339902941420[[#This Row],[113]]*Таблица21339902941420[[#This Row],[15]] -> 0
A19: 13 | F19: =Таблица21339902941420[[#This Row],[ ]] -> 13 | M19: =Таблица21339902941420[[#This Row],[113]]*Таблица21339902941420[[#This Row],[15]] -> 0
... A49: 43 | F49: =Таблица21339902941420[[#This Row],[ ]] -> 43 | M49: =Таблица21339902941420[[#This Row],[113]]*Таблица21339902941420[[#This Row],[15]] -> 0
C50: =SUBTOTAL(109,Таблица21339902941420[2]) -> 22200000 | K50: =SUBTOTAL(109,Таблица21339902941420[1132]) -> 19 | M50: =SUBTOTAL(109,Таблица21339902941420[16]) -> 22982400

Sheet 3-Сулаймон Ога Хазарасп
D1: 3-Сулаймон Ога Хазарасп | H1: Клент шопрга барди: | I1: =SUMIFS(C:C,D:D,J1) -> 25900000 | J1: шопр учун барди
A2: ID-Клиента | F2: =Таблица21339902946[[#Totals],[2]]+-Таблица21339902946[[#Totals],[16]] -> -32881200
A3: № | B3: Дата | C3: Сумма | D3: Примечание | E3: Возврат паддон | F3: № | G3: Дата | H3: Авто | I3: Размер | J3: Блок Куб | K3: Поддон Шт | L3: От | M3: Сумма
C5: =Таблица21339902946[[#Totals],[2]] -> 366373200 | E5: =SUM(Таблица21339902946[4]) -> 0 | K5: =Таблица21339902946[[#Totals],[1132]] -> 322 | M5: =Таблица21339902946[[#Totals],[16]] -> 399254400
B6: 1 | C6: 2 | D6: 3 | E6: 4 | F6: 9 | G6: 10 | H6: 11 | I6: 114 | J6: 113 | K6: 1132 | L6: 15 | M6: 16 | N6: 17
A7: 1 | B7: 46198 | C7: 23328000 | D7: HAZORASP MUHAMMAD | F7: =Таблица21339902946[[#This Row],[ ]] -> 1 | G7: 46197 | H7: 90 G 991 FA | I7: 600x300x200 | J7: 31.104 | K7: 18 | L7: 750000 | M7: =Таблица21339902946[[#This Row],[113]]*Таблица21339902946[[#This Row],[15]] -> 23328000
A8: 2 | B8: 46202 | C8: 24624000 | D8: "A-SIA HOUSE" MCHJ | F8: =Таблица21339902946[[#This Row],[ ]] -> 2 | G8: 46200 | H8: 40 W 910 SB | I8: 600x300x100 | J8: 32.832 | K8: 19 | L8: 750000 | M8: =Таблица21339902946[[#This Row],[113]]*Таблица21339902946[[#This Row],[15]] -> 24624000
A9: 3 | B9: 46203 | C9: 73872000 | D9: Xazorasp Ipoteka Qurilish мчж | F9: =Таблица21339902946[[#This Row],[ ]] -> 3 | G9: 46200 | H9: 90 Z 688 AB | I9: 600x300x100 | J9: 32.832 | K9: 19 | L9: 750000 | M9: =Таблица21339902946[[#This Row],[113]]*Таблица21339902946[[#This Row],[15]] -> 24624000
A10: 4 | B10: 46206 | C10: 24624000 | D10: JAHON QILICH OOO | F10: =Таблица21339902946[[#This Row],[ ]] -> 4 | G10: 46200 | H10: 95 617 MBA | I10: 600x300x200 | J10: 32.832 | K10: 19 | L10: 750000 | M10: =Таблица21339902946[[#This Row],[113]]*Таблица21339902946[[#This Row],[15]] -> 24624000
A11: 5 | B11: 46209 | C11: 61447200 | D11: HAZORASP BINOKOR USTA MChJ | F11: =Таблица21339902946[[#This Row],[ ]] -> 5 | G11: 46200 | H11: 40 148 ECA | I11: 600x300x200 | J11: 32.832 | K11: 19 | L11: 750000 | M11: =Таблица21339902946[[#This Row],[113]]*Таблица21339902946[[#This Row],[15]] -> 24624000
A12: 6 | B12: 46206 | C12: 7500000 | D12: шопр учун барди | F12: =Таблица21339902946[[#This Row],[ ]] -> 6 | G12: 46204 | H12: 90 L 027 DA | I12: 600x300x200 | J12: 32.832 | K12: 19 | L12: 750000 | M12: =Таблица21339902946[[#This Row],[113]]*Таблица21339902946[[#This Row],[15]] -> 24624000
A13: 7 | B13: 46210 | C13: 41965000 | D13: HOZORASP MUHAMMAD XO'JAM CHJ | F13: =Таблица21339902946[[#This Row],[ ]] -> 7 | G13: 46206 | H13: 90 452 PBA | I13: 600x300x200 | J13: 32.832 | K13: 19 | L13: 700000 | M13: =Таблица21339902946[[#This Row],[113]]*Таблица21339902946[[#This Row],[15]] -> 22982400 | N13: 2500000
A14: 8 | B14: 46210 | C14: 4000000 | D14: шопр учун барди | F14: =Таблица21339902946[[#This Row],[ ]] -> 8 | G14: 46206 | H14: 40 E 471 SB | I14: 600x300x100 | J14: 32.832 | K14: 19 | L14: 700000 | M14: =Таблица21339902946[[#This Row],[113]]*Таблица21339902946[[#This Row],[15]] -> 22982400 | N14: 2500000 | Q14: 24624000
A15: 9 | B15: 46213 | C15: 20810000 | D15: OOO QILICH-AMIN-NIYAZ | F15: =Таблица21339902946[[#This Row],[ ]] -> 9 | G15: 46206 | H15: 80 N 441 DB | I15: 600x300x200 | J15: 32.832 | K15: 19 | L15: 700000 | M15: =Таблица21339902946[[#This Row],[113]]*Таблица21339902946[[#This Row],[15]] -> 22982400 | N15: 2500000 | Q15: 61447200
A16: 10 | B16: 46213 | C16: 46620000 | D16: HAZORASP BINOKOR USTA MChJ | F16: =Таблица21339902946[[#This Row],[ ]] -> 10 | G16: 46209 | H16: 95 N 260 OA | I16: 600x300x200 | J16: 32.832 | K16: 19 | L16: 700000 | M16: =Таблица21339902946[[#This Row],[113]]*Таблица21339902946[[#This Row],[15]] -> 22982400 | N16: 2000000 | Q16: 7500000
A17: 11 | B17: 46213 | C17: 7500000 | D17: шопр учун барди | F17: =Таблица21339902946[[#This Row],[ ]] -> 11 | G17: 46210 | H17: 95 512 DBA | I17: 600x300x200 | J17: 32.832 | K17: 19 | L17: 700000 | M17: =Таблица21339902946[[#This Row],[113]]*Таблица21339902946[[#This Row],[15]] -> 22982400 | N17: 2000000 | Q17: 41965000
A18: 12 | B18: 46214 | C18: 4400000 | D18: шопр учун барди | F18: =Таблица21339902946[[#This Row],[ ]] -> 12 | G18: 46210 | H18: 80 801 UBA | I18: 600x300x100 | J18: 32.832 | K18: 19 | L18: 700000 | M18: =Таблица21339902946[[#This Row],[113]]*Таблица21339902946[[#This Row],[15]] -> 22982400 | N18: 2500000 | Q18: 4000000
A19: 13 | B19: 46216 | C19: 23183000 | D19: OOO HAZORASP UNIVERSAL MEGA STROY | F19: =Таблица21339902946[[#This Row],[ ]] -> 13 | G19: 46210 | H19: 90 015 WAA | I19: 600x300x100 | J19: 32.832 | K19: 19 | L19: 700000 | M19: =Таблица21339902946[[#This Row],[113]]*Таблица21339902946[[#This Row],[15]] -> 22982400 | N19: 2500000 | Q19: 20810000
A20: 14 | B20: 46216 | C20: 2500000 | D20: шопр учун барди | F20: =Таблица21339902946[[#This Row],[ ]] -> 14 | G20: 46211 | H20: 80 726 ACA | I20: 600x300x200 | J20: 32.832 | K20: 19 | L20: 700000 | M20: =Таблица21339902946[[#This Row],[113]]*Таблица21339902946[[#This Row],[15]] -> 22982400 | N20: 2500000 | Q20: 46620000
A21: 15 | F21: =Таблица21339902946[[#This Row],[ ]] -> 15 | G21: 46214 | H21: 90 388 CBA | I21: 600x300x200 | J21: 32.832 | K21: 19 | L21: 700000 | M21: =Таблица21339902946[[#This Row],[113]]*Таблица21339902946[[#This Row],[15]] -> 22982400 | N21: 2200000 | Q21: 2200000
A22: 16 | F22: =Таблица21339902946[[#This Row],[ ]] -> 16 | G22: 46214 | H22: 90 358 MBA | I22: 600x300x100 | J22: 32.832 | K22: 19 | L22: 700000 | M22: =Таблица21339902946[[#This Row],[113]]*Таблица21339902946[[#This Row],[15]] -> 22982400 | N22: 2200000 | Q22: 2200000
A23: 17 | F23: =Таблица21339902946[[#This Row],[ ]] -> 17 | G23: 46216 | H23: 50 E 093 GB | I23: 600x300x200 | J23: 32.832 | K23: 19 | L23: 700000 | M23: =Таблица21339902946[[#This Row],[113]]*Таблица21339902946[[#This Row],[15]] -> 22982400 | N23: 2500000 | Q23: 2500000
A24: 18 | F24: =Таблица21339902946[[#This Row],[ ]] -> 18 | M24: =Таблица21339902946[[#This Row],[113]]*Таблица21339902946[[#This Row],[15]] -> 0 | Q24: 2799800
A25: 19 | F25: =Таблица21339902946[[#This Row],[ ]] -> 19 | M25: =Таблица21339902946[[#This Row],[113]]*Таблица21339902946[[#This Row],[15]] -> 0
A26: 20 | F26: =Таблица21339902946[[#This Row],[ ]] -> 20 | M26: =Таблица21339902946[[#This Row],[113]]*Таблица21339902946[[#This Row],[15]] -> 0
A27: 21 | F27: =Таблица21339902946[[#This Row],[ ]] -> 21 | M27: =Таблица21339902946[[#This Row],[113]]*Таблица21339902946[[#This Row],[15]] -> 0
A28: 22 | F28: =Таблица21339902946[[#This Row],[ ]] -> 22 | M28: =Таблица21339902946[[#This Row],[113]]*Таблица21339902946[[#This Row],[15]] -> 0
A29: 23 | F29: =Таблица21339902946[[#This Row],[ ]] -> 23 | M29: =Таблица21339902946[[#This Row],[113]]*Таблица21339902946[[#This Row],[15]] -> 0
A30: 24 | F30: =Таблица21339902946[[#This Row],[ ]] -> 24 | M30: =Таблица21339902946[[#This Row],[113]]*Таблица21339902946[[#This Row],[15]] -> 0
A31: 25 | F31: =Таблица21339902946[[#This Row],[ ]] -> 25 | M31: =Таблица21339902946[[#This Row],[113]]*Таблица21339902946[[#This Row],[15]] -> 0
A32: 26 | F32: =Таблица21339902946[[#This Row],[ ]] -> 26 | M32: =Таблица21339902946[[#This Row],[113]]*Таблица21339902946[[#This Row],[15]] -> 0
A33: 27 | F33: =Таблица21339902946[[#This Row],[ ]] -> 27 | M33: =Таблица21339902946[[#This Row],[113]]*Таблица21339902946[[#This Row],[15]] -> 0
A34: 28 | F34: =Таблица21339902946[[#This Row],[ ]] -> 28 | M34: =Таблица21339902946[[#This Row],[113]]*Таблица21339902946[[#This Row],[15]] -> 0
A35: 29 | F35: =Таблица21339902946[[#This Row],[ ]] -> 29 | M35: =Таблица21339902946[[#This Row],[113]]*Таблица21339902946[[#This Row],[15]] -> 0
A36: 30 | F36: =Таблица21339902946[[#This Row],[ ]] -> 30 | M36: =Таблица21339902946[[#This Row],[113]]*Таблица21339902946[[#This Row],[15]] -> 0
... A49: 43 | F49: =Таблица21339902946[[#This Row],[ ]] -> 43 | M49: =Таблица21339902946[[#This Row],[113]]*Таблица21339902946[[#This Row],[15]] -> 0
C50: =SUBTOTAL(109,Таблица21339902946[2]) -> 366373200 | K50: =SUBTOTAL(109,Таблица21339902946[1132]) -> 322 | M50: =SUBTOTAL(109,Таблица21339902946[16]) -> 399254400

Sheet 3-Мурод ога Урганч
D1: 3-Мурод ога Урганч | H1: Клент шопрга барди: | I1: =SUMIFS(C:C,D:D,J1) -> 0 | J1: шопр учун барди
A2: ID-Клиента | F2: =Таблица213399029469[[#Totals],[2]]+-Таблица213399029469[[#Totals],[16]] -> 0
A3: № | B3: Дата | C3: Сумма | D3: Примечание | E3: Возврат паддон | F3: № | G3: Дата | H3: Авто | I3: Размер | J3: Блок Куб | K3: Поддон Шт | L3: От | M3: Сумма
C5: =Таблица213399029469[[#Totals],[2]] -> 47934720 | E5: =SUM(Таблица213399029469[4]) -> 0 | K5: =Таблица213399029469[[#Totals],[1132]] -> 38 | M5: =Таблица213399029469[[#Totals],[16]] -> 47934720
B6: 1 | C6: 2 | D6: 3 | E6: 4 | F6: 9 | G6: 10 | H6: 11 | I6: 114 | J6: 113 | K6: 1132 | L6: 15 | M6: 16
A7: 1 | B7: 46206 | C7: 47934720 | D7: "Ulgircha savdo diyor" MCHJ | F7: =Таблица213399029469[[#This Row],[ ]] -> 1 | G7: 46203 | H7: 40 148 ECA | I7: 600x300x200 | J7: 32.832 | K7: 19 | L7: 730000 | M7: =Таблица213399029469[[#This Row],[113]]*Таблица213399029469[[#This Row],[15]] -> 23967360
A8: 2 | F8: =Таблица213399029469[[#This Row],[ ]] -> 2 | G8: 46203 | H8: 85 L 868 PA | I8: 600x300x200 | J8: 32.832 | K8: 19 | L8: 730000 | M8: =Таблица213399029469[[#This Row],[113]]*Таблица213399029469[[#This Row],[15]] -> 23967360
A9: 3 | F9: =Таблица213399029469[[#This Row],[ ]] -> 3 | M9: =Таблица213399029469[[#This Row],[113]]*Таблица213399029469[[#This Row],[15]] -> 0
A10: 4 | F10: =Таблица213399029469[[#This Row],[ ]] -> 4 | M10: =Таблица213399029469[[#This Row],[113]]*Таблица213399029469[[#This Row],[15]] -> 0
A11: 5 | F11: =Таблица213399029469[[#This Row],[ ]] -> 5 | M11: =Таблица213399029469[[#This Row],[113]]*Таблица213399029469[[#This Row],[15]] -> 0
A12: 6 | F12: =Таблица213399029469[[#This Row],[ ]] -> 6 | M12: =Таблица213399029469[[#This Row],[113]]*Таблица213399029469[[#This Row],[15]] -> 0
A13: 7 | F13: =Таблица213399029469[[#This Row],[ ]] -> 7 | M13: =Таблица213399029469[[#This Row],[113]]*Таблица213399029469[[#This Row],[15]] -> 0
A14: 8 | F14: =Таблица213399029469[[#This Row],[ ]] -> 8 | M14: =Таблица213399029469[[#This Row],[113]]*Таблица213399029469[[#This Row],[15]] -> 0
A15: 9 | F15: =Таблица213399029469[[#This Row],[ ]] -> 9 | M15: =Таблица213399029469[[#This Row],[113]]*Таблица213399029469[[#This Row],[15]] -> 0
A16: 10 | F16: =Таблица213399029469[[#This Row],[ ]] -> 10 | M16: =Таблица213399029469[[#This Row],[113]]*Таблица213399029469[[#This Row],[15]] -> 0
A17: 11 | F17: =Таблица213399029469[[#This Row],[ ]] -> 11 | M17: =Таблица213399029469[[#This Row],[113]]*Таблица213399029469[[#This Row],[15]] -> 0
A18: 12 | F18: =Таблица213399029469[[#This Row],[ ]] -> 12 | M18: =Таблица213399029469[[#This Row],[113]]*Таблица213399029469[[#This Row],[15]] -> 0
A19: 13 | F19: =Таблица213399029469[[#This Row],[ ]] -> 13 | M19: =Таблица213399029469[[#This Row],[113]]*Таблица213399029469[[#This Row],[15]] -> 0
A20: 14 | F20: =Таблица213399029469[[#This Row],[ ]] -> 14 | M20: =Таблица213399029469[[#This Row],[113]]*Таблица213399029469[[#This Row],[15]] -> 0
... A49: 43 | F49: =Таблица213399029469[[#This Row],[ ]] -> 43 | M49: =Таблица213399029469[[#This Row],[113]]*Таблица213399029469[[#This Row],[15]] -> 0
C50: =SUBTOTAL(109,Таблица213399029469[2]) -> 47934720 | K50: =SUBTOTAL(109,Таблица213399029469[1132]) -> 38 | M50: =SUBTOTAL(109,Таблица213399029469[16]) -> 47934720

Sheet 3-Сарвар ога Шовот
D1: 3-Сарвар ога Шовот | H1: Клент шопрга барди: | I1: =SUMIFS(C:C,D:D,J1) -> 2000000 | J1: шопр учун барди
A2: ID-Клиента | F2: =Таблица21339902946915[[#Totals],[2]]+-Таблица21339902946915[[#Totals],[16]] -> 0
A3: № | B3: Дата | C3: Сумма | D3: Примечание | E3: Возврат паддон | F3: № | G3: Дата | H3: Авто | I3: Размер | J3: Блок Куб | K3: Поддон Шт | L3: От | M3: Сумма
C5: =Таблица21339902946915[[#Totals],[2]] -> 68947200 | E5: =SUM(Таблица21339902946915[4]) -> 0 | K5: =Таблица21339902946915[[#Totals],[1132]] -> 57 | M5: =Таблица21339902946915[[#Totals],[16]] -> 68947200
B6: 1 | C6: 2 | D6: 3 | E6: 4 | F6: 9 | G6: 10 | H6: 11 | I6: 114 | J6: 113 | K6: 1132 | L6: 15 | M6: 16 | N6: 17
A7: 1 | B7: 46209 | C7: 20982400 | D7: XIVA SAYQAL MCHJ | F7: =Таблица21339902946915[[#This Row],[ ]] -> 1 | G7: 46209 | H7: 90 015 WAA | I7: 600x300x200 | J7: 32.832 | K7: 19 | L7: 700000 | M7: =Таблица21339902946915[[#This Row],[113]]*Таблица21339902946915[[#This Row],[15]] -> 22982400
A8: 2 | B8: 46209 | C8: 2000000 | D8: шопр учун барди | F8: =Таблица21339902946915[[#This Row],[ ]] -> 2 | G8: 46209 | H8: 90 015 WAA | I8: 600x300x200 | J8: 32.832 | K8: 19 | L8: 700000 | M8: =Таблица21339902946915[[#This Row],[113]]*Таблица21339902946915[[#This Row],[15]] -> 22982400 | N8: 2200000
A9: 3 | B9: 46213 | C9: 41564800 | D9: XIVA SAYQAL MCHJ | F9: =Таблица21339902946915[[#This Row],[ ]] -> 3 | G9: 46217 | H9: 75 084 GBA | I9: 600x300x100 | J9: 32.832 | K9: 19 | L9: 700000 | M9: =Таблица21339902946915[[#This Row],[113]]*Таблица21339902946915[[#This Row],[15]] -> 22982400 | N9: 2500000
A10: 4 | B10: 46213 | C10: 4620000 | D10: XIVA SAYQAL MCHJ | F10: =Таблица21339902946915[[#This Row],[ ]] -> 4 | M10: =Таблица21339902946915[[#This Row],[113]]*Таблица21339902946915[[#This Row],[15]] -> 0
A11: 5 | B11: 46213 | C11: -220000 | D11: Шопир пули 5% | F11: =Таблица21339902946915[[#This Row],[ ]] -> 5 | M11: =Таблица21339902946915[[#This Row],[113]]*Таблица21339902946915[[#This Row],[15]] -> 0
A12: 6 | F12: =Таблица21339902946915[[#This Row],[ ]] -> 6 | M12: =Таблица21339902946915[[#This Row],[113]]*Таблица21339902946915[[#This Row],[15]] -> 0
A13: 7 | F13: =Таблица21339902946915[[#This Row],[ ]] -> 7 | M13: =Таблица21339902946915[[#This Row],[113]]*Таблица21339902946915[[#This Row],[15]] -> 0
A14: 8 | F14: =Таблица21339902946915[[#This Row],[ ]] -> 8 | M14: =Таблица21339902946915[[#This Row],[113]]*Таблица21339902946915[[#This Row],[15]] -> 0
A15: 9 | F15: =Таблица21339902946915[[#This Row],[ ]] -> 9 | M15: =Таблица21339902946915[[#This Row],[113]]*Таблица21339902946915[[#This Row],[15]] -> 0
A16: 10 | F16: =Таблица21339902946915[[#This Row],[ ]] -> 10 | M16: =Таблица21339902946915[[#This Row],[113]]*Таблица21339902946915[[#This Row],[15]] -> 0
A17: 11 | F17: =Таблица21339902946915[[#This Row],[ ]] -> 11 | M17: =Таблица21339902946915[[#This Row],[113]]*Таблица21339902946915[[#This Row],[15]] -> 0
A18: 12 | F18: =Таблица21339902946915[[#This Row],[ ]] -> 12 | M18: =Таблица21339902946915[[#This Row],[113]]*Таблица21339902946915[[#This Row],[15]] -> 0
A19: 13 | F19: =Таблица21339902946915[[#This Row],[ ]] -> 13 | M19: =Таблица21339902946915[[#This Row],[113]]*Таблица21339902946915[[#This Row],[15]] -> 0
A20: 14 | F20: =Таблица21339902946915[[#This Row],[ ]] -> 14 | M20: =Таблица21339902946915[[#This Row],[113]]*Таблица21339902946915[[#This Row],[15]] -> 0
A21: 15 | F21: =Таблица21339902946915[[#This Row],[ ]] -> 15 | M21: =Таблица21339902946915[[#This Row],[113]]*Таблица21339902946915[[#This Row],[15]] -> 0
A22: 16 | F22: =Таблица21339902946915[[#This Row],[ ]] -> 16 | M22: =Таблица21339902946915[[#This Row],[113]]*Таблица21339902946915[[#This Row],[15]] -> 0
A23: 17 | F23: =Таблица21339902946915[[#This Row],[ ]] -> 17 | M23: =Таблица21339902946915[[#This Row],[113]]*Таблица21339902946915[[#This Row],[15]] -> 0
... A49: 43 | F49: =Таблица21339902946915[[#This Row],[ ]] -> 43 | M49: =Таблица21339902946915[[#This Row],[113]]*Таблица21339902946915[[#This Row],[15]] -> 0
C50: =SUBTOTAL(109,Таблица21339902946915[2]) -> 68947200 | K50: =SUBTOTAL(109,Таблица21339902946915[1132]) -> 57 | M50: =SUBTOTAL(109,Таблица21339902946915[16]) -> 68947200

Sheet 4-Гайрат Штб
D1: 4-Гайрат Штб | H1: Клент шопрга барди: | I1: =SUMIFS(C:C,D:D,J1) -> 0 | J1: шопр учун барди
A2: ID-Клиента | F2: =Таблица213399029467[[#Totals],[2]]+-Таблица213399029467[[#Totals],[16]] -> 0
A3: № | B3: Дата | C3: Сумма | D3: Примечание | E3: Возврат паддон | F3: № | G3: Дата | H3: Авто | I3: Размер | J3: Блок Куб | K3: Поддон Шт | L3: От | M3: Сумма
C5: =Таблица213399029467[[#Totals],[2]] -> 49904640 | E5: =SUM(Таблица213399029467[4]) -> 0 | K5: =Таблица213399029467[[#Totals],[1132]] -> 38 | M5: =Таблица213399029467[[#Totals],[16]] -> 49904640
B6: 1 | C6: 2 | D6: 3 | E6: 4 | F6: 9 | G6: 10 | H6: 11 | I6: 114 | J6: 113 | K6: 1132 | L6: 15 | M6: 16
A7: 1 | B7: 46206 | C7: 49904640 | D7: Шовот темур битон хусусий корхонаси | F7: =Таблица213399029467[[#This Row],[ ]] -> 1 | G7: 46200 | H7: 90 919 LBA | I7: 600x300x200 | J7: 32.832 | K7: 19 | L7: 760000 | M7: =Таблица213399029467[[#This Row],[113]]*Таблица213399029467[[#This Row],[15]] -> 24952320
A8: 2 | F8: =Таблица213399029467[[#This Row],[ ]] -> 2 | G8: 46201 | H8: 90 273 QBA | I8: 600x300x200 | J8: 32.832 | K8: 19 | L8: 760000 | M8: =Таблица213399029467[[#This Row],[113]]*Таблица213399029467[[#This Row],[15]] -> 24952320
A9: 3 | F9: =Таблица213399029467[[#This Row],[ ]] -> 3 | M9: =Таблица213399029467[[#This Row],[113]]*Таблица213399029467[[#This Row],[15]] -> 0
A10: 4 | F10: =Таблица213399029467[[#This Row],[ ]] -> 4 | M10: =Таблица213399029467[[#This Row],[113]]*Таблица213399029467[[#This Row],[15]] -> 0
A11: 5 | F11: =Таблица213399029467[[#This Row],[ ]] -> 5 | M11: =Таблица213399029467[[#This Row],[113]]*Таблица213399029467[[#This Row],[15]] -> 0
A12: 6 | F12: =Таблица213399029467[[#This Row],[ ]] -> 6 | M12: =Таблица213399029467[[#This Row],[113]]*Таблица213399029467[[#This Row],[15]] -> 0
A13: 7 | F13: =Таблица213399029467[[#This Row],[ ]] -> 7 | M13: =Таблица213399029467[[#This Row],[113]]*Таблица213399029467[[#This Row],[15]] -> 0
A14: 8 | F14: =Таблица213399029467[[#This Row],[ ]] -> 8 | M14: =Таблица213399029467[[#This Row],[113]]*Таблица213399029467[[#This Row],[15]] -> 0
A15: 9 | F15: =Таблица213399029467[[#This Row],[ ]] -> 9 | M15: =Таблица213399029467[[#This Row],[113]]*Таблица213399029467[[#This Row],[15]] -> 0
A16: 10 | F16: =Таблица213399029467[[#This Row],[ ]] -> 10 | M16: =Таблица213399029467[[#This Row],[113]]*Таблица213399029467[[#This Row],[15]] -> 0
A17: 11 | F17: =Таблица213399029467[[#This Row],[ ]] -> 11 | M17: =Таблица213399029467[[#This Row],[113]]*Таблица213399029467[[#This Row],[15]] -> 0
A18: 12 | F18: =Таблица213399029467[[#This Row],[ ]] -> 12 | M18: =Таблица213399029467[[#This Row],[113]]*Таблица213399029467[[#This Row],[15]] -> 0
A19: 13 | F19: =Таблица213399029467[[#This Row],[ ]] -> 13 | M19: =Таблица213399029467[[#This Row],[113]]*Таблица213399029467[[#This Row],[15]] -> 0
A20: 14 | F20: =Таблица213399029467[[#This Row],[ ]] -> 14 | M20: =Таблица213399029467[[#This Row],[113]]*Таблица213399029467[[#This Row],[15]] -> 0
... A49: 43 | F49: =Таблица213399029467[[#This Row],[ ]] -> 43 | M49: =Таблица213399029467[[#This Row],[113]]*Таблица213399029467[[#This Row],[15]] -> 0
C50: =SUBTOTAL(109,Таблица213399029467[2]) -> 49904640 | K50: =SUBTOTAL(109,Таблица213399029467[1132]) -> 38 | M50: =SUBTOTAL(109,Таблица213399029467[16]) -> 49904640

Sheet 4-Рустам Шпик
D1: 4-Рустам Шпик | H1: Клент шопрга барди: | I1: =SUMIFS(C:C,D:D,J1) -> 4000000 | J1: шопр учун барди
A2: ID-Клиента | F2: =Таблица2133990294678[[#Totals],[2]]+-Таблица2133990294678[[#Totals],[16]] -> 0.6208
A3: № | B3: Дата | C3: Сумма | D3: Примечание | E3: Возврат паддон | F3: № | G3: Дата | H3: Авто | I3: Размер | J3: Блок Куб | K3: Поддон Шт | L3: От | M3: Сумма
C5: =Таблица2133990294678[[#Totals],[2]] -> 69929800 | E5: =SUM(Таблица2133990294678[4]) -> 0 | J5: =SUM(Таблица2133990294678[113]) -> 98.496 | K5: =Таблица2133990294678[[#Totals],[1132]] -> 57 | M5: =Таблица2133990294678[[#Totals],[16]] -> 69929799
B6: 1 | C6: 2 | D6: 3 | E6: 4 | F6: 9 | G6: 10 | H6: 11 | I6: 114 | J6: 113 | K6: 1132 | L6: 15 | M6: 16
A7: 1 | B7: 46202 | C7: 23965000 | D7: "Ифтихор" хусусий корхонаси | F7: =Таблица2133990294678[[#This Row],[ ]] -> 1 | G7: 46200 | H7: 90 X 700 CA | I7: 600x300x200 | J7: 32.832 | K7: 19 | L7: 729928.1 | M7: =Таблица2133990294678[[#This Row],[113]]*Таблица2133990294678[[#This Row],[15]] -> 23964999
A8: 2 | B8: 46206 | C8: 41964800 | D8: "Ифтихор" хусусий корхонаси | F8: =Таблица2133990294678[[#This Row],[ ]] -> 2 | G8: 46206 | H8: 90 015 WAA | I8: 600x300x200 | J8: 32.832 | K8: 19 | L8: 700000 | M8: =Таблица2133990294678[[#This Row],[113]]*Таблица2133990294678[[#This Row],[15]] -> 22982400
A9: 3 | C9: 4000000 | D9: шопр учун барди | F9: =Таблица2133990294678[[#This Row],[ ]] -> 3 | G9: 46206 | H9: 90 306 FBA | I9: 600x300x200 | J9: 32.832 | K9: 19 | L9: 700000 | M9: =Таблица2133990294678[[#This Row],[113]]*Таблица2133990294678[[#This Row],[15]] -> 22982400
A10: 4 | F10: =Таблица2133990294678[[#This Row],[ ]] -> 4 | M10: =Таблица2133990294678[[#This Row],[113]]*Таблица2133990294678[[#This Row],[15]] -> 0
A11: 5 | F11: =Таблица2133990294678[[#This Row],[ ]] -> 5 | M11: =Таблица2133990294678[[#This Row],[113]]*Таблица2133990294678[[#This Row],[15]] -> 0
A12: 6 | F12: =Таблица2133990294678[[#This Row],[ ]] -> 6 | M12: =Таблица2133990294678[[#This Row],[113]]*Таблица2133990294678[[#This Row],[15]] -> 0
A13: 7 | F13: =Таблица2133990294678[[#This Row],[ ]] -> 7 | M13: =Таблица2133990294678[[#This Row],[113]]*Таблица2133990294678[[#This Row],[15]] -> 0
A14: 8 | F14: =Таблица2133990294678[[#This Row],[ ]] -> 8 | M14: =Таблица2133990294678[[#This Row],[113]]*Таблица2133990294678[[#This Row],[15]] -> 0
A15: 9 | F15: =Таблица2133990294678[[#This Row],[ ]] -> 9 | M15: =Таблица2133990294678[[#This Row],[113]]*Таблица2133990294678[[#This Row],[15]] -> 0
A16: 10 | F16: =Таблица2133990294678[[#This Row],[ ]] -> 10 | M16: =Таблица2133990294678[[#This Row],[113]]*Таблица2133990294678[[#This Row],[15]] -> 0
A17: 11 | F17: =Таблица2133990294678[[#This Row],[ ]] -> 11 | M17: =Таблица2133990294678[[#This Row],[113]]*Таблица2133990294678[[#This Row],[15]] -> 0
A18: 12 | F18: =Таблица2133990294678[[#This Row],[ ]] -> 12 | M18: =Таблица2133990294678[[#This Row],[113]]*Таблица2133990294678[[#This Row],[15]] -> 0
A19: 13 | F19: =Таблица2133990294678[[#This Row],[ ]] -> 13 | M19: =Таблица2133990294678[[#This Row],[113]]*Таблица2133990294678[[#This Row],[15]] -> 0
A20: 14 | F20: =Таблица2133990294678[[#This Row],[ ]] -> 14 | M20: =Таблица2133990294678[[#This Row],[113]]*Таблица2133990294678[[#This Row],[15]] -> 0
A21: 15 | F21: =Таблица2133990294678[[#This Row],[ ]] -> 15 | M21: =Таблица2133990294678[[#This Row],[113]]*Таблица2133990294678[[#This Row],[15]] -> 0
... A49: 43 | F49: =Таблица2133990294678[[#This Row],[ ]] -> 43 | M49: =Таблица2133990294678[[#This Row],[113]]*Таблица2133990294678[[#This Row],[15]] -> 0
C50: =SUBTOTAL(109,Таблица2133990294678[2]) -> 69929800 | K50: =SUBTOTAL(109,Таблица2133990294678[1132]) -> 57 | M50: =SUBTOTAL(109,Таблица2133990294678[16]) -> 69929799

Sheet 4-Элликкала Бостон
D1: 4-Элликкала Бостон | H1: Клент шопрга барди: | I1: =SUMIFS(C:C,D:D,J1) -> 0 | J1: шопр учун барди
A2: ID-Клиента | F2: =Таблица213399029467826[[#Totals],[2]]+-Таблица213399029467826[[#Totals],[16]] -> -22982400
A3: № | B3: Дата | C3: Сумма | D3: Примечание | E3: Возврат паддон | F3: № | G3: Дата | H3: Авто | I3: Размер | J3: Блок Куб | K3: Поддон Шт | L3: От | M3: Сумма
C5: =Таблица213399029467826[[#Totals],[2]] -> 0 | E5: =SUM(Таблица213399029467826[4]) -> 0 | J5: =SUM(Таблица213399029467826[113]) -> 32.832 | K5: =Таблица213399029467826[[#Totals],[1132]] -> 19 | M5: =Таблица213399029467826[[#Totals],[16]] -> 22982400
B6: 1 | C6: 2 | D6: 3 | E6: 4 | F6: 9 | G6: 10 | H6: 11 | I6: 114 | J6: 113 | K6: 1132 | L6: 15 | M6: 16
A7: 1 | F7: =Таблица213399029467826[[#This Row],[ ]] -> 1 | G7: 46185 | H7: 95 F 702 GA | I7: 600x300x200 | J7: 32.832 | K7: 19 | L7: 700000 | M7: =Таблица213399029467826[[#This Row],[113]]*Таблица213399029467826[[#This Row],[15]] -> 22982400
A8: 2 | F8: =Таблица213399029467826[[#This Row],[ ]] -> 2 | M8: =Таблица213399029467826[[#This Row],[113]]*Таблица213399029467826[[#This Row],[15]] -> 0
A9: 3 | F9: =Таблица213399029467826[[#This Row],[ ]] -> 3 | M9: =Таблица213399029467826[[#This Row],[113]]*Таблица213399029467826[[#This Row],[15]] -> 0
A10: 4 | F10: =Таблица213399029467826[[#This Row],[ ]] -> 4 | M10: =Таблица213399029467826[[#This Row],[113]]*Таблица213399029467826[[#This Row],[15]] -> 0
A11: 5 | F11: =Таблица213399029467826[[#This Row],[ ]] -> 5 | M11: =Таблица213399029467826[[#This Row],[113]]*Таблица213399029467826[[#This Row],[15]] -> 0
A12: 6 | F12: =Таблица213399029467826[[#This Row],[ ]] -> 6 | M12: =Таблица213399029467826[[#This Row],[113]]*Таблица213399029467826[[#This Row],[15]] -> 0
A13: 7 | F13: =Таблица213399029467826[[#This Row],[ ]] -> 7 | M13: =Таблица213399029467826[[#This Row],[113]]*Таблица213399029467826[[#This Row],[15]] -> 0
A14: 8 | F14: =Таблица213399029467826[[#This Row],[ ]] -> 8 | M14: =Таблица213399029467826[[#This Row],[113]]*Таблица213399029467826[[#This Row],[15]] -> 0
A15: 9 | F15: =Таблица213399029467826[[#This Row],[ ]] -> 9 | M15: =Таблица213399029467826[[#This Row],[113]]*Таблица213399029467826[[#This Row],[15]] -> 0
A16: 10 | F16: =Таблица213399029467826[[#This Row],[ ]] -> 10 | M16: =Таблица213399029467826[[#This Row],[113]]*Таблица213399029467826[[#This Row],[15]] -> 0
A17: 11 | F17: =Таблица213399029467826[[#This Row],[ ]] -> 11 | M17: =Таблица213399029467826[[#This Row],[113]]*Таблица213399029467826[[#This Row],[15]] -> 0
A18: 12 | F18: =Таблица213399029467826[[#This Row],[ ]] -> 12 | M18: =Таблица213399029467826[[#This Row],[113]]*Таблица213399029467826[[#This Row],[15]] -> 0
A19: 13 | F19: =Таблица213399029467826[[#This Row],[ ]] -> 13 | M19: =Таблица213399029467826[[#This Row],[113]]*Таблица213399029467826[[#This Row],[15]] -> 0
... A49: 43 | F49: =Таблица213399029467826[[#This Row],[ ]] -> 43 | M49: =Таблица213399029467826[[#This Row],[113]]*Таблица213399029467826[[#This Row],[15]] -> 0
C50: =SUBTOTAL(109,Таблица213399029467826[2]) -> 0 | K50: =SUBTOTAL(109,Таблица213399029467826[1132]) -> 19 | M50: =SUBTOTAL(109,Таблица213399029467826[16]) -> 22982400

Sheet 5-Жаср Версал
D1: 5-Жасур Версал | H1: Клент шопрга барди: | I1: =SUMIFS(C:C,D:D,J1) -> 18600000 | J1: шопр учун барди
A2: ID-Клиента | F2: =Таблица213399029467813[[#Totals],[2]]+-Таблица213399029467813[[#Totals],[16]] -> 0
A3: № | B3: Дата | C3: Сумма | D3: Примечание | E3: Возврат паддон | F3: № | G3: Дата | H3: Авто | I3: Размер | J3: Блок Куб | K3: Поддон Шт | L3: От | M3: Сумма
C5: =Таблица213399029467813[[#Totals],[2]] -> 206841600 | E5: =SUM(Таблица213399029467813[4]) -> 0 | J5: =SUM(Таблица213399029467813[113]) -> 295.488 | K5: =Таблица213399029467813[[#Totals],[1132]] -> 171 | M5: =Таблица213399029467813[[#Totals],[16]] -> 206841600
B6: 1 | C6: 2 | D6: 3 | E6: 4 | F6: 9 | G6: 10 | H6: 11 | I6: 114 | J6: 113 | K6: 1132 | L6: 15 | M6: 16 | N6: 17
A7: 1 | B7: 46207 | C7: 62947200 | D7: Jamshidbek Jasmina House | F7: =Таблица213399029467813[[#This Row],[ ]] -> 1 | G7: 46206 | H7: 80 C 385 CB | I7: 600x300x200 | J7: 32.832 | K7: 19 | L7: 700000 | M7: =Таблица213399029467813[[#This Row],[113]]*Таблица213399029467813[[#This Row],[15]] -> 22982400
A8: 2 | B8: 46207 | C8: 6000000 | D8: шопр учун барди | F8: =Таблица213399029467813[[#This Row],[ ]] -> 2 | G8: 46206 | H8: 90 S 954 OA | I8: 600x300x200 | J8: 32.832 | K8: 19 | L8: 700000 | M8: =Таблица213399029467813[[#This Row],[113]]*Таблица213399029467813[[#This Row],[15]] -> 22982400
A9: 3 | B9: 46209 | C9: 2000000 | D9: шопр учун барди | F9: =Таблица213399029467813[[#This Row],[ ]] -> 3 | G9: 46206 | H9: 90 734 МВА | I9: 600x300x100 | J9: 32.832 | K9: 19 | L9: 700000 | M9: =Таблица213399029467813[[#This Row],[113]]*Таблица213399029467813[[#This Row],[15]] -> 22982400
A10: 4 | B10: 46207 | C10: 62947200 | D10: Jamshidbek Jasmina House | F10: =Таблица213399029467813[[#This Row],[ ]] -> 4 | G10: 46209 | H10: 95 C 626 SA | I10: 600x300x100 | J10: 32.832 | K10: 19 | L10: 700000 | M10: =Таблица213399029467813[[#This Row],[113]]*Таблица213399029467813[[#This Row],[15]] -> 22982400
A11: 5 | B11: 46209 | C11: 4000000 | D11: шопр учун барди | F11: =Таблица213399029467813[[#This Row],[ ]] -> 5 | G11: 46210 | H11: 90 Z 410 ZZ | I11: 600x300x100 | J11: 32.832 | K11: 19 | L11: 700000 | M11: =Таблица213399029467813[[#This Row],[113]]*Таблица213399029467813[[#This Row],[15]] -> 22982400
A12: 6 | B12: 46216 | C12: 62347200 | D12: Jamshidbek Jasmina House | F12: =Таблица213399029467813[[#This Row],[ ]] -> 6 | G12: 46211 | H12: 95 G 198 SA | I12: 600x300x100 | J12: 32.832 | K12: 19 | L12: 700000 | M12: =Таблица213399029467813[[#This Row],[113]]*Таблица213399029467813[[#This Row],[15]] -> 22982400
A13: 7 | B13: 46216 | C13: 6600000 | D13: шопр учун барди | F13: =Таблица213399029467813[[#This Row],[ ]] -> 7 | G13: 46214 | H13: 95 O 144 GA | I13: 600x300x200 | J13: 32.832 | K13: 19 | L13: 700000 | M13: =Таблица213399029467813[[#This Row],[113]]*Таблица213399029467813[[#This Row],[15]] -> 22982400 | N13: 2200000
A14: 8 | F14: =Таблица213399029467813[[#This Row],[ ]] -> 8 | G14: 46216 | H14: 70 M 307 HB | I14: 600x300x100 | J14: 32.832 | K14: 19 | L14: 700000 | M14: =Таблица213399029467813[[#This Row],[113]]*Таблица213399029467813[[#This Row],[15]] -> 22982400 | N14: 2300000
A15: 9 | F15: =Таблица213399029467813[[#This Row],[ ]] -> 9 | G15: 46216 | H15: 95 F 702 GA | I15: 600x300x200 | J15: 32.832 | K15: 19 | L15: 700000 | M15: =Таблица213399029467813[[#This Row],[113]]*Таблица213399029467813[[#This Row],[15]] -> 22982400 | N15: 2300000
A16: 10 | F16: =Таблица213399029467813[[#This Row],[ ]] -> 10 | M16: =Таблица213399029467813[[#This Row],[113]]*Таблица213399029467813[[#This Row],[15]] -> 0
A17: 11 | F17: =Таблица213399029467813[[#This Row],[ ]] -> 11 | M17: =Таблица213399029467813[[#This Row],[113]]*Таблица213399029467813[[#This Row],[15]] -> 0
A18: 12 | F18: =Таблица213399029467813[[#This Row],[ ]] -> 12 | M18: =Таблица213399029467813[[#This Row],[113]]*Таблица213399029467813[[#This Row],[15]] -> 0
A19: 13 | F19: =Таблица213399029467813[[#This Row],[ ]] -> 13 | M19: =Таблица213399029467813[[#This Row],[113]]*Таблица213399029467813[[#This Row],[15]] -> 0
A20: 14 | F20: =Таблица213399029467813[[#This Row],[ ]] -> 14 | M20: =Таблица213399029467813[[#This Row],[113]]*Таблица213399029467813[[#This Row],[15]] -> 0
A21: 15 | F21: =Таблица213399029467813[[#This Row],[ ]] -> 15 | M21: =Таблица213399029467813[[#This Row],[113]]*Таблица213399029467813[[#This Row],[15]] -> 0
A22: 16 | F22: =Таблица213399029467813[[#This Row],[ ]] -> 16 | M22: =Таблица213399029467813[[#This Row],[113]]*Таблица213399029467813[[#This Row],[15]] -> 0
A23: 17 | F23: =Таблица213399029467813[[#This Row],[ ]] -> 17 | M23: =Таблица213399029467813[[#This Row],[113]]*Таблица213399029467813[[#This Row],[15]] -> 0
A24: 18 | F24: =Таблица213399029467813[[#This Row],[ ]] -> 18 | M24: =Таблица213399029467813[[#This Row],[113]]*Таблица213399029467813[[#This Row],[15]] -> 0
A25: 19 | F25: =Таблица213399029467813[[#This Row],[ ]] -> 19 | M25: =Таблица213399029467813[[#This Row],[113]]*Таблица213399029467813[[#This Row],[15]] -> 0
A26: 20 | F26: =Таблица213399029467813[[#This Row],[ ]] -> 20 | M26: =Таблица213399029467813[[#This Row],[113]]*Таблица213399029467813[[#This Row],[15]] -> 0
A27: 21 | F27: =Таблица213399029467813[[#This Row],[ ]] -> 21 | M27: =Таблица213399029467813[[#This Row],[113]]*Таблица213399029467813[[#This Row],[15]] -> 0
... A49: 43 | F49: =Таблица213399029467813[[#This Row],[ ]] -> 43 | M49: =Таблица213399029467813[[#This Row],[113]]*Таблица213399029467813[[#This Row],[15]] -> 0
C50: =SUBTOTAL(109,Таблица213399029467813[2]) -> 206841600 | K50: =SUBTOTAL(109,Таблица213399029467813[1132]) -> 171 | M50: =SUBTOTAL(109,Таблица213399029467813[16]) -> 206841600

Sheet 5-Мустафо машал
D1: 5-Мустафо машал | H1: Клент шопрга барди: | I1: =SUMIFS(C:C,D:D,J1) -> 4200000 | J1: шопр учун барди
A2: ID-Клиента | F2: =Таблица21339902946781316[[#Totals],[2]]+-Таблица21339902946781316[[#Totals],[16]] -> 21235200
A3: № | B3: Дата | C3: Сумма | D3: Примечание | E3: Возврат паддон | F3: № | G3: Дата | H3: Авто | I3: Размер | J3: Блок Куб | K3: Поддон Шт | L3: От | M3: Сумма
C5: =Таблица21339902946781316[[#Totals],[2]] -> 67200000 | E5: =SUM(Таблица21339902946781316[4]) -> 0 | J5: =SUM(Таблица21339902946781316[113]) -> 65.664 | K5: =Таблица21339902946781316[[#Totals],[1132]] -> 38 | M5: =Таблица21339902946781316[[#Totals],[16]] -> 45964800
B6: 1 | C6: 2 | D6: 3 | E6: 4 | F6: 9 | G6: 10 | H6: 11 | I6: 114 | J6: 113 | K6: 1132 | L6: 15 | M6: 16
A7: 1 | B7: 46209 | C7: 21000000 | D7: "SHUKR BARAKA" MCHJ | F7: =Таблица21339902946781316[[#This Row],[ ]] -> 1 | G7: 46209 | H7: 40 O 636 TB | I7: 600x300x200 | J7: 32.832 | K7: 19 | L7: 700000 | M7: =Таблица21339902946781316[[#This Row],[113]]*Таблица21339902946781316[[#This Row],[15]] -> 22982400
A8: 2 | B8: 46209 | C8: 2000000 | D8: шопр учун барди | F8: =Таблица21339902946781316[[#This Row],[ ]] -> 2 | G8: 46213 | H8: 95 A 242 TA | I8: 600x300x100 | J8: 32.832 | K8: 19 | L8: 700000 | M8: =Таблица21339902946781316[[#This Row],[113]]*Таблица21339902946781316[[#This Row],[15]] -> 22982400
A9: 3 | B9: 46212 | C9: 21000000 | D9: ``SHUKR BARAKA``MCHJ | F9: =Таблица21339902946781316[[#This Row],[ ]] -> 3 | M9: =Таблица21339902946781316[[#This Row],[113]]*Таблица21339902946781316[[#This Row],[15]] -> 0
A10: 4 | B10: 46213 | C10: 21000000 | D10: ``SHUKR BARAKA``MCHJ | F10: =Таблица21339902946781316[[#This Row],[ ]] -> 4 | M10: =Таблица21339902946781316[[#This Row],[113]]*Таблица21339902946781316[[#This Row],[15]] -> 0
A11: 5 | B11: 46213 | C11: 2200000 | D11: шопр учун барди | F11: =Таблица21339902946781316[[#This Row],[ ]] -> 5 | M11: =Таблица21339902946781316[[#This Row],[113]]*Таблица21339902946781316[[#This Row],[15]] -> 0
A12: 6 | F12: =Таблица21339902946781316[[#This Row],[ ]] -> 6 | M12: =Таблица21339902946781316[[#This Row],[113]]*Таблица21339902946781316[[#This Row],[15]] -> 0
A13: 7 | F13: =Таблица21339902946781316[[#This Row],[ ]] -> 7 | M13: =Таблица21339902946781316[[#This Row],[113]]*Таблица21339902946781316[[#This Row],[15]] -> 0
A14: 8 | F14: =Таблица21339902946781316[[#This Row],[ ]] -> 8 | M14: =Таблица21339902946781316[[#This Row],[113]]*Таблица21339902946781316[[#This Row],[15]] -> 0
A15: 9 | F15: =Таблица21339902946781316[[#This Row],[ ]] -> 9 | M15: =Таблица21339902946781316[[#This Row],[113]]*Таблица21339902946781316[[#This Row],[15]] -> 0
A16: 10 | F16: =Таблица21339902946781316[[#This Row],[ ]] -> 10 | M16: =Таблица21339902946781316[[#This Row],[113]]*Таблица21339902946781316[[#This Row],[15]] -> 0
A17: 11 | F17: =Таблица21339902946781316[[#This Row],[ ]] -> 11 | M17: =Таблица21339902946781316[[#This Row],[113]]*Таблица21339902946781316[[#This Row],[15]] -> 0
A18: 12 | F18: =Таблица21339902946781316[[#This Row],[ ]] -> 12 | M18: =Таблица21339902946781316[[#This Row],[113]]*Таблица21339902946781316[[#This Row],[15]] -> 0
A19: 13 | F19: =Таблица21339902946781316[[#This Row],[ ]] -> 13 | M19: =Таблица21339902946781316[[#This Row],[113]]*Таблица21339902946781316[[#This Row],[15]] -> 0
A20: 14 | F20: =Таблица21339902946781316[[#This Row],[ ]] -> 14 | M20: =Таблица21339902946781316[[#This Row],[113]]*Таблица21339902946781316[[#This Row],[15]] -> 0
A21: 15 | F21: =Таблица21339902946781316[[#This Row],[ ]] -> 15 | M21: =Таблица21339902946781316[[#This Row],[113]]*Таблица21339902946781316[[#This Row],[15]] -> 0
A22: 16 | F22: =Таблица21339902946781316[[#This Row],[ ]] -> 16 | M22: =Таблица21339902946781316[[#This Row],[113]]*Таблица21339902946781316[[#This Row],[15]] -> 0
A23: 17 | F23: =Таблица21339902946781316[[#This Row],[ ]] -> 17 | M23: =Таблица21339902946781316[[#This Row],[113]]*Таблица21339902946781316[[#This Row],[15]] -> 0
... A49: 43 | F49: =Таблица21339902946781316[[#This Row],[ ]] -> 43 | M49: =Таблица21339902946781316[[#This Row],[113]]*Таблица21339902946781316[[#This Row],[15]] -> 0
C50: =SUBTOTAL(109,Таблица21339902946781316[2]) -> 67200000 | K50: =SUBTOTAL(109,Таблица21339902946781316[1132]) -> 38 | M50: =SUBTOTAL(109,Таблица21339902946781316[16]) -> 45964800

Sheet 5-Одилбек Ера хоус
D1: 5-Одилбек Ера хоус | H1: Клент шопрга барди: | I1: =SUMIFS(C:C,D:D,J1) -> 8600000 | J1: шопр учун барди
A2: ID-Клиента | F2: =Таблица2133990294678131619[[#Totals],[2]]+-Таблица2133990294678131619[[#Totals],[16]] -> 200
A3: № | B3: Дата | C3: Сумма | D3: Примечание | E3: Возврат паддон | F3: № | G3: Дата | H3: Авто | I3: Размер | J3: Блок Куб | K3: Поддон Шт | L3: От | M3: Сумма
C5: =Таблица2133990294678131619[[#Totals],[2]] -> 91929800 | E5: =SUM(Таблица2133990294678131619[4]) -> 0 | J5: =SUM(Таблица2133990294678131619[113]) -> 131.328 | K5: =Таблица2133990294678131619[[#Totals],[1132]] -> 76 | M5: =Таблица2133990294678131619[[#Totals],[16]] -> 91929600
B6: 1 | C6: 2 | D6: 3 | E6: 4 | F6: 9 | G6: 10 | H6: 11 | I6: 114 | J6: 113 | K6: 1132 | L6: 15 | M6: 16
A7: 1 | B7: 46212 | C7: 41964800 | D7: "БУНЕДКОР" МЧЖ | F7: =Таблица2133990294678131619[[#This Row],[ ]] -> 1 | G7: 46213 | H7: 90 S 196 AB | I7: 600x300x200 | J7: 32.832 | K7: 19 | L7: 700000 | M7: =Таблица2133990294678131619[[#This Row],[113]]*Таблица2133990294678131619[[#This Row],[15]] -> 22982400
A8: 2 | B8: 46213 | C8: 4000000 | D8: шопр учун барди | F8: =Таблица2133990294678131619[[#This Row],[ ]] -> 2 | G8: 46212 | H8: 80 C 385 CB | I8: 600x300x200 | J8: 32.832 | K8: 19 | L8: 700000 | M8: =Таблица2133990294678131619[[#This Row],[113]]*Таблица2133990294678131619[[#This Row],[15]] -> 22982400
A9: 3 | B9: 46216 | C9: 41365000 | D9: "БУНЕДКОР" МЧЖ | F9: =Таблица2133990294678131619[[#This Row],[ ]] -> 3 | G9: 46216 | H9: 30 100 MAN | I9: 600x300x200 | J9: 32.832 | K9: 19 | L9: 700000 | M9: =Таблица2133990294678131619[[#This Row],[113]]*Таблица2133990294678131619[[#This Row],[15]] -> 22982400
A10: 4 | B10: 14 | C10: 4600000 | D10: шопр учун барди | F10: =Таблица2133990294678131619[[#This Row],[ ]] -> 4 | G10: 46217 | H10: 25 S 005 FA | I10: 600x300x200 | J10: 32.832 | K10: 19 | L10: 700000 | M10: =Таблица2133990294678131619[[#This Row],[113]]*Таблица2133990294678131619[[#This Row],[15]] -> 22982400
A11: 5 | F11: =Таблица2133990294678131619[[#This Row],[ ]] -> 5 | M11: =Таблица2133990294678131619[[#This Row],[113]]*Таблица2133990294678131619[[#This Row],[15]] -> 0
A12: 6 | F12: =Таблица2133990294678131619[[#This Row],[ ]] -> 6 | M12: =Таблица2133990294678131619[[#This Row],[113]]*Таблица2133990294678131619[[#This Row],[15]] -> 0
A13: 7 | F13: =Таблица2133990294678131619[[#This Row],[ ]] -> 7 | M13: =Таблица2133990294678131619[[#This Row],[113]]*Таблица2133990294678131619[[#This Row],[15]] -> 0
A14: 8 | F14: =Таблица2133990294678131619[[#This Row],[ ]] -> 8 | M14: =Таблица2133990294678131619[[#This Row],[113]]*Таблица2133990294678131619[[#This Row],[15]] -> 0
A15: 9 | F15: =Таблица2133990294678131619[[#This Row],[ ]] -> 9 | M15: =Таблица2133990294678131619[[#This Row],[113]]*Таблица2133990294678131619[[#This Row],[15]] -> 0
A16: 10 | F16: =Таблица2133990294678131619[[#This Row],[ ]] -> 10 | M16: =Таблица2133990294678131619[[#This Row],[113]]*Таблица2133990294678131619[[#This Row],[15]] -> 0
A17: 11 | F17: =Таблица2133990294678131619[[#This Row],[ ]] -> 11 | M17: =Таблица2133990294678131619[[#This Row],[113]]*Таблица2133990294678131619[[#This Row],[15]] -> 0
A18: 12 | F18: =Таблица2133990294678131619[[#This Row],[ ]] -> 12 | M18: =Таблица2133990294678131619[[#This Row],[113]]*Таблица2133990294678131619[[#This Row],[15]] -> 0
A19: 13 | F19: =Таблица2133990294678131619[[#This Row],[ ]] -> 13 | M19: =Таблица2133990294678131619[[#This Row],[113]]*Таблица2133990294678131619[[#This Row],[15]] -> 0
A20: 14 | F20: =Таблица2133990294678131619[[#This Row],[ ]] -> 14 | M20: =Таблица2133990294678131619[[#This Row],[113]]*Таблица2133990294678131619[[#This Row],[15]] -> 0
A21: 15 | F21: =Таблица2133990294678131619[[#This Row],[ ]] -> 15 | M21: =Таблица2133990294678131619[[#This Row],[113]]*Таблица2133990294678131619[[#This Row],[15]] -> 0
A22: 16 | F22: =Таблица2133990294678131619[[#This Row],[ ]] -> 16 | M22: =Таблица2133990294678131619[[#This Row],[113]]*Таблица2133990294678131619[[#This Row],[15]] -> 0
... A49: 43 | F49: =Таблица2133990294678131619[[#This Row],[ ]] -> 43 | M49: =Таблица2133990294678131619[[#This Row],[113]]*Таблица2133990294678131619[[#This Row],[15]] -> 0
C50: =SUBTOTAL(109,Таблица2133990294678131619[2]) -> 91929800 | K50: =SUBTOTAL(109,Таблица2133990294678131619[1132]) -> 76 | M50: =SUBTOTAL(109,Таблица2133990294678131619[16]) -> 91929600

Sheet 6-Уткир мини
D1: 6-Уткир мини | H1: Клент шопрга барди: | I1: =SUMIFS(C:C,D:D,J1) -> 4000000 | J1: шопр учун барди
A2: ID-Клиента | F2: =Таблица213399029467813161718[[#Totals],[2]]+-Таблица213399029467813161718[[#Totals],[16]] -> 0
A3: № | B3: Дата | C3: Сумма | D3: Примечание | E3: Возврат паддон | F3: № | G3: Дата | H3: Авто | I3: Размер | J3: Блок Куб | K3: Поддон Шт | L3: От | M3: Сумма
C5: =Таблица213399029467813161718[[#Totals],[2]] -> 45964800 | E5: =SUM(Таблица213399029467813161718[4]) -> 0 | J5: =SUM(Таблица213399029467813161718[113]) -> 65.664 | K5: =Таблица213399029467813161718[[#Totals],[1132]] -> 38 | M5: =Таблица213399029467813161718[[#Totals],[16]] -> 45964800
B6: 1 | C6: 2 | D6: 3 | E6: 4 | F6: 9 | G6: 10 | H6: 11 | I6: 114 | J6: 113 | K6: 1132 | L6: 15 | M6: 16
A7: 1 | B7: 46210 | C7: 40000000 | D7: Коровул курилиш монтаж | F7: =Таблица213399029467813161718[[#This Row],[ ]] -> 1 | G7: 46210 | H7: 95 693 GBA | I7: 600x300x100 | J7: 32.832 | K7: 19 | L7: 700000 | M7: =Таблица213399029467813161718[[#This Row],[113]]*Таблица213399029467813161718[[#This Row],[15]] -> 22982400
A8: 2 | B8: 46210 | C8: 1964800 | D8: Коровул курилиш монтаж | F8: =Таблица213399029467813161718[[#This Row],[ ]] -> 2 | G8: 46211 | H8: 90 779 EBA | I8: 600x300x100 | J8: 32.832 | K8: 19 | L8: 700000 | M8: =Таблица213399029467813161718[[#This Row],[113]]*Таблица213399029467813161718[[#This Row],[15]] -> 22982400
A9: 3 | B9: 46180 | C9: 2000000 | D9: шопр учун барди | F9: =Таблица213399029467813161718[[#This Row],[ ]] -> 3 | M9: =Таблица213399029467813161718[[#This Row],[113]]*Таблица213399029467813161718[[#This Row],[15]] -> 0
A10: 4 | B10: 46211 | C10: 2000000 | D10: шопр учун барди | F10: =Таблица213399029467813161718[[#This Row],[ ]] -> 4 | M10: =Таблица213399029467813161718[[#This Row],[113]]*Таблица213399029467813161718[[#This Row],[15]] -> 0
A11: 5 | F11: =Таблица213399029467813161718[[#This Row],[ ]] -> 5 | M11: =Таблица213399029467813161718[[#This Row],[113]]*Таблица213399029467813161718[[#This Row],[15]] -> 0
A12: 6 | F12: =Таблица213399029467813161718[[#This Row],[ ]] -> 6 | M12: =Таблица213399029467813161718[[#This Row],[113]]*Таблица213399029467813161718[[#This Row],[15]] -> 0
A13: 7 | F13: =Таблица213399029467813161718[[#This Row],[ ]] -> 7 | M13: =Таблица213399029467813161718[[#This Row],[113]]*Таблица213399029467813161718[[#This Row],[15]] -> 0
A14: 8 | F14: =Таблица213399029467813161718[[#This Row],[ ]] -> 8 | M14: =Таблица213399029467813161718[[#This Row],[113]]*Таблица213399029467813161718[[#This Row],[15]] -> 0
A15: 9 | F15: =Таблица213399029467813161718[[#This Row],[ ]] -> 9 | M15: =Таблица213399029467813161718[[#This Row],[113]]*Таблица213399029467813161718[[#This Row],[15]] -> 0
A16: 10 | F16: =Таблица213399029467813161718[[#This Row],[ ]] -> 10 | M16: =Таблица213399029467813161718[[#This Row],[113]]*Таблица213399029467813161718[[#This Row],[15]] -> 0
A17: 11 | F17: =Таблица213399029467813161718[[#This Row],[ ]] -> 11 | M17: =Таблица213399029467813161718[[#This Row],[113]]*Таблица213399029467813161718[[#This Row],[15]] -> 0
A18: 12 | F18: =Таблица213399029467813161718[[#This Row],[ ]] -> 12 | M18: =Таблица213399029467813161718[[#This Row],[113]]*Таблица213399029467813161718[[#This Row],[15]] -> 0
A19: 13 | F19: =Таблица213399029467813161718[[#This Row],[ ]] -> 13 | M19: =Таблица213399029467813161718[[#This Row],[113]]*Таблица213399029467813161718[[#This Row],[15]] -> 0
A20: 14 | F20: =Таблица213399029467813161718[[#This Row],[ ]] -> 14 | M20: =Таблица213399029467813161718[[#This Row],[113]]*Таблица213399029467813161718[[#This Row],[15]] -> 0
A21: 15 | F21: =Таблица213399029467813161718[[#This Row],[ ]] -> 15 | M21: =Таблица213399029467813161718[[#This Row],[113]]*Таблица213399029467813161718[[#This Row],[15]] -> 0
A22: 16 | F22: =Таблица213399029467813161718[[#This Row],[ ]] -> 16 | M22: =Таблица213399029467813161718[[#This Row],[113]]*Таблица213399029467813161718[[#This Row],[15]] -> 0
... A49: 43 | F49: =Таблица213399029467813161718[[#This Row],[ ]] -> 43 | M49: =Таблица213399029467813161718[[#This Row],[113]]*Таблица213399029467813161718[[#This Row],[15]] -> 0
C50: =SUBTOTAL(109,Таблица213399029467813161718[2]) -> 45964800 | K50: =SUBTOTAL(109,Таблица213399029467813161718[1132]) -> 38 | M50: =SUBTOTAL(109,Таблица213399029467813161718[16]) -> 45964800

Sheet 6-Отабек дамирчи
D1: 6-Отабек дамирчи | H1: Клент шопрга барди: | I1: =C8+C9 -> 4700000 | J1: шопр учун барди
A2: ID-Клиента | F2: =Таблица2133990294678131617[[#Totals],[2]]+-Таблица2133990294678131617[[#Totals],[16]] -> 3735200
A3: № | B3: Дата | C3: Сумма | D3: Примечание | E3: Возврат паддон | F3: № | G3: Дата | H3: Авто | I3: Размер | J3: Блок Куб | K3: Поддон Шт | L3: От | M3: Сумма
C5: =Таблица2133990294678131617[[#Totals],[2]] -> 49700000 | E5: =SUM(Таблица2133990294678131617[4]) -> 0 | J5: =SUM(Таблица2133990294678131617[113]) -> 65.664 | K5: =Таблица2133990294678131617[[#Totals],[1132]] -> 38 | M5: =Таблица2133990294678131617[[#Totals],[16]] -> 45964800
B6: 1 | C6: 2 | D6: 3 | E6: 4 | F6: 9 | G6: 10 | H6: 11 | I6: 114 | J6: 113 | K6: 1132 | L6: 15 | M6: 16 | N6: 17
A7: 1 | B7: 46212 | C7: 45000000 | D7: "Qodiriy Construction" Масъулияти Чекланган Жамият | F7: =Таблица2133990294678131617[[#This Row],[ ]] -> 1 | G7: 46214 | H7: 90 M 660 LA | I7: 600x300x200 | J7: 32.832 | K7: 19 | L7: 700000 | M7: =Таблица2133990294678131617[[#This Row],[113]]*Таблица2133990294678131617[[#This Row],[15]] -> 22982400 | N7: 2500000
A8: 2 | B8: 46214 | C8: 2500000 | D8: Шофйор пули | F8: =Таблица2133990294678131617[[#This Row],[ ]] -> 2 | G8: 46210 | H8: 90 340 FBA | I8: 600x300x100 | J8: 32.832 | K8: 19 | L8: 700000 | M8: =Таблица2133990294678131617[[#This Row],[113]]*Таблица2133990294678131617[[#This Row],[15]] -> 22982400 | N8: 2200000
A9: 3 | B9: 46210 | C9: 2200000 | D9: Шофйор пули | F9: =Таблица2133990294678131617[[#This Row],[ ]] -> 3 | M9: =Таблица2133990294678131617[[#This Row],[113]]*Таблица2133990294678131617[[#This Row],[15]] -> 0
A10: 4 | F10: =Таблица2133990294678131617[[#This Row],[ ]] -> 4 | M10: =Таблица2133990294678131617[[#This Row],[113]]*Таблица2133990294678131617[[#This Row],[15]] -> 0
A11: 5 | F11: =Таблица2133990294678131617[[#This Row],[ ]] -> 5 | M11: =Таблица2133990294678131617[[#This Row],[113]]*Таблица2133990294678131617[[#This Row],[15]] -> 0
A12: 6 | F12: =Таблица2133990294678131617[[#This Row],[ ]] -> 6 | M12: =Таблица2133990294678131617[[#This Row],[113]]*Таблица2133990294678131617[[#This Row],[15]] -> 0
A13: 7 | F13: =Таблица2133990294678131617[[#This Row],[ ]] -> 7 | M13: =Таблица2133990294678131617[[#This Row],[113]]*Таблица2133990294678131617[[#This Row],[15]] -> 0
A14: 8 | F14: =Таблица2133990294678131617[[#This Row],[ ]] -> 8 | M14: =Таблица2133990294678131617[[#This Row],[113]]*Таблица2133990294678131617[[#This Row],[15]] -> 0
A15: 9 | F15: =Таблица2133990294678131617[[#This Row],[ ]] -> 9 | M15: =Таблица2133990294678131617[[#This Row],[113]]*Таблица2133990294678131617[[#This Row],[15]] -> 0
A16: 10 | F16: =Таблица2133990294678131617[[#This Row],[ ]] -> 10 | M16: =Таблица2133990294678131617[[#This Row],[113]]*Таблица2133990294678131617[[#This Row],[15]] -> 0
A17: 11 | F17: =Таблица2133990294678131617[[#This Row],[ ]] -> 11 | M17: =Таблица2133990294678131617[[#This Row],[113]]*Таблица2133990294678131617[[#This Row],[15]] -> 0
A18: 12 | F18: =Таблица2133990294678131617[[#This Row],[ ]] -> 12 | M18: =Таблица2133990294678131617[[#This Row],[113]]*Таблица2133990294678131617[[#This Row],[15]] -> 0
A19: 13 | F19: =Таблица2133990294678131617[[#This Row],[ ]] -> 13 | M19: =Таблица2133990294678131617[[#This Row],[113]]*Таблица2133990294678131617[[#This Row],[15]] -> 0
A20: 14 | F20: =Таблица2133990294678131617[[#This Row],[ ]] -> 14 | M20: =Таблица2133990294678131617[[#This Row],[113]]*Таблица2133990294678131617[[#This Row],[15]] -> 0
A21: 15 | F21: =Таблица2133990294678131617[[#This Row],[ ]] -> 15 | M21: =Таблица2133990294678131617[[#This Row],[113]]*Таблица2133990294678131617[[#This Row],[15]] -> 0
... A49: 43 | F49: =Таблица2133990294678131617[[#This Row],[ ]] -> 43 | M49: =Таблица2133990294678131617[[#This Row],[113]]*Таблица2133990294678131617[[#This Row],[15]] -> 0
C50: =SUBTOTAL(109,Таблица2133990294678131617[2]) -> 49700000 | K50: =SUBTOTAL(109,Таблица2133990294678131617[1132]) -> 38 | M50: =SUBTOTAL(109,Таблица2133990294678131617[16]) -> 45964800

Sheet 5-Журат ога хонка
D1: 5-Журат ога хонка | H1: Клент шопрга барди: | I1: =C8 -> 2300000 | J1: шопр учун барди
A2: ID-Клиента | F2: =Таблица213399029467813161721[[#Totals],[2]]+-Таблица213399029467813161721[[#Totals],[16]] -> -400
A3: № | B3: Дата | C3: Сумма | D3: Примечание | E3: Возврат паддон | F3: № | G3: Дата | H3: Авто | I3: Размер | J3: Блок Куб | K3: Поддон Шт | L3: От | M3: Сумма
C5: =Таблица213399029467813161721[[#Totals],[2]] -> 22982000 | E5: =SUM(Таблица213399029467813161721[4]) -> 0 | J5: =SUM(Таблица213399029467813161721[113]) -> 32.832 | K5: =Таблица213399029467813161721[[#Totals],[1132]] -> 19 | M5: =Таблица213399029467813161721[[#Totals],[16]] -> 22982400
B6: 1 | C6: 2 | D6: 3 | E6: 4 | F6: 9 | G6: 10 | H6: 11 | I6: 114 | J6: 113 | K6: 1132 | L6: 15 | M6: 16
A7: 1 | B7: 46213 | C7: 20682000 | D7: "VATANPARVARLIK YOSHLAR KELAJAGI" MCHJ | F7: =Таблица213399029467813161721[[#This Row],[ ]] -> 1 | G7: 46213 | H7: 95 B 760 QA | I7: 600x300x200 | J7: 32.832 | K7: 19 | L7: 700000 | M7: =Таблица213399029467813161721[[#This Row],[113]]*Таблица213399029467813161721[[#This Row],[15]] -> 22982400
A8: 2 | B8: 46213 | C8: 2300000 | D8: Шофйор пули | F8: =Таблица213399029467813161721[[#This Row],[ ]] -> 2 | M8: =Таблица213399029467813161721[[#This Row],[113]]*Таблица213399029467813161721[[#This Row],[15]] -> 0
A9: 3 | F9: =Таблица213399029467813161721[[#This Row],[ ]] -> 3 | M9: =Таблица213399029467813161721[[#This Row],[113]]*Таблица213399029467813161721[[#This Row],[15]] -> 0
A10: 4 | F10: =Таблица213399029467813161721[[#This Row],[ ]] -> 4 | M10: =Таблица213399029467813161721[[#This Row],[113]]*Таблица213399029467813161721[[#This Row],[15]] -> 0
A11: 5 | F11: =Таблица213399029467813161721[[#This Row],[ ]] -> 5 | M11: =Таблица213399029467813161721[[#This Row],[113]]*Таблица213399029467813161721[[#This Row],[15]] -> 0
A12: 6 | F12: =Таблица213399029467813161721[[#This Row],[ ]] -> 6 | M12: =Таблица213399029467813161721[[#This Row],[113]]*Таблица213399029467813161721[[#This Row],[15]] -> 0
A13: 7 | F13: =Таблица213399029467813161721[[#This Row],[ ]] -> 7 | M13: =Таблица213399029467813161721[[#This Row],[113]]*Таблица213399029467813161721[[#This Row],[15]] -> 0
A14: 8 | F14: =Таблица213399029467813161721[[#This Row],[ ]] -> 8 | M14: =Таблица213399029467813161721[[#This Row],[113]]*Таблица213399029467813161721[[#This Row],[15]] -> 0
A15: 9 | F15: =Таблица213399029467813161721[[#This Row],[ ]] -> 9 | M15: =Таблица213399029467813161721[[#This Row],[113]]*Таблица213399029467813161721[[#This Row],[15]] -> 0
A16: 10 | F16: =Таблица213399029467813161721[[#This Row],[ ]] -> 10 | M16: =Таблица213399029467813161721[[#This Row],[113]]*Таблица213399029467813161721[[#This Row],[15]] -> 0
A17: 11 | F17: =Таблица213399029467813161721[[#This Row],[ ]] -> 11 | M17: =Таблица213399029467813161721[[#This Row],[113]]*Таблица213399029467813161721[[#This Row],[15]] -> 0
A18: 12 | F18: =Таблица213399029467813161721[[#This Row],[ ]] -> 12 | M18: =Таблица213399029467813161721[[#This Row],[113]]*Таблица213399029467813161721[[#This Row],[15]] -> 0
A19: 13 | F19: =Таблица213399029467813161721[[#This Row],[ ]] -> 13 | M19: =Таблица213399029467813161721[[#This Row],[113]]*Таблица213399029467813161721[[#This Row],[15]] -> 0
A20: 14 | F20: =Таблица213399029467813161721[[#This Row],[ ]] -> 14 | M20: =Таблица213399029467813161721[[#This Row],[113]]*Таблица213399029467813161721[[#This Row],[15]] -> 0
... A49: 43 | F49: =Таблица213399029467813161721[[#This Row],[ ]] -> 43 | M49: =Таблица213399029467813161721[[#This Row],[113]]*Таблица213399029467813161721[[#This Row],[15]] -> 0
C50: =SUBTOTAL(109,Таблица213399029467813161721[2]) -> 22982000 | K50: =SUBTOTAL(109,Таблица213399029467813161721[1132]) -> 19 | M50: =SUBTOTAL(109,Таблица213399029467813161721[16]) -> 22982400

Sheet 6-Мамун Университети
D1: 6-Мамун Университети | H1: Клент шопрга барди: | I1: =C7 -> 4400000 | J1: шопр учун барди
A2: ID-Клиента | F2: =Таблица21339902946781316172122[[#Totals],[2]]+-Таблица21339902946781316172122[[#Totals],[16]] -> 58435200
A3: № | B3: Дата | C3: Сумма | D3: Примечание | E3: Возврат паддон | F3: № | G3: Дата | H3: Авто | I3: Размер | J3: Блок Куб | K3: Поддон Шт | L3: От | M3: Сумма
C5: =Таблица21339902946781316172122[[#Totals],[2]] -> 104400000 | E5: =SUM(Таблица21339902946781316172122[4]) -> 0 | J5: =SUM(Таблица21339902946781316172122[113]) -> 65.664 | K5: =Таблица21339902946781316172122[[#Totals],[1132]] -> 38 | M5: =Таблица21339902946781316172122[[#Totals],[16]] -> 45964800
B6: 1 | C6: 2 | D6: 3 | E6: 4 | F6: 9 | G6: 10 | H6: 11 | I6: 114 | J6: 113 | K6: 1132 | L6: 15 | M6: 16 | N6: 17
A7: 1 | B7: 46215 | C7: 4400000 | D7: Шопир пули | F7: =Таблица21339902946781316172122[[#This Row],[ ]] -> 1 | G7: 46215 | H7: 90 999 EBA | I7: 600x300x200 | J7: 32.832 | K7: 19 | L7: 700000 | M7: =Таблица21339902946781316172122[[#This Row],[113]]*Таблица21339902946781316172122[[#This Row],[15]] -> 22982400 | N7: 2200000
A8: 2 | B8: 46216 | C8: 100000000 | D8: Мамун Университети | F8: =Таблица21339902946781316172122[[#This Row],[ ]] -> 2 | G8: 46216 | H8: 90 924 LBA | I8: 600x300x100 | J8: 32.832 | K8: 19 | L8: 700000 | M8: =Таблица21339902946781316172122[[#This Row],[113]]*Таблица21339902946781316172122[[#This Row],[15]] -> 22982400 | N8: 2200000
A9: 3 | F9: =Таблица21339902946781316172122[[#This Row],[ ]] -> 3 | M9: =Таблица21339902946781316172122[[#This Row],[113]]*Таблица21339902946781316172122[[#This Row],[15]] -> 0
A10: 4 | F10: =Таблица21339902946781316172122[[#This Row],[ ]] -> 4 | M10: =Таблица21339902946781316172122[[#This Row],[113]]*Таблица21339902946781316172122[[#This Row],[15]] -> 0
A11: 5 | F11: =Таблица21339902946781316172122[[#This Row],[ ]] -> 5 | M11: =Таблица21339902946781316172122[[#This Row],[113]]*Таблица21339902946781316172122[[#This Row],[15]] -> 0
A12: 6 | F12: =Таблица21339902946781316172122[[#This Row],[ ]] -> 6 | M12: =Таблица21339902946781316172122[[#This Row],[113]]*Таблица21339902946781316172122[[#This Row],[15]] -> 0
A13: 7 | F13: =Таблица21339902946781316172122[[#This Row],[ ]] -> 7 | M13: =Таблица21339902946781316172122[[#This Row],[113]]*Таблица21339902946781316172122[[#This Row],[15]] -> 0
A14: 8 | F14: =Таблица21339902946781316172122[[#This Row],[ ]] -> 8 | M14: =Таблица21339902946781316172122[[#This Row],[113]]*Таблица21339902946781316172122[[#This Row],[15]] -> 0
A15: 9 | F15: =Таблица21339902946781316172122[[#This Row],[ ]] -> 9 | M15: =Таблица21339902946781316172122[[#This Row],[113]]*Таблица21339902946781316172122[[#This Row],[15]] -> 0
A16: 10 | F16: =Таблица21339902946781316172122[[#This Row],[ ]] -> 10 | M16: =Таблица21339902946781316172122[[#This Row],[113]]*Таблица21339902946781316172122[[#This Row],[15]] -> 0
A17: 11 | F17: =Таблица21339902946781316172122[[#This Row],[ ]] -> 11 | M17: =Таблица21339902946781316172122[[#This Row],[113]]*Таблица21339902946781316172122[[#This Row],[15]] -> 0
A18: 12 | F18: =Таблица21339902946781316172122[[#This Row],[ ]] -> 12 | M18: =Таблица21339902946781316172122[[#This Row],[113]]*Таблица21339902946781316172122[[#This Row],[15]] -> 0
A19: 13 | F19: =Таблица21339902946781316172122[[#This Row],[ ]] -> 13 | M19: =Таблица21339902946781316172122[[#This Row],[113]]*Таблица21339902946781316172122[[#This Row],[15]] -> 0
A20: 14 | F20: =Таблица21339902946781316172122[[#This Row],[ ]] -> 14 | M20: =Таблица21339902946781316172122[[#This Row],[113]]*Таблица21339902946781316172122[[#This Row],[15]] -> 0
... A49: 43 | F49: =Таблица21339902946781316172122[[#This Row],[ ]] -> 43 | M49: =Таблица21339902946781316172122[[#This Row],[113]]*Таблица21339902946781316172122[[#This Row],[15]] -> 0
C50: =SUBTOTAL(109,Таблица21339902946781316172122[2]) -> 104400000 | K50: =SUBTOTAL(109,Таблица21339902946781316172122[1132]) -> 38 | M50: =SUBTOTAL(109,Таблица21339902946781316172122[16]) -> 45964800

Sheet 3-Уктир ога Шовот
D1: 3-Уктир ога Шовот | H1: Клент шопрга барди: | I1: =SUMIFS(C:C,D:D,J1) -> 0 | J1: шопр учун барди
A2: ID-Клиента | F2: =Таблица2133990294678131617212223[[#Totals],[2]]+-Таблица2133990294678131617212223[[#Totals],[16]] -> 40964800
A3: № | B3: Дата | C3: Сумма | D3: Примечание | E3: Возврат паддон | F3: № | G3: Дата | H3: Авто | I3: Размер | J3: Блок Куб | K3: Поддон Шт | L3: От | M3: Сумма
C5: =Таблица2133990294678131617212223[[#Totals],[2]] -> 40964800 | E5: =SUM(Таблица2133990294678131617212223[4]) -> 0 | J5: =SUM(Таблица2133990294678131617212223[113]) -> 0 | K5: =Таблица2133990294678131617212223[[#Totals],[1132]] -> 0 | M5: =Таблица2133990294678131617212223[[#Totals],[16]] -> 0
B6: 1 | C6: 2 | D6: 3 | E6: 4 | F6: 9 | G6: 10 | H6: 11 | I6: 114 | J6: 113 | K6: 1132 | L6: 15 | M6: 16
A7: 1 | B7: 46217 | C7: 40964800 | D7: SHOVOT METOL COMPOSIT mchj | F7: =Таблица2133990294678131617212223[[#This Row],[ ]] -> 1 | M7: =Таблица2133990294678131617212223[[#This Row],[113]]*Таблица2133990294678131617212223[[#This Row],[15]] -> 0
A8: 2 | F8: =Таблица2133990294678131617212223[[#This Row],[ ]] -> 2 | M8: =Таблица2133990294678131617212223[[#This Row],[113]]*Таблица2133990294678131617212223[[#This Row],[15]] -> 0
A9: 3 | F9: =Таблица2133990294678131617212223[[#This Row],[ ]] -> 3 | M9: =Таблица2133990294678131617212223[[#This Row],[113]]*Таблица2133990294678131617212223[[#This Row],[15]] -> 0 | Q9: 3-Уктир ога Шовот
A10: 4 | F10: =Таблица2133990294678131617212223[[#This Row],[ ]] -> 4 | M10: =Таблица2133990294678131617212223[[#This Row],[113]]*Таблица2133990294678131617212223[[#This Row],[15]] -> 0
A11: 5 | F11: =Таблица2133990294678131617212223[[#This Row],[ ]] -> 5 | M11: =Таблица2133990294678131617212223[[#This Row],[113]]*Таблица2133990294678131617212223[[#This Row],[15]] -> 0
A12: 6 | F12: =Таблица2133990294678131617212223[[#This Row],[ ]] -> 6 | M12: =Таблица2133990294678131617212223[[#This Row],[113]]*Таблица2133990294678131617212223[[#This Row],[15]] -> 0
A13: 7 | F13: =Таблица2133990294678131617212223[[#This Row],[ ]] -> 7 | M13: =Таблица2133990294678131617212223[[#This Row],[113]]*Таблица2133990294678131617212223[[#This Row],[15]] -> 0
A14: 8 | F14: =Таблица2133990294678131617212223[[#This Row],[ ]] -> 8 | M14: =Таблица2133990294678131617212223[[#This Row],[113]]*Таблица2133990294678131617212223[[#This Row],[15]] -> 0
A15: 9 | F15: =Таблица2133990294678131617212223[[#This Row],[ ]] -> 9 | M15: =Таблица2133990294678131617212223[[#This Row],[113]]*Таблица2133990294678131617212223[[#This Row],[15]] -> 0
A16: 10 | F16: =Таблица2133990294678131617212223[[#This Row],[ ]] -> 10 | M16: =Таблица2133990294678131617212223[[#This Row],[113]]*Таблица2133990294678131617212223[[#This Row],[15]] -> 0
A17: 11 | F17: =Таблица2133990294678131617212223[[#This Row],[ ]] -> 11 | M17: =Таблица2133990294678131617212223[[#This Row],[113]]*Таблица2133990294678131617212223[[#This Row],[15]] -> 0
A18: 12 | F18: =Таблица2133990294678131617212223[[#This Row],[ ]] -> 12 | M18: =Таблица2133990294678131617212223[[#This Row],[113]]*Таблица2133990294678131617212223[[#This Row],[15]] -> 0
A19: 13 | F19: =Таблица2133990294678131617212223[[#This Row],[ ]] -> 13 | M19: =Таблица2133990294678131617212223[[#This Row],[113]]*Таблица2133990294678131617212223[[#This Row],[15]] -> 0
A20: 14 | F20: =Таблица2133990294678131617212223[[#This Row],[ ]] -> 14 | M20: =Таблица2133990294678131617212223[[#This Row],[113]]*Таблица2133990294678131617212223[[#This Row],[15]] -> 0
A21: 15 | F21: =Таблица2133990294678131617212223[[#This Row],[ ]] -> 15 | M21: =Таблица2133990294678131617212223[[#This Row],[113]]*Таблица2133990294678131617212223[[#This Row],[15]] -> 0
... A49: 43 | F49: =Таблица2133990294678131617212223[[#This Row],[ ]] -> 43 | M49: =Таблица2133990294678131617212223[[#This Row],[113]]*Таблица2133990294678131617212223[[#This Row],[15]] -> 0
C50: =SUBTOTAL(109,Таблица2133990294678131617212223[2]) -> 40964800 | K50: =SUBTOTAL(109,Таблица2133990294678131617212223[1132]) -> 0 | M50: =SUBTOTAL(109,Таблица2133990294678131617212223[16]) -> 0

Sheet 6-накд клент
D1: 6-накд клент | H1: Клент шопрга барди: | I1: =SUMIFS(C:C,D:D,J1) -> 2250000 | J1: шопр учун барди
A2: ID-Клиента | F2: =Таблица213399029467813161721222324[[#Totals],[2]]+-Таблица213399029467813161721222324[[#Totals],[16]] -> -15894000
A3: № | B3: Дата | C3: Сумма | D3: Примечание | E3: Возврат паддон | F3: № | G3: Дата | H3: Авто | I3: Размер | J3: Блок Куб | K3: Поддон Шт | L3: От | M3: Сумма
C5: =Таблица213399029467813161721222324[[#Totals],[2]] -> 2250000 | E5: =SUM(Таблица213399029467813161721222324[4]) -> 0 | J5: =SUM(Таблица213399029467813161721222324[113]) -> 25.92 | K5: =Таблица213399029467813161721222324[[#Totals],[1132]] -> 15 | M5: =Таблица213399029467813161721222324[[#Totals],[16]] -> 18144000
B6: 1 | C6: 2 | D6: 3 | E6: 4 | F6: 9 | G6: 10 | H6: 11 | I6: 114 | J6: 113 | K6: 1132 | L6: 15 | M6: 16
A7: 1 | B7: 46216 | C7: 2250000 | D7: шопр учун барди | F7: =Таблица213399029467813161721222324[[#This Row],[ ]] -> 1 | G7: 46216 | H7: 90 699 EBA | I7: 600x300x200 | J7: 25.92 | K7: 15 | L7: 700000 | M7: =Таблица213399029467813161721222324[[#This Row],[113]]*Таблица213399029467813161721222324[[#This Row],[15]] -> 18144000
A8: 2 | F8: =Таблица213399029467813161721222324[[#This Row],[ ]] -> 2 | M8: =Таблица213399029467813161721222324[[#This Row],[113]]*Таблица213399029467813161721222324[[#This Row],[15]] -> 0
A9: 3 | F9: =Таблица213399029467813161721222324[[#This Row],[ ]] -> 3 | M9: =Таблица213399029467813161721222324[[#This Row],[113]]*Таблица213399029467813161721222324[[#This Row],[15]] -> 0
A10: 4 | F10: =Таблица213399029467813161721222324[[#This Row],[ ]] -> 4 | M10: =Таблица213399029467813161721222324[[#This Row],[113]]*Таблица213399029467813161721222324[[#This Row],[15]] -> 0
A11: 5 | F11: =Таблица213399029467813161721222324[[#This Row],[ ]] -> 5 | M11: =Таблица213399029467813161721222324[[#This Row],[113]]*Таблица213399029467813161721222324[[#This Row],[15]] -> 0
A12: 6 | F12: =Таблица213399029467813161721222324[[#This Row],[ ]] -> 6 | M12: =Таблица213399029467813161721222324[[#This Row],[113]]*Таблица213399029467813161721222324[[#This Row],[15]] -> 0
A13: 7 | F13: =Таблица213399029467813161721222324[[#This Row],[ ]] -> 7 | M13: =Таблица213399029467813161721222324[[#This Row],[113]]*Таблица213399029467813161721222324[[#This Row],[15]] -> 0
A14: 8 | F14: =Таблица213399029467813161721222324[[#This Row],[ ]] -> 8 | M14: =Таблица213399029467813161721222324[[#This Row],[113]]*Таблица213399029467813161721222324[[#This Row],[15]] -> 0
A15: 9 | F15: =Таблица213399029467813161721222324[[#This Row],[ ]] -> 9 | M15: =Таблица213399029467813161721222324[[#This Row],[113]]*Таблица213399029467813161721222324[[#This Row],[15]] -> 0
A16: 10 | F16: =Таблица213399029467813161721222324[[#This Row],[ ]] -> 10 | M16: =Таблица213399029467813161721222324[[#This Row],[113]]*Таблица213399029467813161721222324[[#This Row],[15]] -> 0
A17: 11 | F17: =Таблица213399029467813161721222324[[#This Row],[ ]] -> 11 | M17: =Таблица213399029467813161721222324[[#This Row],[113]]*Таблица213399029467813161721222324[[#This Row],[15]] -> 0
A18: 12 | F18: =Таблица213399029467813161721222324[[#This Row],[ ]] -> 12 | M18: =Таблица213399029467813161721222324[[#This Row],[113]]*Таблица213399029467813161721222324[[#This Row],[15]] -> 0
A19: 13 | F19: =Таблица213399029467813161721222324[[#This Row],[ ]] -> 13 | M19: =Таблица213399029467813161721222324[[#This Row],[113]]*Таблица213399029467813161721222324[[#This Row],[15]] -> 0
... A49: 43 | F49: =Таблица213399029467813161721222324[[#This Row],[ ]] -> 43 | M49: =Таблица213399029467813161721222324[[#This Row],[113]]*Таблица213399029467813161721222324[[#This Row],[15]] -> 0
C50: =SUBTOTAL(109,Таблица213399029467813161721222324[2]) -> 2250000 | K50: =SUBTOTAL(109,Таблица213399029467813161721222324[1132]) -> 15 | M50: =SUBTOTAL(109,Таблица213399029467813161721222324[16]) -> 18144000

Sheet 0 (6)
D1: 0 | H1: Клент шопрга барди: | I1: =SUMIFS(C:C,D:D,J1) -> 0 | J1: шопр учун барди
A2: ID-Клиента | F2: =Таблица21339902946781316172122232425[[#Totals],[2]]+-Таблица21339902946781316172122232425[[#Totals],[16]] -> 0
A3: № | B3: Дата | C3: Сумма | D3: Примечание | E3: Возврат паддон | F3: № | G3: Дата | H3: Авто | I3: Размер | J3: Блок Куб | K3: Поддон Шт | L3: От | M3: Сумма
C5: =Таблица21339902946781316172122232425[[#Totals],[2]] -> 0 | E5: =SUM(Таблица21339902946781316172122232425[4]) -> 0 | J5: =SUM(Таблица21339902946781316172122232425[113]) -> 0 | K5: =Таблица21339902946781316172122232425[[#Totals],[1132]] -> 0 | M5: =Таблица21339902946781316172122232425[[#Totals],[16]] -> 0
B6: 1 | C6: 2 | D6: 3 | E6: 4 | F6: 9 | G6: 10 | H6: 11 | I6: 114 | J6: 113 | K6: 1132 | L6: 15 | M6: 16
A7: 1 | F7: =Таблица21339902946781316172122232425[[#This Row],[ ]] -> 1 | M7: =Таблица21339902946781316172122232425[[#This Row],[113]]*Таблица21339902946781316172122232425[[#This Row],[15]] -> 0
A8: 2 | F8: =Таблица21339902946781316172122232425[[#This Row],[ ]] -> 2 | M8: =Таблица21339902946781316172122232425[[#This Row],[113]]*Таблица21339902946781316172122232425[[#This Row],[15]] -> 0
A9: 3 | F9: =Таблица21339902946781316172122232425[[#This Row],[ ]] -> 3 | M9: =Таблица21339902946781316172122232425[[#This Row],[113]]*Таблица21339902946781316172122232425[[#This Row],[15]] -> 0
A10: 4 | F10: =Таблица21339902946781316172122232425[[#This Row],[ ]] -> 4 | M10: =Таблица21339902946781316172122232425[[#This Row],[113]]*Таблица21339902946781316172122232425[[#This Row],[15]] -> 0
A11: 5 | F11: =Таблица21339902946781316172122232425[[#This Row],[ ]] -> 5 | M11: =Таблица21339902946781316172122232425[[#This Row],[113]]*Таблица21339902946781316172122232425[[#This Row],[15]] -> 0
A12: 6 | F12: =Таблица21339902946781316172122232425[[#This Row],[ ]] -> 6 | M12: =Таблица21339902946781316172122232425[[#This Row],[113]]*Таблица21339902946781316172122232425[[#This Row],[15]] -> 0
A13: 7 | F13: =Таблица21339902946781316172122232425[[#This Row],[ ]] -> 7 | M13: =Таблица21339902946781316172122232425[[#This Row],[113]]*Таблица21339902946781316172122232425[[#This Row],[15]] -> 0
A14: 8 | F14: =Таблица21339902946781316172122232425[[#This Row],[ ]] -> 8 | M14: =Таблица21339902946781316172122232425[[#This Row],[113]]*Таблица21339902946781316172122232425[[#This Row],[15]] -> 0
A15: 9 | F15: =Таблица21339902946781316172122232425[[#This Row],[ ]] -> 9 | M15: =Таблица21339902946781316172122232425[[#This Row],[113]]*Таблица21339902946781316172122232425[[#This Row],[15]] -> 0
A16: 10 | F16: =Таблица21339902946781316172122232425[[#This Row],[ ]] -> 10 | M16: =Таблица21339902946781316172122232425[[#This Row],[113]]*Таблица21339902946781316172122232425[[#This Row],[15]] -> 0
A17: 11 | F17: =Таблица21339902946781316172122232425[[#This Row],[ ]] -> 11 | M17: =Таблица21339902946781316172122232425[[#This Row],[113]]*Таблица21339902946781316172122232425[[#This Row],[15]] -> 0
A18: 12 | F18: =Таблица21339902946781316172122232425[[#This Row],[ ]] -> 12 | M18: =Таблица21339902946781316172122232425[[#This Row],[113]]*Таблица21339902946781316172122232425[[#This Row],[15]] -> 0
... A49: 43 | F49: =Таблица21339902946781316172122232425[[#This Row],[ ]] -> 43 | M49: =Таблица21339902946781316172122232425[[#This Row],[113]]*Таблица21339902946781316172122232425[[#This Row],[15]] -> 0
C50: =SUBTOTAL(109,Таблица21339902946781316172122232425[2]) -> 0 | K50: =SUBTOTAL(109,Таблица21339902946781316172122232425[1132]) -> 0 | M50: =SUBTOTAL(109,Таблица21339902946781316172122232425[16]) -> 0
